{
  "month": "2025-12",
  "items": [
    {
      "id": "3553410",
      "title": "نقطة تحول في ريال مدريد !",
      "link": "https://hihi2.com/2025/12/11/p3553410.html",
      "pubDate": "2025-12-11T06:32:40.000Z",
      "summary": "هاي كورة – أشارت صحيفة آس الإسبانية إلى أنه بالرغم من هزيمة ريال مدريد بثنائية لهدف أمام مانشستر سيتي في دوري الأبطال إلا أن ذلك لم يمنع لاعبي الريال من دعم تشابي ألونسو . مظاهر الدعم بدت في العديد من اللقطات مثل معانقة رودريغو له بعد التسجيل ، وتصريحات كورتوا ، اسينسيو وبيلينغهام ، الذين […]",
      "description": "<div class=\"wp-block-image\">\n<figure class=\"aligncenter size-full\"><img fetchpriority=\"high\" decoding=\"async\" width=\"500\" height=\"250\" src=\"https://sc5.hihi2.com/wp-content/uploads/2025/12/hihi2-2025-12-11_05-15-02_291620.jpg\" alt=\"\" class=\"wp-image-3553286\" srcset=\"https://sc3.hihi2.com/wp-content/uploads/2025/12/hihi2-2025-12-11_05-15-02_291620.jpg?v=1765419302 500w, https://hihi2.com/wp-content/uploads/2025/12/hihi2-2025-12-11_05-15-02_291620-300x150.jpg?v=1765419302 300w, https://hihi2.com/wp-content/uploads/2025/12/hihi2-2025-12-11_05-15-02_291620-200x100.jpg?v=1765419302 200w\" sizes=\"(max-width: 500px) 100vw, 500px\" /></figure>\n</div>\n\n\n<p></p>\n\n\n\n<p>هاي كورة &#8211; أشارت صحيفة آس الإسبانية إلى أنه بالرغم من هزيمة ريال مدريد بثنائية لهدف أمام مانشستر سيتي في دوري الأبطال إلا أن ذلك لم يمنع لاعبي الريال من دعم تشابي ألونسو .</p>\n\n\n\n<p>مظاهر الدعم بدت في العديد من اللقطات مثل معانقة رودريغو له بعد التسجيل ، وتصريحات كورتوا ، اسينسيو وبيلينغهام ، الذين أكدوا على ثقتهم الكاملة في الإسباني وبأن هناك مجاال للتطور وإصلاح الأخطاء في ما هو قادم .</p>\n\n\n\n<p>اللاعبون باتوا أكثر تحملا للمسؤولية ، وهو ما قد يغير الصورة في المباريات المقبلة .</p>\n",
      "image": "https://sc5.hihi2.com/wp-content/uploads/2025/12/hihi2-2025-12-11_05-15-02_291620.jpg",
      "categories": [
        "أخبار ريال مدريد",
        "الريال",
        "الونسو",
        "رودريغو",
        "ريال مدريد"
      ]
    },
    {
      "id": "3553402",
      "title": "أرقام شرقي أمام الريال",
      "link": "https://hihi2.com/2025/12/11/p3553402.html",
      "pubDate": "2025-12-11T06:31:40.000Z",
      "summary": "هاي كورة _ شارك النجم ريان شرقي أساسيًا أمام ريال مدريد، ونال تقييمًا مرتفعًا بلغ 7.0. إليكم أبرز أرقام شرقي في هذه المباراة: لعب: 71 دقيقة. التسديدات على المرمى: 2. لمس الكرة: 56. المراوغات الناجحة: 1. التمريرات المفتاحية: 2. التمريرات: 38 منها 34 صحيحة. دقة التمرير: 89%. استرجاع الكرة: 3. المواجهات الثنائية الناجحة: 3.",
      "description": "<div class=\"wp-block-image\">\n<figure class=\"aligncenter size-large\"><img decoding=\"async\" width=\"640\" height=\"536\" src=\"https://sc2.hihi2.com/wp-content/uploads/2025/12/hihi2-2025-12-11_09-26-35_032070-640x536.jpg?v=1765434395\" alt=\"\" class=\"wp-image-3553407\" srcset=\"https://sc1.hihi2.com/wp-content/uploads/2025/12/hihi2-2025-12-11_09-26-35_032070-640x536.jpg?v=1765434395 640w, https://hihi2.com/wp-content/uploads/2025/12/hihi2-2025-12-11_09-26-35_032070-300x251.jpg?v=1765434395 300w, https://hihi2.com/wp-content/uploads/2025/12/hihi2-2025-12-11_09-26-35_032070-200x168.jpg?v=1765434395 200w, https://hihi2.com/wp-content/uploads/2025/12/hihi2-2025-12-11_09-26-35_032070-768x644.jpg?v=1765434395 768w, https://hihi2.com/wp-content/uploads/2025/12/hihi2-2025-12-11_09-26-35_032070.jpg?v=1765434395 859w\" sizes=\"(max-width: 640px) 100vw, 640px\" /></figure>\n</div>\n\n\n<p>هاي كورة _ شارك النجم ريان شرقي أساسيًا أمام ريال مدريد، ونال تقييمًا مرتفعًا بلغ 7.0.</p>\n\n\n\n<p>إليكم أبرز أرقام شرقي في هذه المباراة:</p>\n\n\n\n<p>لعب: 71 دقيقة.</p>\n\n\n\n<p>التسديدات على المرمى: 2.</p>\n\n\n\n<p>لمس الكرة: 56.</p>\n\n\n\n<p>المراوغات الناجحة: 1.</p>\n\n\n\n<p>التمريرات المفتاحية: 2.</p>\n\n\n\n<p>التمريرات: 38 منها 34 صحيحة.</p>\n\n\n\n<p>دقة التمرير: 89%.</p>\n\n\n\n<p>استرجاع الكرة: 3.</p>\n\n\n\n<p>المواجهات الثنائية الناجحة: 3.</p>\n\n\n<div class=\"wp-block-image\">\n<figure class=\"aligncenter size-full\"><img decoding=\"async\" width=\"636\" height=\"449\" src=\"https://sc4.hihi2.com/wp-content/uploads/2025/12/hihi2-2025-12-11_09-30-14_850970.jpg?v=1765434614\" alt=\"\" class=\"wp-image-3553411\" srcset=\"https://sc5.hihi2.com/wp-content/uploads/2025/12/hihi2-2025-12-11_09-30-14_850970.jpg?v=1765434614 636w, https://hihi2.com/wp-content/uploads/2025/12/hihi2-2025-12-11_09-30-14_850970-300x212.jpg?v=1765434614 300w, https://hihi2.com/wp-content/uploads/2025/12/hihi2-2025-12-11_09-30-14_850970-200x141.jpg?v=1765434614 200w\" sizes=\"(max-width: 636px) 100vw, 636px\" /></figure>\n</div>",
      "image": "https://sc2.hihi2.com/wp-content/uploads/2025/12/hihi2-2025-12-11_09-26-35_032070-640x536.jpg?v=1765434395",
      "categories": [
        "أخبار دوري أبطال أوروبا",
        "أخبار ريال مدريد",
        "أخبار مانشستر سيتي",
        "أرقام شرقي",
        "دوري أبطال أوروبا",
        "ريال مدريد",
        "ريان شرقي",
        "مانشستر سيتي"
      ]
    },
    {
      "id": "3553405",
      "title": "هل تؤثر تصريحات رينارد على ملف الأجانب في دوري روشن ؟",
      "link": "https://hihi2.com/2025/12/11/p3553405.html",
      "pubDate": "2025-12-11T06:30:19.000Z",
      "summary": "هاي كورة – سلط الإعلامي الرياضي وليد الفراج الضوء على التصريحات المتكررة للفرنسي هيرفي رينارد ، المدير الفني للمنتخب السعودي ، بشأن ضعف مشاركة اللاعبين المحليين في دوري روشن . أكد الفراج أن استمرار هذا الأمر قد يؤدي إلى تراجع مستوى الأخضر ، إذ قال : ” ‏كلام رينارد المتكرر عن ضعف مشاركة اللاعب السعودي […]",
      "description": "\n<figure class=\"wp-block-image size-large\"><img loading=\"lazy\" decoding=\"async\" width=\"640\" height=\"361\" src=\"https://sc2.hihi2.com/wp-content/uploads/2025/12/hihi2-2025-12-11_09-26-07_266072-640x361.jpg\" alt=\"\" class=\"wp-image-3553406\" srcset=\"https://sc3.hihi2.com/wp-content/uploads/2025/12/hihi2-2025-12-11_09-26-07_266072-640x361.jpg?v=1765434367 640w, https://hihi2.com/wp-content/uploads/2025/12/hihi2-2025-12-11_09-26-07_266072-300x169.jpg?v=1765434367 300w, https://hihi2.com/wp-content/uploads/2025/12/hihi2-2025-12-11_09-26-07_266072-200x113.jpg?v=1765434367 200w, https://hihi2.com/wp-content/uploads/2025/12/hihi2-2025-12-11_09-26-07_266072.jpg?v=1765434367 678w\" sizes=\"auto, (max-width: 640px) 100vw, 640px\" /></figure>\n\n\n\n<p>هاي كورة &#8211; سلط الإعلامي الرياضي وليد الفراج الضوء على التصريحات المتكررة للفرنسي هيرفي رينارد ، المدير الفني للمنتخب السعودي ، بشأن ضعف مشاركة اللاعبين المحليين في دوري روشن .</p>\n\n\n\n<p>أكد الفراج أن استمرار هذا الأمر قد يؤدي إلى تراجع مستوى الأخضر ، إذ قال : &#8221; ‏كلام رينارد المتكرر عن ضعف مشاركة اللاعب السعودي في الدوري وانعكاسها الخطير على المنتخب الأول . </p>\n\n\n\n<p>&#8221; ومشاهدتنا لأثر دوريات عربية أقل فنيًا من روشن على منتخباتها في المغرب والأردن وسوريا ودول آسيوية صاعدة مثل أوزباكستان . أعتقد حان الوقت لنقاش أثر عدد الأجانب .. لا مخرج مستدام &#8221; .</p>\n",
      "image": "https://sc2.hihi2.com/wp-content/uploads/2025/12/hihi2-2025-12-11_09-26-07_266072-640x361.jpg",
      "categories": [
        "أخبار المنتخب السعودي",
        "المنتخب السعودي",
        "دوري روشن",
        "هيرفي رينارد"
      ]
    },
    {
      "id": "3553395",
      "title": "إحصائيات هالاند أمام الريال",
      "link": "https://hihi2.com/2025/12/11/p3553395.html",
      "pubDate": "2025-12-11T06:23:56.000Z",
      "summary": "هاي كورة _ شارك النجم إيرلينغ هالاند أساسيًا أمام ريال مدريد، ونال تقييمًا مرتفعًا بلغ 7.1. إليكم أبرز أرقام هالاند في هذه المباراة: لعب: 70 دقيقة. الأهداف: 1. التسديدات على المرمى: 3. لمس الكرة: 13. التمريرات: 5 منها 3 صحيحة. دقة التمرير: 60%. المواجهات الثنائية الناجحة: 2.",
      "description": "<div class=\"wp-block-image\">\n<figure class=\"aligncenter size-large\"><img loading=\"lazy\" decoding=\"async\" width=\"640\" height=\"514\" src=\"https://sc1.hihi2.com/wp-content/uploads/2025/12/hihi2-2025-12-11_09-19-18_492694-640x514.jpg?v=1765433958\" alt=\"\" class=\"wp-image-3553397\" srcset=\"https://sc3.hihi2.com/wp-content/uploads/2025/12/hihi2-2025-12-11_09-19-18_492694-640x514.jpg?v=1765433958 640w, https://hihi2.com/wp-content/uploads/2025/12/hihi2-2025-12-11_09-19-18_492694-300x241.jpg?v=1765433958 300w, https://hihi2.com/wp-content/uploads/2025/12/hihi2-2025-12-11_09-19-18_492694-200x161.jpg?v=1765433958 200w, https://hihi2.com/wp-content/uploads/2025/12/hihi2-2025-12-11_09-19-18_492694-768x616.jpg?v=1765433958 768w, https://hihi2.com/wp-content/uploads/2025/12/hihi2-2025-12-11_09-19-18_492694.jpg?v=1765433958 897w\" sizes=\"auto, (max-width: 640px) 100vw, 640px\" /></figure>\n</div>\n\n\n<p>هاي كورة _ شارك النجم إيرلينغ هالاند أساسيًا أمام ريال مدريد، ونال تقييمًا مرتفعًا بلغ 7.1.</p>\n\n\n\n<p>إليكم أبرز أرقام هالاند في هذه المباراة:</p>\n\n\n\n<p>لعب: 70 دقيقة.</p>\n\n\n\n<p>الأهداف: 1.</p>\n\n\n\n<p>التسديدات على المرمى: 3.</p>\n\n\n\n<p>لمس الكرة: 13.</p>\n\n\n\n<p>التمريرات: 5 منها 3 صحيحة.</p>\n\n\n\n<p>دقة التمرير: 60%.</p>\n\n\n\n<p>المواجهات الثنائية الناجحة: 2.</p>\n\n\n\n<blockquote class=\"wp-block-quote is-layout-flow wp-block-quote-is-layout-flow\"><div class=\"wp-block-image\">\n<figure class=\"aligncenter size-large\"><img loading=\"lazy\" decoding=\"async\" width=\"640\" height=\"443\" src=\"https://sc2.hihi2.com/wp-content/uploads/2025/12/hihi2-2025-12-11_09-22-33_619266-640x443.jpg?v=1765434153\" alt=\"\" class=\"wp-image-3553398\" srcset=\"https://sc2.hihi2.com/wp-content/uploads/2025/12/hihi2-2025-12-11_09-22-33_619266-640x443.jpg?v=1765434153 640w, https://hihi2.com/wp-content/uploads/2025/12/hihi2-2025-12-11_09-22-33_619266-300x208.jpg?v=1765434153 300w, https://hihi2.com/wp-content/uploads/2025/12/hihi2-2025-12-11_09-22-33_619266-200x138.jpg?v=1765434153 200w, https://hihi2.com/wp-content/uploads/2025/12/hihi2-2025-12-11_09-22-33_619266.jpg?v=1765434153 647w\" sizes=\"auto, (max-width: 640px) 100vw, 640px\" /></figure>\n</div></blockquote>\n",
      "image": "https://sc1.hihi2.com/wp-content/uploads/2025/12/hihi2-2025-12-11_09-19-18_492694-640x514.jpg?v=1765433958",
      "categories": [
        "أخبار دوري أبطال أوروبا",
        "أخبار ريال مدريد",
        "أخبار مانشستر سيتي",
        "أرقام هالاند",
        "إيرلينغ هالاند",
        "دوري أبطال أوروبا",
        "ريال مدريد",
        "مانشستر سيتي"
      ]
    },
    {
      "id": "3553392",
      "title": "الاتحاد يحدد مارس موعدًا محتملًا لعودة مدافعه",
      "link": "https://hihi2.com/2025/12/11/p3553392.html",
      "pubDate": "2025-12-11T06:23:18.000Z",
      "summary": "هاي كورة – اعتمد الجهاز الطبي لنادي الاتحاد خطة علاجية وتأهيلية متكاملة لمدافع الفريق ، سعد آل موسى ، بعد نجاح العملية الجراحية التي أجريت له في إنجلترا تحت إشراف الطبيب بيتر أدوجهي ، بحسب ما ذكرته تقارير صحفية . البرنامج المخصص للمدافع الاتحادي يشمل ما يلي : -تمارين علاج طبيعي . -تمارين تأهيلية ميداني […]",
      "description": "\n<figure class=\"wp-block-image size-large\"><img loading=\"lazy\" decoding=\"async\" width=\"640\" height=\"331\" src=\"https://sc2.hihi2.com/wp-content/uploads/2025/12/hihi2-2025-12-11_09-16-41_339306-640x331.jpg\" alt=\"\" class=\"wp-image-3553394\" srcset=\"https://sc4.hihi2.com/wp-content/uploads/2025/12/hihi2-2025-12-11_09-16-41_339306-640x331.jpg?v=1765433801 640w, https://hihi2.com/wp-content/uploads/2025/12/hihi2-2025-12-11_09-16-41_339306-300x155.jpg?v=1765433801 300w, https://hihi2.com/wp-content/uploads/2025/12/hihi2-2025-12-11_09-16-41_339306-200x104.jpg?v=1765433801 200w, https://hihi2.com/wp-content/uploads/2025/12/hihi2-2025-12-11_09-16-41_339306-768x398.jpg?v=1765433801 768w, https://hihi2.com/wp-content/uploads/2025/12/hihi2-2025-12-11_09-16-41_339306.jpg?v=1765433801 1002w\" sizes=\"auto, (max-width: 640px) 100vw, 640px\" /></figure>\n\n\n\n<p>هاي كورة &#8211; اعتمد الجهاز الطبي لنادي الاتحاد خطة علاجية وتأهيلية متكاملة لمدافع الفريق ، سعد آل موسى ، بعد نجاح العملية الجراحية التي أجريت له في إنجلترا تحت إشراف الطبيب بيتر أدوجهي ، بحسب ما ذكرته تقارير صحفية .</p>\n\n\n\n<p>البرنامج المخصص للمدافع الاتحادي يشمل <mark style=\"background-color:rgba(0, 0, 0, 0)\" class=\"has-inline-color has-vivid-red-color\"><strong>ما يلي :</strong></mark></p>\n\n\n\n<p>-تمارين علاج طبيعي .</p>\n\n\n\n<p>-تمارين تأهيلية ميداني .</p>\n\n\n\n<p>-متابعة يومية لتقييم التحسن .</p>\n\n\n\n<p>-إمكانية تعديل الجدول الزمني لتقصير فترة التعافي إذا أظهرت حالته تقدمًا أسرع .</p>\n\n\n\n<p>من المتوقع أن تمتد خطة تأهيل المدافع ، البالغ من العمر 23 عامًا ، حتى مارس المقبل ، مع احتمال عودة سعد آل موسى قبل الموعد المحدد .</p>\n",
      "image": "https://sc2.hihi2.com/wp-content/uploads/2025/12/hihi2-2025-12-11_09-16-41_339306-640x331.jpg",
      "categories": [
        "أخبار الاتحاد السعودي",
        "الاتحاد",
        "دوري روشن",
        "سعد آل موسى"
      ]
    },
    {
      "id": "3553404",
      "title": "ريال مدريد .. الأكثر تضررا من ” ريمونتادا ” برشلونة !",
      "link": "https://hihi2.com/2025/12/11/p3553404.html",
      "pubDate": "2025-12-11T06:20:00.000Z",
      "summary": "هاي كورة – بات فريق برشلونة يحمل لقب ” لاعبي الريمونتادا ” تحت قيادة هانز فليك حيث كانت العودة أمام اينتراخت فرانكفورت هي السادسة عشر للبارسا مع الألماني . الفريق الكتالوني عاد بنتائج مبارياته تسع مرات في الموسم الماضي وسبع في الحالي حتى الآن . ريال مدريد يعد الفريق الأكثر عرضة لريمونتادا البلوغرانا ، وذلك […]",
      "description": "<div class=\"wp-block-image\">\n<figure class=\"aligncenter size-full\"><img loading=\"lazy\" decoding=\"async\" width=\"538\" height=\"300\" src=\"https://sc2.hihi2.com/wp-content/uploads/2025/12/hihi2-2025-12-11_09-27-29_143417.png?v=1765434449\" alt=\"\" class=\"wp-image-3553408\" srcset=\"https://sc1.hihi2.com/wp-content/uploads/2025/12/hihi2-2025-12-11_09-27-29_143417.png?v=1765434449 538w, https://hihi2.com/wp-content/uploads/2025/12/hihi2-2025-12-11_09-27-29_143417-300x167.png?v=1765434449 300w, https://hihi2.com/wp-content/uploads/2025/12/hihi2-2025-12-11_09-27-29_143417-200x112.png?v=1765434449 200w\" sizes=\"auto, (max-width: 538px) 100vw, 538px\" /></figure>\n</div>\n\n\n<p></p>\n\n\n\n<p>هاي كورة &#8211; بات فريق برشلونة يحمل لقب &#8221; لاعبي الريمونتادا &#8221; تحت قيادة هانز فليك حيث كانت العودة أمام اينتراخت فرانكفورت هي السادسة عشر للبارسا مع الألماني .</p>\n\n\n\n<p>الفريق الكتالوني عاد بنتائج مبارياته تسع مرات في الموسم الماضي وسبع في الحالي حتى الآن .</p>\n\n\n\n<p>ريال مدريد يعد الفريق الأكثر عرضة لريمونتادا البلوغرانا ، وذلك في ثلاث مباريات جمعت بين الفريقين وشهدت تقدم الريال ثم فوز برشلونة .</p>\n",
      "image": "https://sc2.hihi2.com/wp-content/uploads/2025/12/hihi2-2025-12-11_09-27-29_143417.png?v=1765434449",
      "categories": [
        "أخبار برشلونة",
        "أخبار ريال مدريد",
        "برشلونة",
        "ريال مدريد",
        "فليك"
      ]
    },
    {
      "id": "3553386",
      "title": "عين على تشواميني في مباراة السيتي",
      "link": "https://hihi2.com/2025/12/11/p3553386.html",
      "pubDate": "2025-12-11T06:15:35.000Z",
      "summary": "هاي كورة _ شارك النجم أوريلين تشواميني أساسيًا أمام مانشستر سيتي، ونال تقييمًا متوسطًا بلغ 6.7. إليكم أبرز أرقام تشواميني في هذه المباراة: لعب: 90 دقيقة. التمريرات: 58 منها 54 صحيحة. دقة التمرير: 93%. التسديدات: 1. لمس الكرة: 68. اعتراضات: 1. استخلاص الكرة: 2. اعتراض تسديدات: 2. استرجاع الكرة: 4. المواجهات الثنائية الناجحة: 3.",
      "description": "<div class=\"wp-block-image\">\n<figure class=\"aligncenter size-large\"><img loading=\"lazy\" decoding=\"async\" width=\"640\" height=\"528\" src=\"https://sc3.hihi2.com/wp-content/uploads/2025/12/hihi2-2025-12-11_09-10-22_728273-640x528.jpg?v=1765433422\" alt=\"\" class=\"wp-image-3553388\" srcset=\"https://sc5.hihi2.com/wp-content/uploads/2025/12/hihi2-2025-12-11_09-10-22_728273-640x528.jpg?v=1765433422 640w, https://hihi2.com/wp-content/uploads/2025/12/hihi2-2025-12-11_09-10-22_728273-300x247.jpg?v=1765433422 300w, https://hihi2.com/wp-content/uploads/2025/12/hihi2-2025-12-11_09-10-22_728273-200x165.jpg?v=1765433422 200w, https://hihi2.com/wp-content/uploads/2025/12/hihi2-2025-12-11_09-10-22_728273-768x633.jpg?v=1765433422 768w, https://hihi2.com/wp-content/uploads/2025/12/hihi2-2025-12-11_09-10-22_728273.jpg?v=1765433422 873w\" sizes=\"auto, (max-width: 640px) 100vw, 640px\" /></figure>\n</div>\n\n\n<p>هاي كورة _ شارك النجم أوريلين تشواميني أساسيًا أمام مانشستر سيتي، ونال تقييمًا متوسطًا بلغ 6.7.</p>\n\n\n\n<p>إليكم أبرز أرقام تشواميني في هذه المباراة:</p>\n\n\n\n<p>لعب: 90 دقيقة.</p>\n\n\n\n<p>التمريرات: 58 منها 54 صحيحة.</p>\n\n\n\n<p>دقة التمرير: 93%.</p>\n\n\n\n<p>التسديدات: 1.</p>\n\n\n\n<p>لمس الكرة: 68.</p>\n\n\n\n<p>اعتراضات: 1.</p>\n\n\n\n<p>استخلاص الكرة: 2.</p>\n\n\n\n<p>اعتراض تسديدات: 2.</p>\n\n\n\n<p>استرجاع الكرة: 4.</p>\n\n\n\n<p>المواجهات الثنائية الناجحة: 3.</p>\n\n\n\n<blockquote class=\"wp-block-quote is-layout-flow wp-block-quote-is-layout-flow\"><div class=\"wp-block-image\">\n<figure class=\"aligncenter size-large\"><img loading=\"lazy\" decoding=\"async\" width=\"640\" height=\"446\" src=\"https://sc4.hihi2.com/wp-content/uploads/2025/12/hihi2-2025-12-11_09-13-55_457630-640x446.jpg?v=1765433635\" alt=\"\" class=\"wp-image-3553389\" srcset=\"https://sc4.hihi2.com/wp-content/uploads/2025/12/hihi2-2025-12-11_09-13-55_457630-640x446.jpg?v=1765433635 640w, https://hihi2.com/wp-content/uploads/2025/12/hihi2-2025-12-11_09-13-55_457630-300x209.jpg?v=1765433635 300w, https://hihi2.com/wp-content/uploads/2025/12/hihi2-2025-12-11_09-13-55_457630-200x139.jpg?v=1765433635 200w, https://hihi2.com/wp-content/uploads/2025/12/hihi2-2025-12-11_09-13-55_457630.jpg?v=1765433635 645w\" sizes=\"auto, (max-width: 640px) 100vw, 640px\" /></figure>\n</div></blockquote>\n",
      "image": "https://sc3.hihi2.com/wp-content/uploads/2025/12/hihi2-2025-12-11_09-10-22_728273-640x528.jpg?v=1765433422",
      "categories": [
        "أخبار دوري أبطال أوروبا",
        "أخبار ريال مدريد",
        "أخبار مانشستر سيتي",
        "أرقام تشواميني",
        "أوريلين تشواميني",
        "دوري أبطال أوروبا",
        "ريال مدريد",
        "مانشستر سيتي"
      ]
    },
    {
      "id": "3553376",
      "title": "أرقام بيلينغهام أمام السيتي",
      "link": "https://hihi2.com/2025/12/11/p3553376.html",
      "pubDate": "2025-12-11T06:06:23.000Z",
      "summary": "هاي كورة _ شارك النجم جود بيلينغهام أساسيًا أمام مانشستر سيتي، ونال تقييمًا مرتفعًا بلغ 7.3. إليكم أبرز أرقام بيلينغهام في هذه المباراة: لعب: 90 دقيقة. التمريرات الحاسمة: 1. التمريرات المفتاحية: 3. التمريرات: 36 منها 29 صحيحة. دقة التمرير: 81%. الكرات الطويلة الناجحة: 5. التسديدات: 3. لمس الكرة: 52. المراوغات الناجحة: 2. استخلاص الكرة: 2. […]",
      "description": "<div class=\"wp-block-image\">\n<figure class=\"aligncenter size-large\"><img loading=\"lazy\" decoding=\"async\" width=\"640\" height=\"504\" src=\"https://sc1.hihi2.com/wp-content/uploads/2025/12/hihi2-2025-12-11_09-00-48_718843-640x504.jpg?v=1765432848\" alt=\"\" class=\"wp-image-3553380\" srcset=\"https://sc3.hihi2.com/wp-content/uploads/2025/12/hihi2-2025-12-11_09-00-48_718843-640x504.jpg?v=1765432848 640w, https://hihi2.com/wp-content/uploads/2025/12/hihi2-2025-12-11_09-00-48_718843-300x236.jpg?v=1765432848 300w, https://hihi2.com/wp-content/uploads/2025/12/hihi2-2025-12-11_09-00-48_718843-200x157.jpg?v=1765432848 200w, https://hihi2.com/wp-content/uploads/2025/12/hihi2-2025-12-11_09-00-48_718843-768x604.jpg?v=1765432848 768w, https://hihi2.com/wp-content/uploads/2025/12/hihi2-2025-12-11_09-00-48_718843.jpg?v=1765432848 915w\" sizes=\"auto, (max-width: 640px) 100vw, 640px\" /></figure>\n</div>\n\n\n<p>هاي كورة _ شارك النجم جود بيلينغهام أساسيًا أمام مانشستر سيتي، ونال تقييمًا مرتفعًا بلغ 7.3.</p>\n\n\n\n<p>إليكم أبرز أرقام بيلينغهام في هذه المباراة:</p>\n\n\n\n<p>لعب: 90 دقيقة.</p>\n\n\n\n<p>التمريرات الحاسمة: 1.</p>\n\n\n\n<p>التمريرات المفتاحية: 3.</p>\n\n\n\n<p>التمريرات: 36 منها 29 صحيحة.</p>\n\n\n\n<p>دقة التمرير: 81%.</p>\n\n\n\n<p>الكرات الطويلة الناجحة: 5.</p>\n\n\n\n<p>التسديدات: 3.</p>\n\n\n\n<p>لمس الكرة: 52.</p>\n\n\n\n<p>المراوغات الناجحة: 2.</p>\n\n\n\n<p>استخلاص الكرة: 2.</p>\n\n\n\n<p>استرجاع الكرة: 3.</p>\n\n\n\n<p>المواجهات الثنائية الناجحة: 9.</p>\n\n\n<div class=\"wp-block-image\">\n<figure class=\"aligncenter size-large\"><img loading=\"lazy\" decoding=\"async\" width=\"640\" height=\"437\" src=\"https://sc2.hihi2.com/wp-content/uploads/2025/12/hihi2-2025-12-11_09-04-33_789764-640x437.jpg?v=1765433073\" alt=\"\" class=\"wp-image-3553381\" srcset=\"https://sc2.hihi2.com/wp-content/uploads/2025/12/hihi2-2025-12-11_09-04-33_789764-640x437.jpg?v=1765433073 640w, https://hihi2.com/wp-content/uploads/2025/12/hihi2-2025-12-11_09-04-33_789764-300x205.jpg?v=1765433073 300w, https://hihi2.com/wp-content/uploads/2025/12/hihi2-2025-12-11_09-04-33_789764-200x136.jpg?v=1765433073 200w, https://hihi2.com/wp-content/uploads/2025/12/hihi2-2025-12-11_09-04-33_789764.jpg?v=1765433073 648w\" sizes=\"auto, (max-width: 640px) 100vw, 640px\" /></figure>\n</div>",
      "image": "https://sc1.hihi2.com/wp-content/uploads/2025/12/hihi2-2025-12-11_09-00-48_718843-640x504.jpg?v=1765432848",
      "categories": [
        "أخبار دوري أبطال أوروبا",
        "أخبار ريال مدريد",
        "أخبار مانشستر سيتي",
        "أرقام بيلينغهام",
        "جود بيلينغهام",
        "دوري أبطال أوروبا",
        "ريال مدريد",
        "مانشستر سيتي"
      ]
    },
    {
      "id": "3553369",
      "title": "حصة تدريبية حاسمة للأخضر قبل مواجهة فلسطين",
      "link": "https://hihi2.com/2025/12/11/p3553369.html",
      "pubDate": "2025-12-11T06:05:24.000Z",
      "summary": "هاي كورة – أنهى المنتخب السعودي الأول لكرة القدم استعداداته لمواجهته المرتقبة أمام فلسطين ، في إطار منافسات ربع نهائي كأس العرب 2025 ، المقررة مساء الخميس . شهد أحد ملاعب تدريب مركز ” سباير ” الرياضي ، إقامة الحصة التدريبية الأخيرة للأخضر تحت إشراف المدرب الفرنسي هيرفي رينارد ، والتي نفذ خلالها ما يلي […]",
      "description": "\n<figure class=\"wp-block-image size-large\"><img loading=\"lazy\" decoding=\"async\" width=\"640\" height=\"355\" src=\"https://sc2.hihi2.com/wp-content/uploads/2025/12/hihi2-2025-12-11_08-59-58_308120-640x355.jpg\" alt=\"\" class=\"wp-image-3553377\" srcset=\"https://sc5.hihi2.com/wp-content/uploads/2025/12/hihi2-2025-12-11_08-59-58_308120-640x355.jpg?v=1765432798 640w, https://hihi2.com/wp-content/uploads/2025/12/hihi2-2025-12-11_08-59-58_308120-300x166.jpg?v=1765432798 300w, https://hihi2.com/wp-content/uploads/2025/12/hihi2-2025-12-11_08-59-58_308120-200x111.jpg?v=1765432798 200w, https://hihi2.com/wp-content/uploads/2025/12/hihi2-2025-12-11_08-59-58_308120.jpg?v=1765432798 749w\" sizes=\"auto, (max-width: 640px) 100vw, 640px\" /></figure>\n\n\n\n<p>هاي كورة &#8211; أنهى المنتخب السعودي الأول لكرة القدم استعداداته لمواجهته المرتقبة أمام فلسطين ، في إطار منافسات ربع نهائي كأس العرب 2025 ، المقررة مساء الخميس .</p>\n\n\n\n<p>شهد أحد ملاعب تدريب مركز &#8221; سباير &#8221; الرياضي ، إقامة الحصة التدريبية الأخيرة للأخضر تحت إشراف المدرب الفرنسي هيرفي رينارد ، والتي نفذ خلالها <mark style=\"background-color:rgba(0, 0, 0, 0)\" class=\"has-inline-color has-vivid-red-color\"><strong>ما يلي :</strong></mark></p>\n\n\n\n<p>• تمارين الإحماء .</p>\n\n\n\n<p>• إقامة مربعات تكتيكية مصغرة .</p>\n\n\n\n<p>• مناورة على نصف مساحة الملعب لتطبيق النهج التكتيكي .</p>\n\n\n\n<p>• التدرب على تنفيذ الكراث الثابتة .</p>\n",
      "image": "https://sc2.hihi2.com/wp-content/uploads/2025/12/hihi2-2025-12-11_08-59-58_308120-640x355.jpg",
      "categories": [
        "أخبار المنتخب السعودي",
        "المنتخب السعودي",
        "كأس العرب",
        "منتخب فلسطين"
      ]
    },
    {
      "id": "3553367",
      "title": "على الرغم من رفضه .. مورينيو يمكنه تدريب الريال !",
      "link": "https://hihi2.com/2025/12/11/p3553367.html",
      "pubDate": "2025-12-11T05:58:42.000Z",
      "summary": "هاي كورة – رأي خاص بالصحفي دييغو بلازا ” يمكن لخوزيه مورينيو أن يترك بنفيكا ويدرب ريال مدريد الموسم المقبل لوجود بند في عقده مع النادي البرتغالي يشترط موافقة الطرفين على تفعيل موسم إضافي وحال رفض مورينيو ، فلن يتم التفعيل . ” ” لن تكون هناك غرامة على مورينيو حال رحيله في الصيف المقبل […]",
      "description": "<div class=\"wp-block-image\">\n<figure class=\"aligncenter size-large\"><img loading=\"lazy\" decoding=\"async\" width=\"640\" height=\"360\" src=\"https://sc4.hihi2.com/wp-content/uploads/2025/12/hihi2-2025-12-11_08-58-09_530842-640x360.jpg?v=1765432689\" alt=\"\" class=\"wp-image-3553373\" srcset=\"https://sc5.hihi2.com/wp-content/uploads/2025/12/hihi2-2025-12-11_08-58-09_530842-640x360.jpg?v=1765432689 640w, https://hihi2.com/wp-content/uploads/2025/12/hihi2-2025-12-11_08-58-09_530842-300x169.jpg?v=1765432689 300w, https://hihi2.com/wp-content/uploads/2025/12/hihi2-2025-12-11_08-58-09_530842-200x112.jpg?v=1765432689 200w, https://hihi2.com/wp-content/uploads/2025/12/hihi2-2025-12-11_08-58-09_530842-768x432.jpg?v=1765432689 768w, https://hihi2.com/wp-content/uploads/2025/12/hihi2-2025-12-11_08-58-09_530842.jpg?v=1765432689 900w\" sizes=\"auto, (max-width: 640px) 100vw, 640px\" /></figure>\n</div>\n\n\n<p></p>\n\n\n\n<p>هاي كورة &#8211;<strong><mark style=\"background-color:rgba(0, 0, 0, 0)\" class=\"has-inline-color has-vivid-red-color\"> رأي خاص بالصحفي دييغو بلازا </mark></strong></p>\n\n\n\n<p>&#8221; يمكن لخوزيه مورينيو أن يترك بنفيكا ويدرب ريال مدريد الموسم المقبل لوجود بند في عقده مع النادي البرتغالي يشترط موافقة الطرفين على تفعيل موسم إضافي وحال رفض مورينيو ، فلن يتم التفعيل . &#8221; </p>\n\n\n\n<p>&#8221; لن تكون هناك غرامة على مورينيو حال رحيله في الصيف المقبل &#8221; .</p>\n\n\n\n<p></p>\n",
      "image": "https://sc4.hihi2.com/wp-content/uploads/2025/12/hihi2-2025-12-11_08-58-09_530842-640x360.jpg?v=1765432689",
      "categories": [
        "أخبار ريال مدريد",
        "الريال",
        "ريال مدريد",
        "مورينيو"
      ]
    },
    {
      "id": "3553363",
      "title": "إحصائيات رودريغو أمام السيتي",
      "link": "https://hihi2.com/2025/12/11/p3553363.html",
      "pubDate": "2025-12-11T05:57:52.000Z",
      "summary": "هاي كورة _ شارك النجم رودريغو غوس أساسيًا أمام مانشستر سيتي، ونال تقييمًا مرتفعًا بلغ 8.1. إليكم أبرز أرقام رودريغو في هذه المباراة: لعب: 90 دقيقة. الأهداف: 1. التمريرات المفتاحية: 5. العرضيات الناجحة: 4. التمريرات: 30 منها 22 صحيحة. دقة التمرير: 73%. التسديدات: 2 منها تسديدة على المرمى. لمس الكرة: 56. المراوغات الناجحة: 3. اعتراضات: […]",
      "description": "\n<blockquote class=\"wp-block-quote is-layout-flow wp-block-quote-is-layout-flow\"><div class=\"wp-block-image\">\n<figure class=\"aligncenter size-large\"><img loading=\"lazy\" decoding=\"async\" width=\"640\" height=\"521\" src=\"https://sc3.hihi2.com/wp-content/uploads/2025/12/hihi2-2025-12-11_08-52-58_952912-640x521.jpg?v=1765432379\" alt=\"\" class=\"wp-image-3553365\" srcset=\"https://sc5.hihi2.com/wp-content/uploads/2025/12/hihi2-2025-12-11_08-52-58_952912-640x521.jpg?v=1765432379 640w, https://hihi2.com/wp-content/uploads/2025/12/hihi2-2025-12-11_08-52-58_952912-300x244.jpg?v=1765432379 300w, https://hihi2.com/wp-content/uploads/2025/12/hihi2-2025-12-11_08-52-58_952912-200x163.jpg?v=1765432379 200w, https://hihi2.com/wp-content/uploads/2025/12/hihi2-2025-12-11_08-52-58_952912-768x626.jpg?v=1765432379 768w, https://hihi2.com/wp-content/uploads/2025/12/hihi2-2025-12-11_08-52-58_952912.jpg?v=1765432379 884w\" sizes=\"auto, (max-width: 640px) 100vw, 640px\" /></figure>\n</div></blockquote>\n\n\n\n<p>هاي كورة _ شارك النجم رودريغو غوس أساسيًا أمام مانشستر سيتي، ونال تقييمًا مرتفعًا بلغ 8.1.</p>\n\n\n\n<p>إليكم أبرز أرقام رودريغو في هذه المباراة:</p>\n\n\n\n<p>لعب: 90 دقيقة.</p>\n\n\n\n<p>الأهداف: 1.</p>\n\n\n\n<p>التمريرات المفتاحية: 5.</p>\n\n\n\n<p>العرضيات الناجحة: 4.</p>\n\n\n\n<p>التمريرات: 30 منها 22 صحيحة.</p>\n\n\n\n<p>دقة التمرير: 73%.</p>\n\n\n\n<p>التسديدات: 2 منها تسديدة على المرمى.</p>\n\n\n\n<p>لمس الكرة: 56.</p>\n\n\n\n<p>المراوغات الناجحة: 3.</p>\n\n\n\n<p>اعتراضات: 1.</p>\n\n\n\n<p>استرجاع الكرة: 6.</p>\n\n\n\n<p>المواجهات الثنائية الناجحة: 7.</p>\n\n\n<div class=\"wp-block-image\">\n<figure class=\"aligncenter size-large\"><img loading=\"lazy\" decoding=\"async\" width=\"640\" height=\"440\" src=\"https://sc3.hihi2.com/wp-content/uploads/2025/12/hihi2-2025-12-11_08-56-38_658831-640x440.jpg?v=1765432598\" alt=\"\" class=\"wp-image-3553370\" srcset=\"https://sc4.hihi2.com/wp-content/uploads/2025/12/hihi2-2025-12-11_08-56-38_658831-640x440.jpg?v=1765432598 640w, https://hihi2.com/wp-content/uploads/2025/12/hihi2-2025-12-11_08-56-38_658831-300x206.jpg?v=1765432598 300w, https://hihi2.com/wp-content/uploads/2025/12/hihi2-2025-12-11_08-56-38_658831-200x137.jpg?v=1765432598 200w, https://hihi2.com/wp-content/uploads/2025/12/hihi2-2025-12-11_08-56-38_658831.jpg?v=1765432598 655w\" sizes=\"auto, (max-width: 640px) 100vw, 640px\" /></figure>\n</div>",
      "image": "https://sc3.hihi2.com/wp-content/uploads/2025/12/hihi2-2025-12-11_08-52-58_952912-640x521.jpg?v=1765432379",
      "categories": [
        "أخبار دوري أبطال أوروبا",
        "أخبار ريال مدريد",
        "أخبار مانشستر سيتي",
        "أرقام رودريغو",
        "دوري أبطال أوروبا",
        "رودريغو غوس",
        "ريال مدريد",
        "مانشستر سيتي"
      ]
    },
    {
      "id": "3553356",
      "title": "فابينيو يرفض قرار الاتحاد !",
      "link": "https://hihi2.com/2025/12/11/p3553356.html",
      "pubDate": "2025-12-11T05:56:24.000Z",
      "summary": "هاي كورة – وفقًا للصحفي أندريه هيرنان ، أبدى نادي الاتحاد استعداده لإعفاء النجم البرازيلي فابينيو تافاريس من عقده الحالي وذلك قبل انتهاءه منتصف العام القادم ، إلا أن اللاعب رفض الرحيل . أشار هيرنان إلى أن فابينيو ( صاحب الـ 32 عامًا ) يحصل على حوالي 24 مليون يورو مع الاتحاد كراتب سنوي ، […]",
      "description": "\n<figure class=\"wp-block-image size-large\"><img loading=\"lazy\" decoding=\"async\" width=\"640\" height=\"320\" src=\"https://sc5.hihi2.com/wp-content/uploads/2025/12/hihi2-2025-12-11_08-48-21_013825-640x320.jpg\" alt=\"\" class=\"wp-image-3553359\" srcset=\"https://sc5.hihi2.com/wp-content/uploads/2025/12/hihi2-2025-12-11_08-48-21_013825-640x320.jpg?v=1765432101 640w, https://hihi2.com/wp-content/uploads/2025/12/hihi2-2025-12-11_08-48-21_013825-300x150.jpg?v=1765432101 300w, https://hihi2.com/wp-content/uploads/2025/12/hihi2-2025-12-11_08-48-21_013825-200x100.jpg?v=1765432101 200w, https://hihi2.com/wp-content/uploads/2025/12/hihi2-2025-12-11_08-48-21_013825-768x384.jpg?v=1765432101 768w, https://hihi2.com/wp-content/uploads/2025/12/hihi2-2025-12-11_08-48-21_013825.jpg?v=1765432101 1000w\" sizes=\"auto, (max-width: 640px) 100vw, 640px\" /></figure>\n\n\n\n<p>هاي كورة &#8211; وفقًا للصحفي أندريه هيرنان ، أبدى نادي الاتحاد استعداده لإعفاء النجم البرازيلي فابينيو تافاريس من عقده الحالي وذلك قبل انتهاءه منتصف العام القادم ، إلا أن اللاعب رفض الرحيل .</p>\n\n\n\n<p>أشار هيرنان إلى أن فابينيو ( صاحب الـ 32 عامًا ) يحصل على حوالي 24 مليون يورو مع الاتحاد كراتب سنوي ، أي حوالي 2 مليون يورو شهريًا ، وفي حال رحيله خلال النافذة الشتوية المقبلة سيتنازل عن رواتب 6 أشهر من عقده .</p>\n\n\n\n<p>شدد أيضًا على أن فابينيو يفضل حاليًا الاستمرار خارج البرازيل ، في حال رحيله عن العميد بشكل نهائي ، إذ يرى أن العودة إلى أوروبا أكثر الخيارات المناسب له .</p>\n",
      "image": "https://sc5.hihi2.com/wp-content/uploads/2025/12/hihi2-2025-12-11_08-48-21_013825-640x320.jpg",
      "categories": [
        "أخبار الاتحاد السعودي",
        "الاتحاد",
        "دوري روشن",
        "فابينيو تافاريس"
      ]
    },
    {
      "id": "3553361",
      "title": "ألونسو وجد ما افتقده في الريال !",
      "link": "https://hihi2.com/2025/12/11/p3553361.html",
      "pubDate": "2025-12-11T05:54:42.000Z",
      "summary": "هاي كورة – تحدث تشابي ألونسو إثر خسارة ريال مدريد أمام مانشستر سيتي بهدفين لهدف في دوري الأبطال ، مؤكدا على دعم لاعبي الريال له . ألونسو تحدث قائلا ” نعم ، أشعر بدعم اللاعبين . سنتجاوز هذه اللحظة جميعاً معاً . “",
      "description": "<div class=\"wp-block-image\">\n<figure class=\"aligncenter size-large\"><img loading=\"lazy\" decoding=\"async\" width=\"640\" height=\"426\" src=\"https://sc4.hihi2.com/wp-content/uploads/2025/12/hihi2-2025-12-11_08-49-42_645437-640x426.jpg?v=1765432182\" alt=\"\" class=\"wp-image-3553362\" srcset=\"https://sc4.hihi2.com/wp-content/uploads/2025/12/hihi2-2025-12-11_08-49-42_645437-640x426.jpg?v=1765432182 640w, https://hihi2.com/wp-content/uploads/2025/12/hihi2-2025-12-11_08-49-42_645437-300x200.jpg?v=1765432182 300w, https://hihi2.com/wp-content/uploads/2025/12/hihi2-2025-12-11_08-49-42_645437-200x133.jpg?v=1765432182 200w, https://hihi2.com/wp-content/uploads/2025/12/hihi2-2025-12-11_08-49-42_645437.jpg?v=1765432182 680w\" sizes=\"auto, (max-width: 640px) 100vw, 640px\" /></figure>\n</div>\n\n\n<p></p>\n\n\n\n<p>هاي كورة &#8211; تحدث تشابي ألونسو إثر خسارة ريال مدريد أمام مانشستر سيتي بهدفين لهدف في دوري الأبطال ، مؤكدا على دعم لاعبي الريال له .</p>\n\n\n\n<p>ألونسو تحدث قائلا &#8221; نعم ، أشعر بدعم اللاعبين . سنتجاوز هذه اللحظة جميعاً معاً . &#8220;</p>\n\n\n\n<p></p>\n",
      "image": "https://sc4.hihi2.com/wp-content/uploads/2025/12/hihi2-2025-12-11_08-49-42_645437-640x426.jpg?v=1765432182",
      "categories": [
        "أخبار ريال مدريد",
        "الريال",
        "الونسو",
        "ريال مدريد"
      ]
    },
    {
      "id": "3553357",
      "title": "بيلينغهام يؤكد على بدء مرحلة جديدة في مدريد !",
      "link": "https://hihi2.com/2025/12/11/p3553357.html",
      "pubDate": "2025-12-11T05:48:24.000Z",
      "summary": "هاي كورة – تحدث جود بيلينغهام عن مباراة ريال مدريد أمام مانشستر سيتي في دوري الأبطال ، والتي انتهت بفوز السيتي بهدفين لهدف . بيلينغهام تحدث قائلا ” اليوم تغير شيء ما ، أشعر بذلك . علينا الآن أن ندرك ضرورة التحسن ، جميعنا . أتفهم صيحات الاستهجان ، فالناس يدفعون مبالغ طائلة لمتابعتنا ، […]",
      "description": "<div class=\"wp-block-image\">\n<figure class=\"aligncenter size-full\"><img loading=\"lazy\" decoding=\"async\" width=\"500\" height=\"254\" src=\"https://sc3.hihi2.com/wp-content/uploads/2025/12/hihi2-2025-12-11_08-47-45_128897.jpg?v=1765432065\" alt=\"\" class=\"wp-image-3553358\" srcset=\"https://sc3.hihi2.com/wp-content/uploads/2025/12/hihi2-2025-12-11_08-47-45_128897.jpg?v=1765432065 500w, https://hihi2.com/wp-content/uploads/2025/12/hihi2-2025-12-11_08-47-45_128897-300x152.jpg?v=1765432065 300w, https://hihi2.com/wp-content/uploads/2025/12/hihi2-2025-12-11_08-47-45_128897-200x102.jpg?v=1765432065 200w\" sizes=\"auto, (max-width: 500px) 100vw, 500px\" /></figure>\n</div>\n\n\n<p></p>\n\n\n\n<p>هاي كورة &#8211; تحدث جود بيلينغهام عن مباراة ريال مدريد أمام مانشستر سيتي في دوري الأبطال ، والتي انتهت بفوز السيتي بهدفين لهدف .</p>\n\n\n\n<p>بيلينغهام تحدث قائلا &#8221; اليوم تغير شيء ما ، أشعر بذلك . علينا الآن أن ندرك ضرورة التحسن ، جميعنا . أتفهم صيحات الاستهجان ، فالناس يدفعون مبالغ طائلة لمتابعتنا ، ونحن نلعب لأفضل نادٍ في العالم . &#8220;<br></p>\n",
      "image": "https://sc3.hihi2.com/wp-content/uploads/2025/12/hihi2-2025-12-11_08-47-45_128897.jpg?v=1765432065",
      "categories": [
        "أخبار ريال مدريد",
        "الريال",
        "بيلينغهام",
        "ريال مدريد"
      ]
    },
    {
      "id": "3553351",
      "title": "عاملة منزلية وراء غياب كاراسكو عن الشباب !",
      "link": "https://hihi2.com/2025/12/11/p3553351.html",
      "pubDate": "2025-12-11T05:44:25.000Z",
      "summary": "هاي كورة – على ذمة صحيفة ” الرياضية ” ، غاب البلجيكي يانيك كاراسكو ، لاعب فريق الشباب ، عن التدريبات الجماعية لليث الأبيض ، وذلك لليوم الثاني على التوالي . أوضحت الصحيفة أن اللاعب البلجيكي رفض الحضور إلى مقر النادي قبل الاستجابة لمطالبه الشخصية ، والتي تتعلق باستقدام عاملة منزلية ، مؤكدًا أنه غير […]",
      "description": "\n<figure class=\"wp-block-image size-large\"><img loading=\"lazy\" decoding=\"async\" width=\"640\" height=\"354\" src=\"https://sc2.hihi2.com/wp-content/uploads/2025/12/hihi2-2025-12-11_08-37-28_458763-640x354.jpg?v=1765431448\" alt=\"\" class=\"wp-image-3553352\" srcset=\"https://sc3.hihi2.com/wp-content/uploads/2025/12/hihi2-2025-12-11_08-37-28_458763-640x354.jpg?v=1765431448 640w, https://hihi2.com/wp-content/uploads/2025/12/hihi2-2025-12-11_08-37-28_458763-300x166.jpg?v=1765431448 300w, https://hihi2.com/wp-content/uploads/2025/12/hihi2-2025-12-11_08-37-28_458763-200x111.jpg?v=1765431448 200w, https://hihi2.com/wp-content/uploads/2025/12/hihi2-2025-12-11_08-37-28_458763-768x424.jpg?v=1765431448 768w, https://hihi2.com/wp-content/uploads/2025/12/hihi2-2025-12-11_08-37-28_458763-1536x849.jpg?v=1765431448 1536w, https://hihi2.com/wp-content/uploads/2025/12/hihi2-2025-12-11_08-37-28_458763.jpg?v=1765431448 1665w\" sizes=\"auto, (max-width: 640px) 100vw, 640px\" /></figure>\n\n\n\n<p>هاي كورة &#8211; على ذمة صحيفة &#8221; الرياضية &#8221; ، غاب البلجيكي يانيك كاراسكو ، لاعب فريق الشباب ، عن التدريبات الجماعية لليث الأبيض ، وذلك لليوم الثاني على التوالي .</p>\n\n\n\n<p>أوضحت الصحيفة أن اللاعب البلجيكي رفض الحضور إلى مقر النادي قبل الاستجابة لمطالبه الشخصية ، والتي تتعلق باستقدام عاملة منزلية ، مؤكدًا أنه غير قادر على العودة للتدريبات ما لم تُنفذ رغبته .</p>\n\n\n\n<p>من جانبها ، تعمل إدارة الشباب في الوقت الحالي على إنهاء هذه المسألة عبر التواصل مع وكيل أعمال اللاعب ، على أمل إعادة كاراسكو إلى التدريبات قبل استئناف الاستحقاقات القادمة .</p>\n",
      "image": "https://sc2.hihi2.com/wp-content/uploads/2025/12/hihi2-2025-12-11_08-37-28_458763-640x354.jpg?v=1765431448",
      "categories": [
        "أخبار الشباب السعودي",
        "أخبار الكرة السعودية",
        "الشباب",
        "دوري روشن",
        "كاراسكو"
      ]
    },
    {
      "id": "3553353",
      "title": "هذا ما يحتاج لاعبو الريال لإثباته أمام الافيس !",
      "link": "https://hihi2.com/2025/12/11/p3553353.html",
      "pubDate": "2025-12-11T05:40:48.000Z",
      "summary": "هاي كورة – رأي خاص بالصحفي توماس رونسيرو على الرغم من الهزيمة أمام مانشستر سيتي لكن الريال لا يزال ضمن المراكز الثمانية الأولى في دوري الأبطال ويمكنه التأهل ، الأداء أصبح جيدا ، أتمنى أن يستمر أمام الافيس وأن يثبت اللاعبين أن المشكلة لم تكن في ألونسو",
      "description": "<div class=\"wp-block-image\">\n<figure class=\"aligncenter size-full\"><img loading=\"lazy\" decoding=\"async\" width=\"502\" height=\"252\" src=\"https://sc1.hihi2.com/wp-content/uploads/2025/12/hihi2-2025-12-11_03-18-09_323309.jpg\" alt=\"\" class=\"wp-image-3553211\" srcset=\"https://sc5.hihi2.com/wp-content/uploads/2025/12/hihi2-2025-12-11_03-18-09_323309.jpg?v=1765412289 502w, https://hihi2.com/wp-content/uploads/2025/12/hihi2-2025-12-11_03-18-09_323309-300x151.jpg?v=1765412289 300w, https://hihi2.com/wp-content/uploads/2025/12/hihi2-2025-12-11_03-18-09_323309-200x100.jpg?v=1765412289 200w\" sizes=\"auto, (max-width: 502px) 100vw, 502px\" /></figure>\n</div>\n\n\n<p></p>\n\n\n\n<p>هاي كورة &#8211; <strong><mark style=\"background-color:rgba(0, 0, 0, 0)\" class=\"has-inline-color has-vivid-red-color\">رأي خاص بالصحفي توماس رونسيرو </mark></strong></p>\n\n\n\n<p>على الرغم من الهزيمة أمام مانشستر سيتي لكن الريال لا يزال ضمن المراكز الثمانية الأولى في دوري الأبطال ويمكنه التأهل ، الأداء أصبح جيدا ، أتمنى أن يستمر أمام الافيس وأن يثبت اللاعبين أن المشكلة لم تكن في ألونسو </p>\n",
      "image": "https://sc1.hihi2.com/wp-content/uploads/2025/12/hihi2-2025-12-11_03-18-09_323309.jpg",
      "categories": [
        "أخبار ريال مدريد",
        "البلانكو",
        "الريال",
        "الونسو",
        "ريال مدريد"
      ]
    },
    {
      "id": "3553345",
      "title": "لماذا وقع ستيف كالزادا مع الهلال ؟",
      "link": "https://hihi2.com/2025/12/11/p3553345.html",
      "pubDate": "2025-12-11T05:30:53.000Z",
      "summary": "هاي كورة – كشف الإسباني ستيف كالزادا ، الرئيس التنفيذي لشركة نادي الهلال ، عن سبب موافقته على الانضمام إلى الزعيم ، والذي بدأ العمل رسميًا معه في يناير 2024 . تحدث كالزادا قائلًا : ” لقد وقّعت مع نادي الهلال لأن الزعيم هو أكبر نادٍ في السعودية ، نعم ، كنت محظوظًا بالعمل مع […]",
      "description": "\n<figure class=\"wp-block-image size-large\"><img loading=\"lazy\" decoding=\"async\" width=\"640\" height=\"359\" src=\"https://sc2.hihi2.com/wp-content/uploads/2025/12/hihi2-2025-12-11_08-27-05_194878-640x359.jpg?v=1765430825\" alt=\"\" class=\"wp-image-3553348\" srcset=\"https://sc2.hihi2.com/wp-content/uploads/2025/12/hihi2-2025-12-11_08-27-05_194878-640x359.jpg?v=1765430825 640w, https://hihi2.com/wp-content/uploads/2025/12/hihi2-2025-12-11_08-27-05_194878-300x168.jpg?v=1765430825 300w, https://hihi2.com/wp-content/uploads/2025/12/hihi2-2025-12-11_08-27-05_194878-200x112.jpg?v=1765430825 200w, https://hihi2.com/wp-content/uploads/2025/12/hihi2-2025-12-11_08-27-05_194878.jpg?v=1765430825 739w\" sizes=\"auto, (max-width: 640px) 100vw, 640px\" /></figure>\n\n\n\n<p>هاي كورة &#8211; كشف الإسباني ستيف كالزادا ، الرئيس التنفيذي لشركة نادي الهلال ، عن سبب موافقته على الانضمام إلى الزعيم ، والذي بدأ العمل رسميًا معه في يناير 2024 .</p>\n\n\n\n<p>تحدث كالزادا قائلًا : &#8221; لقد وقّعت مع نادي الهلال لأن الزعيم هو أكبر نادٍ في السعودية ، نعم ، كنت محظوظًا بالعمل مع بعض أكبر الأندية في العالم . </p>\n\n\n\n<p>&#8221; عندما جاءت الفرصة للعمل في السعودية ، كنت أعلم جيدًا أن الهلال هو أكبر نادٍ هناك ، وكنت واضحًا جدًا بأن النادي الوحيد الذي سأغادر مانشستر سيتي من أجله هو الزعيم &#8221; .</p>\n",
      "image": "https://sc2.hihi2.com/wp-content/uploads/2025/12/hihi2-2025-12-11_08-27-05_194878-640x359.jpg?v=1765430825",
      "categories": [
        "أخبار الهلال السعودي",
        "الهلال",
        "دوري روشن",
        "ستيف كالزادا"
      ]
    },
    {
      "id": "3553341",
      "title": "كم بلغ سعر أغلى تذكرة في مباراة النصر والوحدة ؟",
      "link": "https://hihi2.com/2025/12/11/p3553341.html",
      "pubDate": "2025-12-11T05:23:52.000Z",
      "summary": "هاي كورة – شهدت مدينة أبو ظبي حدثًا استثنائيًا مع مباراة الفريق الأول لكرة القدم بنادي النصر ضد الوحدة الإماراتي ، حيث بلغ سعر أغلى تذكرة في اللقاء التجريبي 578 دولارًا ، مساء الأربعاء . المباراة التجريبية ، التي انتهت بفوز النصر بنتيجة 4-2 ، تراوحت أسعار تذاكرها بين 55 دولارًا للدرجة العادية و578 لمنصة […]",
      "description": "\n<figure class=\"wp-block-image size-large\"><img loading=\"lazy\" decoding=\"async\" width=\"640\" height=\"340\" src=\"https://sc5.hihi2.com/wp-content/uploads/2025/12/hihi2-2025-12-11_08-16-22_298259-640x340.jpg\" alt=\"\" class=\"wp-image-3553342\" srcset=\"https://sc3.hihi2.com/wp-content/uploads/2025/12/hihi2-2025-12-11_08-16-22_298259-640x340.jpg?v=1765430182 640w, https://hihi2.com/wp-content/uploads/2025/12/hihi2-2025-12-11_08-16-22_298259-300x159.jpg?v=1765430182 300w, https://hihi2.com/wp-content/uploads/2025/12/hihi2-2025-12-11_08-16-22_298259-200x106.jpg?v=1765430182 200w, https://hihi2.com/wp-content/uploads/2025/12/hihi2-2025-12-11_08-16-22_298259-768x408.jpg?v=1765430182 768w, https://hihi2.com/wp-content/uploads/2025/12/hihi2-2025-12-11_08-16-22_298259.jpg?v=1765430182 1499w\" sizes=\"auto, (max-width: 640px) 100vw, 640px\" /></figure>\n\n\n\n<p>هاي كورة &#8211; شهدت مدينة أبو ظبي حدثًا استثنائيًا مع مباراة الفريق الأول لكرة القدم بنادي النصر ضد الوحدة الإماراتي ، حيث بلغ سعر أغلى تذكرة في اللقاء التجريبي 578 دولارًا ، مساء الأربعاء .</p>\n\n\n\n<p>المباراة التجريبية ، التي انتهت بفوز النصر بنتيجة 4-2 ، تراوحت أسعار تذاكرها بين 55 دولارًا للدرجة العادية و578 لمنصة كبار الشخصيات في ملعب آل نهيان ، ورغم ذلك شهدت حضورًا جماهيريًا كبيرًا ارتدى معظمه قميص الأسطورة البرتغالية كريستيانو رونالدو .</p>\n\n\n\n<p></p>\n",
      "image": "https://sc5.hihi2.com/wp-content/uploads/2025/12/hihi2-2025-12-11_08-16-22_298259-640x340.jpg",
      "categories": [
        "أخبار النصر السعودي",
        "النصر",
        "الوحدة الإماراتي",
        "رونالدو"
      ]
    },
    {
      "id": "3553344",
      "title": "صورة : مشجعو الريال يدعمون ألونسو",
      "link": "https://hihi2.com/2025/12/11/p3553344.html",
      "pubDate": "2025-12-11T05:20:00.000Z",
      "summary": "هاي كورة – قام بعض مشجعي ريال مدريد بتقديم الدعم لتشابي ألونسو ، وذلك إثر الهزيمة من مانشستر سيتي بهدفين لهدف في دوري الأبطال . المشجعون انتظروا أمام البرنابيو بعد اللقاء وقال أحدهم لألونسو أثناء تحركه بسيارته ” اصبر يا تشابي ، نحن نثق بك ” . ويأتي ذلك في الوقت الذي تتوارد فيه التقارير […]",
      "description": "<div class=\"wp-block-image\">\n<figure class=\"aligncenter size-full\"><img loading=\"lazy\" decoding=\"async\" width=\"628\" height=\"584\" src=\"https://sc3.hihi2.com/wp-content/uploads/2025/12/hihi2-2025-12-11_08-24-29_591819.jpg?v=1765430669\" alt=\"\" class=\"wp-image-3553346\" srcset=\"https://sc2.hihi2.com/wp-content/uploads/2025/12/hihi2-2025-12-11_08-24-29_591819.jpg?v=1765430669 628w, https://hihi2.com/wp-content/uploads/2025/12/hihi2-2025-12-11_08-24-29_591819-300x279.jpg?v=1765430669 300w, https://hihi2.com/wp-content/uploads/2025/12/hihi2-2025-12-11_08-24-29_591819-200x186.jpg?v=1765430669 200w\" sizes=\"auto, (max-width: 628px) 100vw, 628px\" /></figure>\n</div>\n\n\n<p></p>\n\n\n\n<p>هاي كورة &#8211; قام بعض مشجعي ريال مدريد بتقديم الدعم لتشابي ألونسو ، وذلك إثر الهزيمة من مانشستر سيتي بهدفين لهدف في دوري الأبطال .</p>\n\n\n\n<p>المشجعون انتظروا أمام البرنابيو بعد اللقاء وقال أحدهم لألونسو أثناء تحركه بسيارته &#8221; اصبر يا تشابي ، نحن نثق بك &#8221; .</p>\n\n\n\n<p>ويأتي ذلك في الوقت الذي تتوارد فيه التقارير عن احتمالية إقالة الإسباني قبل انتهاء العام الحالي .</p>\n",
      "image": "https://sc3.hihi2.com/wp-content/uploads/2025/12/hihi2-2025-12-11_08-24-29_591819.jpg?v=1765430669",
      "categories": [
        "أخبار ريال مدريد",
        "الريال"
      ]
    },
    {
      "id": "3553337",
      "title": "النصر مهتم بضم محمد صلاح !",
      "link": "https://hihi2.com/2025/12/11/p3553337.html",
      "pubDate": "2025-12-11T05:13:07.000Z",
      "summary": "هاي كورة – أشارت تقارير صحفية إلى أن نادي النصر يولي اهتمامًا كبيرًا بالنجم المصري محمد صلاح ، لاعب فريق ليفربول الإنجليزي ، إذ يرى فيه إضافة فنية وتسويقية كبيرة . أكدت التقارير أن الإدارة النصراوية مستعدة للتحرك بشكل جاد خلال فترة الانتقالات الشتوية المقبلة ، حيث سيبذل النادي قصارى جهده لإتمام الصفقة في يناير […]",
      "description": "\n<figure class=\"wp-block-image size-large\"><img loading=\"lazy\" decoding=\"async\" width=\"512\" height=\"640\" src=\"https://sc4.hihi2.com/wp-content/uploads/2025/12/hihi2-2025-12-11_08-08-06_730792-512x640.jpg?v=1765429686\" alt=\"\" class=\"wp-image-3553339\" srcset=\"https://sc1.hihi2.com/wp-content/uploads/2025/12/hihi2-2025-12-11_08-08-06_730792-512x640.jpg?v=1765429686 512w, https://hihi2.com/wp-content/uploads/2025/12/hihi2-2025-12-11_08-08-06_730792-240x300.jpg?v=1765429686 240w, https://hihi2.com/wp-content/uploads/2025/12/hihi2-2025-12-11_08-08-06_730792-160x200.jpg?v=1765429686 160w, https://hihi2.com/wp-content/uploads/2025/12/hihi2-2025-12-11_08-08-06_730792-768x960.jpg?v=1765429686 768w, https://hihi2.com/wp-content/uploads/2025/12/hihi2-2025-12-11_08-08-06_730792.jpg?v=1765429686 1080w\" sizes=\"auto, (max-width: 512px) 100vw, 512px\" /></figure>\n\n\n\n<p>هاي كورة &#8211; أشارت تقارير صحفية إلى أن نادي النصر يولي اهتمامًا كبيرًا بالنجم المصري محمد صلاح ، لاعب فريق ليفربول الإنجليزي ، إذ يرى فيه إضافة فنية وتسويقية كبيرة .</p>\n\n\n\n<p>أكدت التقارير أن الإدارة النصراوية مستعدة للتحرك بشكل جاد خلال فترة الانتقالات الشتوية المقبلة ، حيث سيبذل النادي قصارى جهده لإتمام الصفقة في يناير 2026 .</p>\n\n\n\n<p>تشمل هذه الجهود تقديم عرض مالي قوي ، والدخول في مفاوضات مكثفة مع اللاعب وناديه ، سعيًا لإقناع إدارة ليفربول بالتخلي عن أحد أبرز نجوم فريقها الأول .</p>\n",
      "image": "https://sc4.hihi2.com/wp-content/uploads/2025/12/hihi2-2025-12-11_08-08-06_730792-512x640.jpg?v=1765429686",
      "categories": [
        "أخبار النصر السعودي",
        "أخبار ليفربول",
        "النصر",
        "ليفربول",
        "محمد صلاح"
      ]
    },
    {
      "id": "3553334",
      "title": "الأهلي ينتظر التعويض الكبير !",
      "link": "https://hihi2.com/2025/12/11/p3553334.html",
      "pubDate": "2025-12-11T05:05:07.000Z",
      "summary": "هاي كورة – أفصح فيصل زيد ، مدير المركز الإعلامي للأهلي سابقًا ، عن كواليس مهمة تتعلق بتوزيع ملفات اللاعبين الأجانب داخل الراقي ، مشيرًا إلى أن النادي ما زال بانتظار التعويض المالي الخاص بالراحلين ، حيث قال : ” ‏حالياً إدوارد ميندي ، فرانك كيسيه ، روجير إيبانيز ، رياض محرز على لجنة الاستقطاب […]",
      "description": "\n<figure class=\"wp-block-image size-large\"><img loading=\"lazy\" decoding=\"async\" width=\"640\" height=\"326\" src=\"https://sc3.hihi2.com/wp-content/uploads/2025/12/hihi2-2025-12-11_08-00-04_938012-640x326.jpg\" alt=\"\" class=\"wp-image-3553335\" srcset=\"https://sc4.hihi2.com/wp-content/uploads/2025/12/hihi2-2025-12-11_08-00-04_938012-640x326.jpg?v=1765429205 640w, https://hihi2.com/wp-content/uploads/2025/12/hihi2-2025-12-11_08-00-04_938012-300x153.jpg?v=1765429205 300w, https://hihi2.com/wp-content/uploads/2025/12/hihi2-2025-12-11_08-00-04_938012-200x102.jpg?v=1765429205 200w, https://hihi2.com/wp-content/uploads/2025/12/hihi2-2025-12-11_08-00-04_938012.jpg?v=1765429205 736w\" sizes=\"auto, (max-width: 640px) 100vw, 640px\" /></figure>\n\n\n\n<p>هاي كورة &#8211; أفصح فيصل زيد ، مدير المركز الإعلامي للأهلي سابقًا ، عن كواليس مهمة تتعلق بتوزيع ملفات اللاعبين الأجانب داخل الراقي ، مشيرًا إلى أن النادي ما زال بانتظار التعويض المالي الخاص بالراحلين ، حيث قال :</p>\n\n\n\n<p>&#8221; ‏حالياً إدوارد ميندي ، فرانك كيسيه ، روجير إيبانيز ، رياض محرز على لجنة الاستقطاب ، بينما بقية اللاعبين الأجانب على شركة ‎النادي الأهلي . </p>\n\n\n\n<p>&#8221; وبعد خروج ماكسيمان وفيرمينو ، لم يتم تعويض الأهلي بميزانية هذين اللاعبين حتى الآن . ويمكن تعويضه بإحدى طريقتين : 1- التعاقد مع لاعب فئة (A) . 2- أو تحمّل ( عقود ) كل من إيفان توني وميريح ديميرال &#8221; .</p>\n",
      "image": "https://sc3.hihi2.com/wp-content/uploads/2025/12/hihi2-2025-12-11_08-00-04_938012-640x326.jpg",
      "categories": [
        "أخبار الاهلي السعودي",
        "الأهلي",
        "دوري روشن",
        "ميريح ديميرال"
      ]
    },
    {
      "id": "3553331",
      "title": "مفاجآت قوية بانتظار السوق الشتوي السعودي !",
      "link": "https://hihi2.com/2025/12/11/p3553331.html",
      "pubDate": "2025-12-11T04:56:41.000Z",
      "summary": "هاي كورة – شدد الإعلامي الرياضي وليد الفراج على أن سوق الانتقالات الشتوي في دوري روشن السعودي ، والذي ينطلق في يناير 2026 ، سيشهد مفاجآت قوية على مستوى لاعبي الأندية الكبرى . قال الفراج : ” ‏هناك عدد كبير من اللاعبين النجوم سيدخلون الفترة الحرة في يناير المقبل ، وحسب معلوماتي فإن اللاعبين الذين […]",
      "description": "\n<figure class=\"wp-block-image size-large\"><img loading=\"lazy\" decoding=\"async\" width=\"640\" height=\"357\" src=\"https://sc2.hihi2.com/wp-content/uploads/2025/12/hihi2-2025-12-11_07-53-09_450055-640x357.jpg\" alt=\"\" class=\"wp-image-3553332\" srcset=\"https://sc3.hihi2.com/wp-content/uploads/2025/12/hihi2-2025-12-11_07-53-09_450055-640x357.jpg?v=1765428790 640w, https://hihi2.com/wp-content/uploads/2025/12/hihi2-2025-12-11_07-53-09_450055-300x167.jpg?v=1765428790 300w, https://hihi2.com/wp-content/uploads/2025/12/hihi2-2025-12-11_07-53-09_450055-200x112.jpg?v=1765428790 200w, https://hihi2.com/wp-content/uploads/2025/12/hihi2-2025-12-11_07-53-09_450055-768x429.jpg?v=1765428790 768w, https://hihi2.com/wp-content/uploads/2025/12/hihi2-2025-12-11_07-53-09_450055-1536x857.jpg?v=1765428790 1536w, https://hihi2.com/wp-content/uploads/2025/12/hihi2-2025-12-11_07-53-09_450055-2048x1143.jpg?v=1765428790 2048w\" sizes=\"auto, (max-width: 640px) 100vw, 640px\" /></figure>\n\n\n\n<p>هاي كورة &#8211; شدد الإعلامي الرياضي وليد الفراج على أن سوق الانتقالات الشتوي في دوري روشن السعودي ، والذي ينطلق في يناير 2026 ، سيشهد مفاجآت قوية على مستوى لاعبي الأندية الكبرى . </p>\n\n\n\n<p>قال الفراج : &#8221; ‏هناك عدد كبير من اللاعبين النجوم سيدخلون الفترة الحرة في يناير المقبل ، وحسب معلوماتي فإن اللاعبين الذين تم التعاقد معهم من لجنة الاستقطاب سيتم توفير مبلغ التجديد لهذه الأندية . </p>\n\n\n\n<p>&#8221; مع ترك المساحة لهم للاستبدال والتجديد ، ولهذا أتوقع مفاجآت قادمة مع إغلاق الانتقالات الشتوية السعودية &#8221; .</p>\n",
      "image": "https://sc2.hihi2.com/wp-content/uploads/2025/12/hihi2-2025-12-11_07-53-09_450055-640x357.jpg",
      "categories": [
        "أخبار الاتحاد السعودي",
        "أخبار الاهلي السعودي",
        "أخبار النصر السعودي",
        "أخبار الهلال السعودي",
        "الأهلي",
        "الاتحاد",
        "النصر",
        "الهلال",
        "دوري روشن"
      ]
    },
    {
      "id": "3553328",
      "title": "الأهلي يؤمن رياض محرز !",
      "link": "https://hihi2.com/2025/12/11/p3553328.html",
      "pubDate": "2025-12-11T04:50:02.000Z",
      "summary": "هاي كورة – تمكنت إدارة النادي الأهلي من الاتفاق مع الدولي الجزائري رياض محرز ، لاعب الفريق الأول ، على تجديد عقده الحالي لمدة موسم إضافي ، ليتأكد استمراره مع الراقي حتى عام 2028 ، وفقًا لما ذكرته تقارير صحفية . أشارت التقارير إلى أن الاتفاق جاء بعد سلسلة مفاوضات جادة حظيت برغبة مشتركة في […]",
      "description": "\n<figure class=\"wp-block-image size-large\"><img loading=\"lazy\" decoding=\"async\" width=\"640\" height=\"329\" src=\"https://sc5.hihi2.com/wp-content/uploads/2025/12/hihi2-2025-12-11_07-43-51_564127-640x329.jpg\" alt=\"\" class=\"wp-image-3553329\" srcset=\"https://sc2.hihi2.com/wp-content/uploads/2025/12/hihi2-2025-12-11_07-43-51_564127-640x329.jpg?v=1765428232 640w, https://hihi2.com/wp-content/uploads/2025/12/hihi2-2025-12-11_07-43-51_564127-300x154.jpg?v=1765428232 300w, https://hihi2.com/wp-content/uploads/2025/12/hihi2-2025-12-11_07-43-51_564127-200x103.jpg?v=1765428232 200w, https://hihi2.com/wp-content/uploads/2025/12/hihi2-2025-12-11_07-43-51_564127-768x395.jpg?v=1765428232 768w, https://hihi2.com/wp-content/uploads/2025/12/hihi2-2025-12-11_07-43-51_564127-1536x789.jpg?v=1765428232 1536w, https://hihi2.com/wp-content/uploads/2025/12/hihi2-2025-12-11_07-43-51_564127-2048x1052.jpg?v=1765428232 2048w\" sizes=\"auto, (max-width: 640px) 100vw, 640px\" /></figure>\n\n\n\n<p>هاي كورة &#8211; تمكنت إدارة النادي الأهلي من الاتفاق مع الدولي الجزائري رياض محرز ، لاعب الفريق الأول ، على تجديد عقده الحالي لمدة موسم إضافي ، ليتأكد استمراره مع الراقي حتى عام 2028 ، وفقًا لما ذكرته تقارير صحفية .</p>\n\n\n\n<p>أشارت التقارير إلى أن الاتفاق جاء بعد سلسلة مفاوضات جادة حظيت برغبة مشتركة في استمرار اللاعب مع الفريق ، خاصة في ظل المستويات الكبيرة التي يقدمها محرز منذ انضمامه للراقي في 2023 .</p>\n\n\n\n<p>وينتظر أن يعلن النادي الأهلي رسميًا خلال الأيام القادمة عن تجديد العقد ، ليغلق الباب أمام العروض الخارجية التي كانت تستهدف ضم الدولي الجزائري .</p>\n",
      "image": "https://sc5.hihi2.com/wp-content/uploads/2025/12/hihi2-2025-12-11_07-43-51_564127-640x329.jpg",
      "categories": [
        "أخبار الاهلي السعودي",
        "الأهلي",
        "دوري روشن",
        "رياض محرز"
      ]
    },
    {
      "id": "3553324",
      "title": "لاعب النصر خارج معسكر الأخضر في قطر !",
      "link": "https://hihi2.com/2025/12/11/p3553324.html",
      "pubDate": "2025-12-11T04:40:11.000Z",
      "summary": "هاي كورة – استبعد الفرنسي هيرفي رينارد ، المدير الفني للمنتخب السعودي الأول لكرة القدم ، اللاعب أيمن يحيى من معسكر الأخضر في قطر ، على هامش المشاركة في بطولة كأس العرب 2025 ، بحسب ما أعلنه الحساب الرسمي للصقور . يأتي هذا القرار بناءً على تقرير الجهاز الطبي للمنتخب ، والذي بين عدم جاهزية […]",
      "description": "\n<figure class=\"wp-block-image size-full\"><img loading=\"lazy\" decoding=\"async\" width=\"619\" height=\"495\" src=\"https://sc4.hihi2.com/wp-content/uploads/2025/12/hihi2-2025-12-11_07-30-52_034642.jpg?v=1765427452\" alt=\"\" class=\"wp-image-3553326\" srcset=\"https://sc1.hihi2.com/wp-content/uploads/2025/12/hihi2-2025-12-11_07-30-52_034642.jpg?v=1765427452 619w, https://hihi2.com/wp-content/uploads/2025/12/hihi2-2025-12-11_07-30-52_034642-300x240.jpg?v=1765427452 300w, https://hihi2.com/wp-content/uploads/2025/12/hihi2-2025-12-11_07-30-52_034642-200x160.jpg?v=1765427452 200w\" sizes=\"auto, (max-width: 619px) 100vw, 619px\" /></figure>\n\n\n\n<p>هاي كورة &#8211; استبعد الفرنسي هيرفي رينارد ، المدير الفني للمنتخب السعودي الأول لكرة القدم ، اللاعب أيمن يحيى من معسكر الأخضر في قطر ، على هامش المشاركة في بطولة كأس العرب 2025 ، بحسب ما أعلنه الحساب الرسمي للصقور .</p>\n\n\n\n<p>يأتي هذا القرار بناءً على تقرير الجهاز الطبي للمنتخب ، والذي بين عدم جاهزية لاعب نادي النصر للمشاركة في المباريات القادمة بسبب إصابته في الركبة ، وذلك بعد إجراء الفحوصات الطبية . </p>\n\n\n\n<p>يستعد الأخضر بقيادة المدرب الفرنسي لمواجهة فلسطين في ربع نهائي كأس العرب ، مساء الخميس ، على أرضية ملعب « لوسيل » المونديالي .</p>\n",
      "image": "https://sc4.hihi2.com/wp-content/uploads/2025/12/hihi2-2025-12-11_07-30-52_034642.jpg?v=1765427452",
      "categories": [
        "أخبار المنتخب السعودي",
        "أخبار النصر السعودي",
        "أيمن يحيى",
        "المنتخب السعودي",
        "النصر",
        "كأس العرب"
      ]
    },
    {
      "id": "3553321",
      "title": "هل جدد كريم بنزيما عقده مع الاتحاد ؟",
      "link": "https://hihi2.com/2025/12/11/p3553321.html",
      "pubDate": "2025-12-11T04:25:50.000Z",
      "summary": "هاي كورة – أشارت العديد من التقارير الصحفية خلال الآونة الأخيرة إلى أن النجم الفرنسي كريم بنزيما جدد عقده مع الاتحاد ، وذلك قبل انتهائه في 30 يونيو 2026 . الصحفي الفرنسي سانتي أونا نفى هذه التقارير ، مشيرًا إلى أن بنزيما لم يجدد عقده مع الاتحاد ، إذ لم يتلقَ أي عروض رسمية من […]",
      "description": "\n<figure class=\"wp-block-image size-large\"><img loading=\"lazy\" decoding=\"async\" width=\"640\" height=\"353\" src=\"https://sc1.hihi2.com/wp-content/uploads/2025/12/hihi2-2025-12-11_07-19-39_376030-640x353.jpg\" alt=\"\" class=\"wp-image-3553322\" srcset=\"https://sc1.hihi2.com/wp-content/uploads/2025/12/hihi2-2025-12-11_07-19-39_376030-640x353.jpg?v=1765426780 640w, https://hihi2.com/wp-content/uploads/2025/12/hihi2-2025-12-11_07-19-39_376030-300x165.jpg?v=1765426780 300w, https://hihi2.com/wp-content/uploads/2025/12/hihi2-2025-12-11_07-19-39_376030-200x110.jpg?v=1765426780 200w, https://hihi2.com/wp-content/uploads/2025/12/hihi2-2025-12-11_07-19-39_376030-768x423.jpg?v=1765426780 768w, https://hihi2.com/wp-content/uploads/2025/12/hihi2-2025-12-11_07-19-39_376030-1536x846.jpg?v=1765426780 1536w, https://hihi2.com/wp-content/uploads/2025/12/hihi2-2025-12-11_07-19-39_376030-2048x1128.jpg?v=1765426780 2048w\" sizes=\"auto, (max-width: 640px) 100vw, 640px\" /></figure>\n\n\n\n<p>هاي كورة &#8211; أشارت العديد من التقارير الصحفية خلال الآونة الأخيرة إلى أن النجم الفرنسي كريم بنزيما جدد عقده مع الاتحاد ، وذلك قبل انتهائه في 30 يونيو 2026 .</p>\n\n\n\n<p>الصحفي الفرنسي سانتي أونا نفى هذه التقارير ، مشيرًا إلى أن بنزيما لم يجدد عقده مع الاتحاد ، إذ لم يتلقَ أي عروض رسمية من إدارة النادي الجداوي حتى الآن .</p>\n\n\n\n<p>تجدر الإشارة إلى أن بنزيما ، الذي سيبلغ من العمر 38 عامًا في 19 ديسمبر الجاري ، خاض هذا الموسم 12 مباراة بمختلف المسابقات مع الاتحاد ، شهدت تسجيله 11 هدفًا .</p>\n",
      "image": "https://sc1.hihi2.com/wp-content/uploads/2025/12/hihi2-2025-12-11_07-19-39_376030-640x353.jpg",
      "categories": [
        "أخبار الاتحاد السعودي",
        "الاتحاد",
        "دوري روشن",
        "كريم بنزيما"
      ]
    }
  ]
}