{
  "month": "2025-12",
  "items": [
    {
      "id": "3552598",
      "title": "برشلونة فليك لا يفقد الايمان ..!",
      "link": "https://hihi2.com/2025/12/10/p3552598.html",
      "pubDate": "2025-12-10T20:21:40.000Z",
      "summary": "هاي كورة- سلطت صحيفة اس الاسبانية الضوء على ريمونتادات برشلونة هذا الموسم حيث فاز البارسا في 4 مباريات متتالية بعد التأخر في النتيجة بجميعها وذلك حدث للمرة الأولى في تاريخ النادي . الصحيفة قالت : ” برشلونة فليك لا يفقد الايمان ابدا ، رجال هانسي يجدوا صعوبة في العثور على السحر في اوروبا هذا الموسم […]",
      "description": "<div class=\"wp-block-image\">\n<figure class=\"aligncenter size-large\"><img fetchpriority=\"high\" decoding=\"async\" width=\"640\" height=\"360\" src=\"https://sc3.hihi2.com/wp-content/uploads/2025/12/hihi2-2025-12-10_23-19-56_038595-640x360.png?v=1765397999\" alt=\"\" class=\"wp-image-3552599\" srcset=\"https://sc4.hihi2.com/wp-content/uploads/2025/12/hihi2-2025-12-10_23-19-56_038595-640x360.png?v=1765397999 640w, https://hihi2.com/wp-content/uploads/2025/12/hihi2-2025-12-10_23-19-56_038595-300x169.png?v=1765397999 300w, https://hihi2.com/wp-content/uploads/2025/12/hihi2-2025-12-10_23-19-56_038595-200x112.png?v=1765397999 200w, https://hihi2.com/wp-content/uploads/2025/12/hihi2-2025-12-10_23-19-56_038595.png?v=1765397999 680w\" sizes=\"(max-width: 640px) 100vw, 640px\" /></figure>\n</div>\n\n\n<p>هاي كورة- سلطت صحيفة اس الاسبانية الضوء على ريمونتادات برشلونة هذا الموسم حيث فاز البارسا في 4 مباريات متتالية بعد التأخر في النتيجة بجميعها وذلك حدث للمرة الأولى في تاريخ النادي .</p>\n\n\n\n<p>الصحيفة قالت : &#8221; برشلونة فليك لا يفقد الايمان ابدا ، رجال هانسي يجدوا صعوبة في العثور على السحر في اوروبا هذا الموسم ، ومع ذلك لا يزالون يحتفظون بنفس الايمان دائما &#8220;</p>\n\n\n\n<p>&#8221; في عشرة ايام ، قلب البارسا 4 مباريات : الافيس ، اتلتيكو مدريد ، بيتيس  وآينتراخت فرانكفورت &#8220;</p>\n\n\n\n<p>&#8220;ولا يحدث ذلك إلا اذا كنت تؤمن بانه يمكنك ان تفعلها &#8221; .</p>\n",
      "image": "https://sc3.hihi2.com/wp-content/uploads/2025/12/hihi2-2025-12-10_23-19-56_038595-640x360.png?v=1765397999",
      "categories": [
        "أخبار برشلونة",
        "البارسا",
        "الدوري الإسباني",
        "برشلونة",
        "فليك"
      ]
    },
    {
      "id": "3552408",
      "title": "ألونسو يكشف سبب غياب مبابي عن تشكيلة ريال مدريد",
      "link": "https://hihi2.com/2025/12/10/p3552408.html",
      "pubDate": "2025-12-10T20:16:40.000Z",
      "summary": "هاي كورة- لم يتم اختيار كيليان مبابي ضمن التشكيلة الأساسية لريال مدريد للمرة الأولى هذا الموسم، حيث يواجه اللوس بلانكوس مانشستر سيتي. وتشير المصادر إلى أن مبابي يعاني من آلام في الركبة، وقد أوضح المدرب تشابي ألونسو الوضع قبل المباراة. قال ألونسو قبل المباراة: “كان إشراك كيليان مبابي أساسياً أمراً محفوفاً بالمخاطر، سنرى ما إذا […]",
      "description": "<div class=\"wp-block-image\">\n<figure class=\"aligncenter size-large\"><img decoding=\"async\" src=\"https://sc3.hihi2.com/wp-content/uploads/2025/12/hihi2-2025-12-10_23-14-58_844020-501x640.jpg?v=1765397700\" alt=\"\" class=\"wp-image-3552591\"/></figure>\n</div>\n\n\n<p></p>\n\n\n\n<p>هاي كورة- لم يتم اختيار كيليان مبابي ضمن التشكيلة الأساسية لريال مدريد للمرة الأولى هذا الموسم، حيث يواجه اللوس بلانكوس مانشستر سيتي.</p>\n\n\n\n<p>وتشير المصادر إلى أن مبابي يعاني من آلام في الركبة، وقد أوضح المدرب تشابي ألونسو الوضع قبل المباراة.</p>\n\n\n\n<p>قال ألونسو قبل المباراة: &#8220;كان إشراك كيليان مبابي أساسياً أمراً محفوفاً بالمخاطر، سنرى ما إذا كان مبابي سيلعب قليلاً في النهاية، لكنه لم يكن مرتاحاً&#8221;.</p>\n\n\n\n<p>&#8220;يقدم غونزالو غارسيا الكثير للفريق. وفي مثل هذه المواقف، تتاح الفرص. نحن نثق به&#8221;. </p>\n",
      "image": "https://sc3.hihi2.com/wp-content/uploads/2025/12/hihi2-2025-12-10_23-14-58_844020-501x640.jpg?v=1765397700",
      "categories": [
        "أخبار ريال مدريد",
        "الأخبار",
        "ريال مدريد",
        "مبابي"
      ]
    },
    {
      "id": "3552585",
      "title": "تصريحات الونسو قبل انطلاق مباراة مانشستر سيتي",
      "link": "https://hihi2.com/2025/12/10/p3552585.html",
      "pubDate": "2025-12-10T20:15:40.000Z",
      "summary": "هاي كورة- صرح تشابي الونسو ، مدرب ريال مدريد ، قبل انطلاق مباراة مانشستر سيتي قائلا : ” نحتاج اليوم إلى تقديم مباراة متكاملة من كل الجوانب “ ” يجب ان نكون منظمين وصلبين في الدفاع ومترابطين كذلك في الخطوط “ ” علينا اظهار شخصية قوية والحفاظ على ثبات في الاداء “ ” كما يجب […]",
      "description": "<div class=\"wp-block-image\">\n<figure class=\"aligncenter size-large\"><img decoding=\"async\" width=\"622\" height=\"640\" src=\"https://sc3.hihi2.com/wp-content/uploads/2025/12/hihi2-2025-12-10_23-14-14_924491-622x640.png?v=1765397658\" alt=\"\" class=\"wp-image-3552590\" srcset=\"https://sc2.hihi2.com/wp-content/uploads/2025/12/hihi2-2025-12-10_23-14-14_924491-622x640.png?v=1765397658 622w, https://hihi2.com/wp-content/uploads/2025/12/hihi2-2025-12-10_23-14-14_924491-292x300.png?v=1765397658 292w, https://hihi2.com/wp-content/uploads/2025/12/hihi2-2025-12-10_23-14-14_924491-194x200.png?v=1765397658 194w, https://hihi2.com/wp-content/uploads/2025/12/hihi2-2025-12-10_23-14-14_924491.png?v=1765397658 661w\" sizes=\"(max-width: 622px) 100vw, 622px\" /></figure>\n</div>\n\n\n<p>هاي كورة- صرح تشابي الونسو ، مدرب ريال مدريد ، قبل انطلاق مباراة مانشستر سيتي قائلا :</p>\n\n\n\n<p>&#8221; نحتاج اليوم إلى تقديم مباراة متكاملة من كل الجوانب &#8220;</p>\n\n\n\n<p>&#8221; يجب ان نكون منظمين وصلبين في الدفاع ومترابطين كذلك في الخطوط &#8220;</p>\n\n\n\n<p>&#8221; علينا اظهار شخصية قوية والحفاظ على ثبات في الاداء &#8220;</p>\n\n\n\n<p>&#8221; كما يجب ان نلعب بحماس يليق بمباراة من هذا المستوى &#8221; </p>\n\n\n\n<p>&#8221; يجب علينا ان ندرك أن لكل لحظة توقيتها &#8221; .</p>\n",
      "image": "https://sc3.hihi2.com/wp-content/uploads/2025/12/hihi2-2025-12-10_23-14-14_924491-622x640.png?v=1765397658",
      "categories": [
        "أخبار ريال مدريد",
        "الونسو",
        "ريال مدريد",
        "مانشستر سيتي"
      ]
    },
    {
      "id": "3552584",
      "title": "تصريحات بوتراغينيو قبل انطلاق مباراة مانشستر سيتي",
      "link": "https://hihi2.com/2025/12/10/p3552584.html",
      "pubDate": "2025-12-10T20:10:22.000Z",
      "summary": "هاي كورة- صرح ايميليو بوتراغينيو ، مدير العلاقات المؤسسية في ريال مدريد ، قبل انطلاق مباراة مانشستر سيتي قائلا : ” مان سيتي ، لا يوجد الكثير لنقوله ، اقصى صعوبة فريق قوي للغاية ، يملك العديد من نقاط القوة والفضائل ويجبرنا على تقديم مباراة شبه مثالية ، لكن هذا هو البرنابيو ودوري الابطال “ […]",
      "description": "<div class=\"wp-block-image\">\n<figure class=\"aligncenter size-full\"><img decoding=\"async\" width=\"500\" height=\"255\" src=\"https://sc5.hihi2.com/wp-content/uploads/2025/12/hihi2-2025-12-10_23-07-21_795646.jpg?v=1765397241\" alt=\"\" class=\"wp-image-3552586\" srcset=\"https://sc1.hihi2.com/wp-content/uploads/2025/12/hihi2-2025-12-10_23-07-21_795646.jpg?v=1765397241 500w, https://hihi2.com/wp-content/uploads/2025/12/hihi2-2025-12-10_23-07-21_795646-300x153.jpg?v=1765397241 300w, https://hihi2.com/wp-content/uploads/2025/12/hihi2-2025-12-10_23-07-21_795646-200x102.jpg?v=1765397241 200w\" sizes=\"(max-width: 500px) 100vw, 500px\" /></figure>\n</div>\n\n\n<p>هاي كورة- صرح ايميليو بوتراغينيو ، مدير العلاقات المؤسسية في ريال مدريد ، قبل انطلاق مباراة مانشستر سيتي قائلا :</p>\n\n\n\n<p>&#8221; مان سيتي ، لا يوجد الكثير لنقوله ، اقصى صعوبة  فريق قوي للغاية ، يملك العديد من نقاط القوة والفضائل  ويجبرنا على تقديم مباراة شبه مثالية ، لكن هذا هو البرنابيو ودوري الابطال &#8220;</p>\n\n\n\n<p>&#8221; نحن نعرف بعضنا جيدا ، هذه مباراة عظيمة ، العالم كله يترقب ما سيحدث الليلة ، الاجواء يصعب التفوق عليها ، ولدينا كل المكونات لرؤية مباراة كرة قدم رائعة ، ومن الطبيعي ان نراها &#8221; .</p>\n",
      "image": "https://sc5.hihi2.com/wp-content/uploads/2025/12/hihi2-2025-12-10_23-07-21_795646.jpg?v=1765397241",
      "categories": [
        "أخبار ريال مدريد",
        "أخبار مانشستر سيتي",
        "الريال",
        "السيتي",
        "دوري ابطال اوروبا",
        "ريال مدريد",
        "مانشستر سيتي"
      ]
    },
    {
      "id": "3552559",
      "title": "تصريحات غوارديولا قبل انطلاق مباراة ريال مدريد",
      "link": "https://hihi2.com/2025/12/10/p3552559.html",
      "pubDate": "2025-12-10T20:00:55.000Z",
      "summary": "هاي كورة- تنطلق مباراة ريال مدريد ضد مانشستر سيتي بعد دقائق على ملعب السانتياغو برنابيو ضمن منافسات الجولة السادسة في دور المجموعات ببطولة دوري ابطال اوروبا . وصرح بيب غوارديولا مدرب مانشستر سيتي قبل انطلاق المباراة قائلا : “هل تعرف كم مرة جئت الى هنا كلاعب ومدرب ؟ يمكنني ان احصل على مقصورة خاصة هنا” […]",
      "description": "<div class=\"wp-block-image\">\n<figure class=\"aligncenter size-full\"><img loading=\"lazy\" decoding=\"async\" width=\"500\" height=\"264\" src=\"https://sc4.hihi2.com/wp-content/uploads/2025/12/hihi2-2025-12-10_23-00-37_629205.jpg?v=1765396837\" alt=\"\" class=\"wp-image-3552580\" srcset=\"https://sc1.hihi2.com/wp-content/uploads/2025/12/hihi2-2025-12-10_23-00-37_629205.jpg?v=1765396837 500w, https://hihi2.com/wp-content/uploads/2025/12/hihi2-2025-12-10_23-00-37_629205-300x158.jpg?v=1765396837 300w, https://hihi2.com/wp-content/uploads/2025/12/hihi2-2025-12-10_23-00-37_629205-200x106.jpg?v=1765396837 200w\" sizes=\"auto, (max-width: 500px) 100vw, 500px\" /></figure>\n</div>\n\n\n<p>هاي كورة- تنطلق مباراة ريال مدريد ضد مانشستر سيتي بعد دقائق على ملعب السانتياغو برنابيو ضمن منافسات الجولة السادسة في دور المجموعات ببطولة دوري ابطال اوروبا .</p>\n\n\n\n<p>وصرح بيب غوارديولا مدرب مانشستر سيتي قبل انطلاق المباراة قائلا :</p>\n\n\n\n<p>&#8220;هل تعرف كم مرة جئت الى هنا كلاعب ومدرب ؟ يمكنني ان احصل على مقصورة خاصة هنا&#8221; .</p>\n\n\n\n<p>&#8221; نفس التشكيلة ، لعبنا بشكل جيد امام سندرلاند ، واعجبتني بعض الخطط ، وبالطبع يختلف التشكيل لأن ريال مدريد يلعب باسلوب مختلف ، لكنني اتطلع الى ذلك &#8221; .</p>\n\n\n\n<p>&#8221; خطوة بخطوة ، ريان صغير السن ، وهذه اول مرة يلعب فيها على اكبر المسارح ، لكنه يتمتع بشخصية قوية ، وبالطبع لديه شيء مميز في الثلث الأخير من الملعب ، ولهذا السبب اخترناه &#8220;</p>\n",
      "image": "https://sc4.hihi2.com/wp-content/uploads/2025/12/hihi2-2025-12-10_23-00-37_629205.jpg?v=1765396837",
      "categories": [
        "أخبار ريال مدريد",
        "دوري الابطال",
        "ريال مدريد",
        "غوارديولا",
        "مانشستر سيتي"
      ]
    },
    {
      "id": "3552572",
      "title": "تعليق فينيسيوس على غياب مبابي عن مواجهة مانشستر سيتي",
      "link": "https://hihi2.com/2025/12/10/p3552572.html",
      "pubDate": "2025-12-10T19:57:20.000Z",
      "summary": "هاي كورة- علق فينيسيوس جونيور نجم الريال على غياب مبابي عن مباراة مانشستر سيتي قائلا : ” مباراة اليوم مهمة لأننا نلعب على ارضنا امام جماهيرنا والفوز سيقربنا من التاهل بين افضل ثمانية وفوزنا هنا اليوم قد يحسن ادائنا هذا الموسم ” . ” نعلم اهمية مبابي ونامل ان يساعدنا قريبا ، اليوم علينا الثقة […]",
      "description": "<div class=\"wp-block-image\">\n<figure class=\"aligncenter size-large\"><img loading=\"lazy\" decoding=\"async\" width=\"640\" height=\"590\" src=\"https://sc4.hihi2.com/wp-content/uploads/2025/12/hihi2-2025-12-10_22-55-40_688623-640x590.png?v=1765396543\" alt=\"\" class=\"wp-image-3552576\" srcset=\"https://sc1.hihi2.com/wp-content/uploads/2025/12/hihi2-2025-12-10_22-55-40_688623-640x590.png?v=1765396543 640w, https://hihi2.com/wp-content/uploads/2025/12/hihi2-2025-12-10_22-55-40_688623-300x277.png?v=1765396543 300w, https://hihi2.com/wp-content/uploads/2025/12/hihi2-2025-12-10_22-55-40_688623-200x184.png?v=1765396543 200w, https://hihi2.com/wp-content/uploads/2025/12/hihi2-2025-12-10_22-55-40_688623.png?v=1765396543 666w\" sizes=\"auto, (max-width: 640px) 100vw, 640px\" /></figure>\n</div>\n\n\n<p>هاي كورة- علق فينيسيوس جونيور نجم الريال على غياب مبابي عن مباراة مانشستر سيتي قائلا :</p>\n\n\n\n<p>&#8221; مباراة اليوم مهمة لأننا نلعب على ارضنا امام جماهيرنا والفوز سيقربنا من التاهل بين افضل ثمانية وفوزنا هنا اليوم قد يحسن ادائنا هذا الموسم &#8221; . </p>\n\n\n\n<p>&#8221; نعلم اهمية مبابي ونامل ان يساعدنا قريبا ، اليوم علينا الثقة بغونزالو ورودريغو اللذين سيبذلان اقصى جهد من اجل تعويضه &#8221; .</p>\n",
      "image": "https://sc4.hihi2.com/wp-content/uploads/2025/12/hihi2-2025-12-10_22-55-40_688623-640x590.png?v=1765396543",
      "categories": [
        "أخبار ريال مدريد",
        "الدوري الإسباني",
        "الريال",
        "ريال مدريد",
        "فينيسيوس",
        "مبابي"
      ]
    },
    {
      "id": "3552573",
      "title": "راشفورد يعيد الحيوية لهجوم برشلونة",
      "link": "https://hihi2.com/2025/12/10/p3552573.html",
      "pubDate": "2025-12-10T19:56:59.000Z",
      "summary": "هاي كورة- دخل ماركوس راشفورد من مقاعد البدلاء في مباراة برشلونة ضد فرانكفورت ليحدث فارقًا واضحًا ، حيث أعاد النشاط إلى خط هجوم الفريق وصنع تمريرة حاسمة رائعة لكوندي . ويواصل النجم الإنجليزي تقديم مستويات قوية هذا الموسم ، إذ سجل في دوري أبطال أوروبا 4 أهداف وصنع 3 تمريرات حاسمة ، وفي الدوري الإسباني […]",
      "description": "<div class=\"wp-block-image\">\n<figure class=\"aligncenter size-large\"><img decoding=\"async\" src=\"https://sc1.hihi2.com/wp-content/uploads/2025/12/hihi2-2025-12-10_22-55-18_825437-640x640.png?v=1765396522\" alt=\"\" class=\"wp-image-3552575\"/></figure>\n</div>\n\n\n<p>هاي كورة- دخل ماركوس راشفورد من مقاعد البدلاء في مباراة برشلونة ضد فرانكفورت ليحدث فارقًا واضحًا ، حيث أعاد النشاط إلى خط هجوم الفريق وصنع تمريرة حاسمة رائعة لكوندي .</p>\n\n\n\n<p>ويواصل النجم الإنجليزي تقديم مستويات قوية هذا الموسم ، إذ سجل في دوري أبطال أوروبا 4 أهداف وصنع 3 تمريرات حاسمة ، وفي الدوري الإسباني أحرز هدفين وصنع 8 تمريرات ، ليصل مجموع مساهماته الهجومية إلى 17 هدفًا هذا الموسم ، ما يؤكد أهميته الكبيرة في خطط المدرب فليك.</p>\n",
      "image": "https://sc1.hihi2.com/wp-content/uploads/2025/12/hihi2-2025-12-10_22-55-18_825437-640x640.png?v=1765396522",
      "categories": [
        "أخبار برشلونة",
        "الدوري الإسباني",
        "برشلونة",
        "راشفورد",
        "فليك",
        "ماركوس راشفورد"
      ]
    },
    {
      "id": "3552568",
      "title": "تصريحات فينيسيوس قبل انطلاق مباراة مانشستر سيتي",
      "link": "https://hihi2.com/2025/12/10/p3552568.html",
      "pubDate": "2025-12-10T19:52:47.000Z",
      "summary": "هاي كورة- تنطلق مباراة ريال مدريد ضد مانشستر سيتي بعد دقائق على ملعب السانتياغو برنابيو ضمن منافسات الجولة السادسة في دور المجموعات ببطولة دوري ابطال اوروبا . وصرح فينيسيوس جونيور نجم الريال قبل انطلاق المباراة قائلا : ” نحن جميعا متحدون الجهاز الفني والمدرب والرئيس والجماهير واللاعبين “ ” اليوم يجب ان نلعب كفريق واحد […]",
      "description": "<div class=\"wp-block-image\">\n<figure class=\"aligncenter size-large\"><img loading=\"lazy\" decoding=\"async\" width=\"640\" height=\"638\" src=\"https://sc4.hihi2.com/wp-content/uploads/2025/12/hihi2-2025-12-10_22-51-38_471360-640x638.png?v=1765396301\" alt=\"\" class=\"wp-image-3552569\" srcset=\"https://sc1.hihi2.com/wp-content/uploads/2025/12/hihi2-2025-12-10_22-51-38_471360-640x638.png?v=1765396301 640w, https://hihi2.com/wp-content/uploads/2025/12/hihi2-2025-12-10_22-51-38_471360-300x300.png?v=1765396301 300w, https://hihi2.com/wp-content/uploads/2025/12/hihi2-2025-12-10_22-51-38_471360-200x200.png?v=1765396301 200w, https://hihi2.com/wp-content/uploads/2025/12/hihi2-2025-12-10_22-51-38_471360.png?v=1765396301 680w\" sizes=\"auto, (max-width: 640px) 100vw, 640px\" /></figure>\n</div>\n\n\n<p>هاي كورة- تنطلق مباراة ريال مدريد ضد مانشستر سيتي بعد دقائق على ملعب السانتياغو برنابيو ضمن منافسات الجولة السادسة في دور المجموعات ببطولة دوري ابطال اوروبا .</p>\n\n\n\n<p>وصرح فينيسيوس جونيور نجم الريال قبل انطلاق المباراة قائلا :</p>\n\n\n\n<p>&#8221; نحن جميعا متحدون الجهاز الفني والمدرب والرئيس والجماهير واللاعبين &#8220;</p>\n\n\n\n<p>&#8221; اليوم يجب ان نلعب كفريق واحد لنقدم مباراة كبيرة &#8220;</p>\n\n\n\n<p>&#8221; فمواجهة السيتي صعبة ، لكنها مباراة قادرة على تغيير الموسم ونحن نحب هذا التحدي &#8220;</p>\n",
      "image": "https://sc4.hihi2.com/wp-content/uploads/2025/12/hihi2-2025-12-10_22-51-38_471360-640x638.png?v=1765396301",
      "categories": [
        "أخبار مانشستر سيتي",
        "الدوري الانجليزي",
        "السيتي",
        "فينيسيوس",
        "مانشستر سيتي"
      ]
    },
    {
      "id": "3552557",
      "title": "نائب عمدة برشلونة ينفي تورط الأمن في اعمال الشغب في مباراة فرانكفورت",
      "link": "https://hihi2.com/2025/12/10/p3552557.html",
      "pubDate": "2025-12-10T19:48:52.000Z",
      "summary": "هاي كورة- شهدت مباراة برشلونة ضد اينتراخت فرانكفورت اعمال شغب من جماهير النادي الالماني بالمواجهة التي جمعت الفريقين مساء امس الاربعاء ضمن منافسات الجولة السادسة في دوري ابطال اوروبا . وفقا لصحيفة ماركا الاسبانية ، نفى البرت باتيي نائب عمدة بلدية برشلونة تورط امن البلدية في اعمال الشغب الأخيرة امام فرانكفورت . واكد باتيي ان […]",
      "description": "<div class=\"wp-block-image\">\n<figure class=\"aligncenter size-large\"><img loading=\"lazy\" decoding=\"async\" width=\"640\" height=\"426\" src=\"https://sc3.hihi2.com/wp-content/uploads/2025/12/hihi2-2025-12-10_22-47-46_639230-640x426.png?v=1765396069\" alt=\"\" class=\"wp-image-3552565\" srcset=\"https://sc2.hihi2.com/wp-content/uploads/2025/12/hihi2-2025-12-10_22-47-46_639230-640x426.png?v=1765396069 640w, https://hihi2.com/wp-content/uploads/2025/12/hihi2-2025-12-10_22-47-46_639230-300x200.png?v=1765396069 300w, https://hihi2.com/wp-content/uploads/2025/12/hihi2-2025-12-10_22-47-46_639230-200x133.png?v=1765396069 200w, https://hihi2.com/wp-content/uploads/2025/12/hihi2-2025-12-10_22-47-46_639230.png?v=1765396069 680w\" sizes=\"auto, (max-width: 640px) 100vw, 640px\" /></figure>\n</div>\n\n\n<p>هاي كورة- شهدت مباراة برشلونة ضد اينتراخت فرانكفورت اعمال شغب من جماهير النادي الالماني بالمواجهة التي جمعت الفريقين مساء امس الاربعاء ضمن منافسات الجولة السادسة في دوري ابطال اوروبا .</p>\n\n\n\n<p>وفقا لصحيفة ماركا الاسبانية ، نفى البرت باتيي نائب عمدة بلدية برشلونة تورط امن البلدية في اعمال الشغب الأخيرة امام فرانكفورت .</p>\n\n\n\n<p>واكد باتيي ان الأمن داخل الملعب من اختصاص الشرطة الاقليمية &#8220;موسوس&#8221; ، بينما الشرطة المحلية جاهزة دائما للتدخل عند الحاجة ، مع وجود تنسيق ثلاثي بين موسوس، الشرطة البلدية ، وخدمات امن النادي .</p>\n",
      "image": "https://sc3.hihi2.com/wp-content/uploads/2025/12/hihi2-2025-12-10_22-47-46_639230-640x426.png?v=1765396069",
      "categories": [
        "أخبار برشلونة",
        "الدوري الإسباني",
        "برشلونة",
        "دوري ابطال اوروبا",
        "فرانكفورت"
      ]
    },
    {
      "id": "3552555",
      "title": "تشكيلة نيوكاسل يونايتد ضد باير ليفركوزن",
      "link": "https://hihi2.com/2025/12/10/p3552555.html",
      "pubDate": "2025-12-10T19:46:07.000Z",
      "summary": "هاي كورة – أعلن إيدي هاو عن تشكيلة نيوكاسل يونايتد التي ستخوض مواجهة باير ليفركوزن الليلة في دوري أبطال أوروبا . ومن المقرر أن تقام المباراة على ملعب باي أرينا في الجولة السادسة من مرحلة الدوري .",
      "description": "<div class=\"wp-block-image\">\n<figure class=\"aligncenter size-full\"><img loading=\"lazy\" decoding=\"async\" width=\"500\" height=\"250\" src=\"https://sc3.hihi2.com/wp-content/uploads/2025/12/hihi2-2025-12-10_22-45-30_333633.png?v=1765395930\" alt=\"\" class=\"wp-image-3552562\" srcset=\"https://sc5.hihi2.com/wp-content/uploads/2025/12/hihi2-2025-12-10_22-45-30_333633.png?v=1765395930 500w, https://hihi2.com/wp-content/uploads/2025/12/hihi2-2025-12-10_22-45-30_333633-300x150.png?v=1765395930 300w, https://hihi2.com/wp-content/uploads/2025/12/hihi2-2025-12-10_22-45-30_333633-200x100.png?v=1765395930 200w\" sizes=\"auto, (max-width: 500px) 100vw, 500px\" /></figure>\n</div>\n\n\n<p>هاي كورة &#8211; أعلن إيدي هاو عن تشكيلة نيوكاسل يونايتد التي ستخوض مواجهة باير ليفركوزن الليلة في دوري أبطال أوروبا .</p>\n\n\n\n<p>ومن المقرر أن تقام المباراة على ملعب باي أرينا في الجولة السادسة من مرحلة الدوري .</p>\n\n\n<div class=\"wp-block-image\">\n<figure class=\"aligncenter size-large\"><img loading=\"lazy\" decoding=\"async\" width=\"512\" height=\"640\" src=\"https://sc5.hihi2.com/wp-content/uploads/2025/12/hihi2-2025-12-10_22-45-15_634048-512x640.jpeg?v=1765395915\" alt=\"\" class=\"wp-image-3552561\" srcset=\"https://sc1.hihi2.com/wp-content/uploads/2025/12/hihi2-2025-12-10_22-45-15_634048-512x640.jpeg?v=1765395915 512w, https://hihi2.com/wp-content/uploads/2025/12/hihi2-2025-12-10_22-45-15_634048-240x300.jpeg?v=1765395915 240w, https://hihi2.com/wp-content/uploads/2025/12/hihi2-2025-12-10_22-45-15_634048-160x200.jpeg?v=1765395915 160w, https://hihi2.com/wp-content/uploads/2025/12/hihi2-2025-12-10_22-45-15_634048.jpeg?v=1765395915 720w\" sizes=\"auto, (max-width: 512px) 100vw, 512px\" /></figure>\n</div>",
      "image": "https://sc3.hihi2.com/wp-content/uploads/2025/12/hihi2-2025-12-10_22-45-30_333633.png?v=1765395930",
      "categories": [
        "أخبار الكرة الالمانية",
        "أخبار دوري أبطال أوروبا",
        "أخبار نيوكاسل",
        "باير ليفركوزن",
        "دوري أبطال أوروبا",
        "نيوكاسل يونايتد"
      ]
    },
    {
      "id": "3552549",
      "title": "هنري ينتقد محمد صلاح",
      "link": "https://hihi2.com/2025/12/10/p3552549.html",
      "pubDate": "2025-12-10T19:43:41.000Z",
      "summary": "هاي كورة- انتقد المهاجم الفرنسي الاسبق تييري هنري اسطورة نادي ارسنال المهاجم المصري محمد صلاح لاعب نادي ليفربول بعد توتر علاقته مع المدرب الهولندي ارني سلوت و خروجه للصحافة للإعلان عن غضبه . تيري هنري قال انه هو الاخر كانت علاقته تتوتر بالمدرب ارسينن فينغر في ارسنال او بيب غوارديولا في برشلونة لكنه لم يكن […]",
      "description": "<div class=\"wp-block-image\">\n<figure class=\"aligncenter size-large\"><img loading=\"lazy\" decoding=\"async\" width=\"640\" height=\"331\" src=\"https://sc3.hihi2.com/wp-content/uploads/2025/12/hihi2-2025-12-10_22-42-26_544568-640x331.jpeg?v=1765395746\" alt=\"\" class=\"wp-image-3552552\" srcset=\"https://sc3.hihi2.com/wp-content/uploads/2025/12/hihi2-2025-12-10_22-42-26_544568-640x331.jpeg?v=1765395746 640w, https://hihi2.com/wp-content/uploads/2025/12/hihi2-2025-12-10_22-42-26_544568-300x155.jpeg?v=1765395746 300w, https://hihi2.com/wp-content/uploads/2025/12/hihi2-2025-12-10_22-42-26_544568-200x103.jpeg?v=1765395746 200w, https://hihi2.com/wp-content/uploads/2025/12/hihi2-2025-12-10_22-42-26_544568-768x397.jpeg?v=1765395746 768w, https://hihi2.com/wp-content/uploads/2025/12/hihi2-2025-12-10_22-42-26_544568-1536x793.jpeg?v=1765395746 1536w, https://hihi2.com/wp-content/uploads/2025/12/hihi2-2025-12-10_22-42-26_544568.jpeg?v=1765395746 1599w\" sizes=\"auto, (max-width: 640px) 100vw, 640px\" /></figure>\n</div>\n\n\n<p>هاي كورة- انتقد المهاجم الفرنسي الاسبق تييري هنري اسطورة نادي ارسنال المهاجم المصري محمد صلاح لاعب نادي ليفربول بعد توتر علاقته مع المدرب الهولندي ارني سلوت و خروجه للصحافة للإعلان عن غضبه .</p>\n\n\n\n<p>تيري هنري قال انه هو الاخر كانت علاقته تتوتر بالمدرب ارسينن فينغر في ارسنال او بيب غوارديولا في برشلونة لكنه لم يكن يخرج للصحافة ليعلن عن ذلك لأنه يتعين على اللاعب حماية النادي من خلال الحفاظ على السرية .</p>\n\n\n\n<p>المهاجم الفرنسي قال انه مهما بلغت حالة فقدان الاعصاب لا يتعين على اللاعب نشر غسيل ناديه امام الملا مضيفا انه يتفهم حالة صلاح لكن مصلحة الفريق تبقى اهم مهما كانت ظروف اللاعب .</p>\n",
      "image": "https://sc3.hihi2.com/wp-content/uploads/2025/12/hihi2-2025-12-10_22-42-26_544568-640x331.jpeg?v=1765395746",
      "categories": [
        "أخبار ليفربول",
        "ارسنال",
        "تييري هنري",
        "سلوت",
        "صلاح",
        "ليفربول",
        "محمد صلاح"
      ]
    },
    {
      "id": "3552548",
      "title": "احصائية سلبية لـ غوارديولا ضد الريال",
      "link": "https://hihi2.com/2025/12/10/p3552548.html",
      "pubDate": "2025-12-10T19:43:35.000Z",
      "summary": "هاي كورة- تنطلق مباراة مانشستر سيتي ضد ريال مدريد بعد دقائق على ملعب السانتياغو برنابيو ضمن منافسات الجولة السادسة في دور المجموعات ببطولة دوري ابطال اوروبا . بيب غوارديولا مدرب مانشستر سيتي لم يحقق اي فوز في آخر 4 مباريات له لمواجهة ريال مدريد (تعادلان وخسارتان ) ، بينما استقبلت شباكه 10 اهداف في تلك […]",
      "description": "<div class=\"wp-block-image\">\n<figure class=\"aligncenter size-full\"><img loading=\"lazy\" decoding=\"async\" width=\"500\" height=\"250\" src=\"https://sc5.hihi2.com/wp-content/uploads/2025/12/hihi2-2025-12-10_22-42-52_787366.jpg?v=1765395772\" alt=\"\" class=\"wp-image-3552553\" srcset=\"https://sc4.hihi2.com/wp-content/uploads/2025/12/hihi2-2025-12-10_22-42-52_787366.jpg?v=1765395772 500w, https://hihi2.com/wp-content/uploads/2025/12/hihi2-2025-12-10_22-42-52_787366-300x150.jpg?v=1765395772 300w, https://hihi2.com/wp-content/uploads/2025/12/hihi2-2025-12-10_22-42-52_787366-200x100.jpg?v=1765395772 200w\" sizes=\"auto, (max-width: 500px) 100vw, 500px\" /></figure>\n</div>\n\n\n<p>هاي كورة- تنطلق مباراة مانشستر سيتي ضد ريال مدريد بعد دقائق على ملعب السانتياغو برنابيو ضمن منافسات الجولة السادسة في دور المجموعات ببطولة دوري ابطال اوروبا .</p>\n\n\n\n<p>بيب غوارديولا مدرب مانشستر سيتي لم يحقق اي فوز في آخر 4 مباريات له لمواجهة ريال مدريد (تعادلان وخسارتان ) ، بينما استقبلت شباكه 10 اهداف في تلك المباريات الاربع ( بمعدل 2.5 هدف في المباراة الواحدة ) .</p>\n",
      "image": "https://sc5.hihi2.com/wp-content/uploads/2025/12/hihi2-2025-12-10_22-42-52_787366.jpg?v=1765395772",
      "categories": [
        "أخبار ريال مدريد",
        "الدوري الإسباني",
        "الريال",
        "ريال مدريد",
        "غوارديولا"
      ]
    },
    {
      "id": "3552547",
      "title": "دي يونغ يثير التساؤل حوله ..!",
      "link": "https://hihi2.com/2025/12/10/p3552547.html",
      "pubDate": "2025-12-10T19:32:42.000Z",
      "summary": "هاي كورة – راي خاص بالصحفي خافي ميغيل عبر صحيفة اس الاسبانية ” رغم حجم تأثيره في الوسط ، لا يزال فرينكي دي يونغ دون اهداف هذا الموسم ، وهو امر يثير التساؤل بالنظر الى مهاراته المتنوعة ، اذ لم يسجل سوى 19 هدفا في 276 مباراة بقميص برشلونة ” .",
      "description": "<div class=\"wp-block-image\">\n<figure class=\"aligncenter size-full\"><img loading=\"lazy\" decoding=\"async\" width=\"500\" height=\"253\" src=\"https://sc3.hihi2.com/wp-content/uploads/2025/12/hihi2-2025-12-10_22-32-00_612048.jpg?v=1765395120\" alt=\"\" class=\"wp-image-3552550\" srcset=\"https://sc3.hihi2.com/wp-content/uploads/2025/12/hihi2-2025-12-10_22-32-00_612048.jpg?v=1765395120 500w, https://hihi2.com/wp-content/uploads/2025/12/hihi2-2025-12-10_22-32-00_612048-300x152.jpg?v=1765395120 300w, https://hihi2.com/wp-content/uploads/2025/12/hihi2-2025-12-10_22-32-00_612048-200x101.jpg?v=1765395120 200w\" sizes=\"auto, (max-width: 500px) 100vw, 500px\" /></figure>\n</div>\n\n\n<p class=\"has-vivid-red-color has-text-color has-link-color wp-elements-13d867e0393bb7f74f7a01ac573cb8e1\"><strong>هاي كورة – راي خاص بالصحفي خافي ميغيل عبر صحيفة اس الاسبانية</strong></p>\n\n\n\n<p>&#8221; رغم حجم تأثيره في الوسط ، لا يزال فرينكي دي يونغ دون اهداف هذا الموسم ، وهو امر يثير التساؤل بالنظر الى مهاراته المتنوعة ، اذ لم يسجل سوى 19 هدفا في 276 مباراة بقميص برشلونة &#8221; .</p>\n",
      "image": "https://sc3.hihi2.com/wp-content/uploads/2025/12/hihi2-2025-12-10_22-32-00_612048.jpg?v=1765395120",
      "categories": [
        "أخبار برشلونة",
        "الدوري الإسباني",
        "برشلونة",
        "دي يونغ"
      ]
    },
    {
      "id": "3552534",
      "title": "برشلونة يحصي الأضرار في منطقة جماهير فرانكفورت",
      "link": "https://hihi2.com/2025/12/10/p3552534.html",
      "pubDate": "2025-12-10T19:28:15.000Z",
      "summary": "هاي كورة- تسببت جماهير آينتراخت فرانكفورت في اضرار كبيرة داخل المنطقة المخصصة لهم في ملعب الكامب نو بالمباراة التي جمعت الفريقين مساء امس الثلاثاء ضمن منافسات دوري ابطال اوروبا . وفقا لصحيفة اس الاسبانية دمرت جماهير فرانكفورت الحاجز الفاصل مع جماهر البارسا ، واقتلعت مقاعد وقامت بتكسيرها ، إضافة الى تخريب الحمامات عمدا عبر التبول […]",
      "description": "<div class=\"wp-block-image\">\n<figure class=\"aligncenter size-large\"><img loading=\"lazy\" decoding=\"async\" width=\"480\" height=\"640\" src=\"https://sc1.hihi2.com/wp-content/uploads/2025/12/hihi2-2025-12-10_22-26-43_691617-480x640.png?v=1765394807\" alt=\"\" class=\"wp-image-3552544\" srcset=\"https://sc4.hihi2.com/wp-content/uploads/2025/12/hihi2-2025-12-10_22-26-43_691617-480x640.png?v=1765394807 480w, https://hihi2.com/wp-content/uploads/2025/12/hihi2-2025-12-10_22-26-43_691617-225x300.png?v=1765394807 225w, https://hihi2.com/wp-content/uploads/2025/12/hihi2-2025-12-10_22-26-43_691617-150x200.png?v=1765394807 150w, https://hihi2.com/wp-content/uploads/2025/12/hihi2-2025-12-10_22-26-43_691617.png?v=1765394807 675w\" sizes=\"auto, (max-width: 480px) 100vw, 480px\" /></figure>\n</div>\n\n\n<p>هاي كورة- تسببت جماهير آينتراخت فرانكفورت في اضرار كبيرة داخل المنطقة المخصصة لهم في ملعب الكامب نو بالمباراة التي جمعت الفريقين مساء امس الثلاثاء ضمن منافسات دوري ابطال اوروبا .</p>\n\n\n\n<p>وفقا لصحيفة اس الاسبانية دمرت جماهير فرانكفورت الحاجز الفاصل مع جماهر البارسا ، واقتلعت مقاعد وقامت بتكسيرها ، إضافة الى تخريب الحمامات عمدا عبر التبول خارج المراحيض وتغطية المكان بملصقات .</p>\n\n\n\n<p>كما اشعلت الجماهير 7 قنابل دخانية والقت اكوابا مملوءة بالكحول باتجاه جماهير برشلونة في الاسفل ، ما تسبب في حالة من الاشمئزاز والتوتر داخل المدرجات .</p>\n",
      "image": "https://sc1.hihi2.com/wp-content/uploads/2025/12/hihi2-2025-12-10_22-26-43_691617-480x640.png?v=1765394807",
      "categories": [
        "أخبار برشلونة",
        "البارسا",
        "الدوري الإسباني",
        "برشلونة",
        "فرانكفورت"
      ]
    },
    {
      "id": "3552536",
      "title": "تشكيلة اتلتيك بيلباو الرسمية ضد باريس سان جيرمان",
      "link": "https://hihi2.com/2025/12/10/p3552536.html",
      "pubDate": "2025-12-10T19:18:14.000Z",
      "summary": "هاي كورة- اعلن ارنسو فالفيردي مدرب اتلتيك بيلباو عن تشكيلة فريقه الرسمية ضد باريس سان جيرمان مساء اليوم الاربعاء ضمن منافسات الجولة السادسة في دوري ابطال اوروبا . وجاءت التشكيلة كالتالي :",
      "description": "<div class=\"wp-block-image\">\n<figure class=\"aligncenter size-full\"><img loading=\"lazy\" decoding=\"async\" width=\"500\" height=\"253\" src=\"https://sc1.hihi2.com/wp-content/uploads/2025/12/hihi2-2025-12-10_22-17-45_319672.jpg?v=1765394265\" alt=\"\" class=\"wp-image-3552541\" srcset=\"https://sc1.hihi2.com/wp-content/uploads/2025/12/hihi2-2025-12-10_22-17-45_319672.jpg?v=1765394265 500w, https://hihi2.com/wp-content/uploads/2025/12/hihi2-2025-12-10_22-17-45_319672-300x152.jpg?v=1765394265 300w, https://hihi2.com/wp-content/uploads/2025/12/hihi2-2025-12-10_22-17-45_319672-200x101.jpg?v=1765394265 200w\" sizes=\"auto, (max-width: 500px) 100vw, 500px\" /></figure>\n</div>\n\n\n<p>هاي كورة- اعلن ارنسو فالفيردي مدرب اتلتيك بيلباو عن تشكيلة فريقه الرسمية ضد باريس سان جيرمان مساء اليوم الاربعاء ضمن منافسات الجولة السادسة في دوري ابطال اوروبا .</p>\n\n\n\n<p>وجاءت التشكيلة كالتالي : </p>\n\n\n<div class=\"wp-block-image\">\n<figure class=\"aligncenter size-large\"><img loading=\"lazy\" decoding=\"async\" width=\"512\" height=\"640\" src=\"https://sc4.hihi2.com/wp-content/uploads/2025/12/hihi2-2025-12-10_22-15-50_909967-512x640.png?v=1765394155\" alt=\"\" class=\"wp-image-3552540\" srcset=\"https://sc4.hihi2.com/wp-content/uploads/2025/12/hihi2-2025-12-10_22-15-50_909967-512x640.png?v=1765394155 512w, https://hihi2.com/wp-content/uploads/2025/12/hihi2-2025-12-10_22-15-50_909967-240x300.png?v=1765394155 240w, https://hihi2.com/wp-content/uploads/2025/12/hihi2-2025-12-10_22-15-50_909967-160x200.png?v=1765394155 160w, https://hihi2.com/wp-content/uploads/2025/12/hihi2-2025-12-10_22-15-50_909967-768x960.png?v=1765394155 768w, https://hihi2.com/wp-content/uploads/2025/12/hihi2-2025-12-10_22-15-50_909967.png?v=1765394155 1080w\" sizes=\"auto, (max-width: 512px) 100vw, 512px\" /></figure>\n</div>",
      "image": "https://sc1.hihi2.com/wp-content/uploads/2025/12/hihi2-2025-12-10_22-17-45_319672.jpg?v=1765394265",
      "categories": [
        "أخبار باريس سان جرمان",
        "اتلتيك بيلباو",
        "باريس سان جيرمان",
        "دوري ابطال اوروبا"
      ]
    },
    {
      "id": "3552533",
      "title": "تشكيلة بوروسيا دورتموند ضد بودو غليمت في دوري أبطال أوروبا",
      "link": "https://hihi2.com/2025/12/10/p3552533.html",
      "pubDate": "2025-12-10T19:11:24.000Z",
      "summary": "هاي كورة – أعلن نيكو كوفاتش مدرب بوروسيا دورتموند عن تشكيلة الفريق الرسمية التي ستخوض مباراة بودو/غليمت . وسيتواجه الفريقان مساء اليوم في الجولة السادسة من مرحلة الدوري في دوري أبطال أوروبا.",
      "description": "<div class=\"wp-block-image\">\n<figure class=\"aligncenter size-full\"><img loading=\"lazy\" decoding=\"async\" width=\"500\" height=\"250\" src=\"https://sc5.hihi2.com/wp-content/uploads/2025/12/hihi2-2025-12-10_22-10-35_976372.png?v=1765393836\" alt=\"\" class=\"wp-image-3552538\" srcset=\"https://sc4.hihi2.com/wp-content/uploads/2025/12/hihi2-2025-12-10_22-10-35_976372.png?v=1765393836 500w, https://hihi2.com/wp-content/uploads/2025/12/hihi2-2025-12-10_22-10-35_976372-300x150.png?v=1765393836 300w, https://hihi2.com/wp-content/uploads/2025/12/hihi2-2025-12-10_22-10-35_976372-200x100.png?v=1765393836 200w\" sizes=\"auto, (max-width: 500px) 100vw, 500px\" /></figure>\n</div>\n\n\n<p>هاي كورة &#8211; أعلن نيكو كوفاتش مدرب بوروسيا دورتموند عن تشكيلة الفريق الرسمية التي ستخوض مباراة بودو/غليمت .</p>\n\n\n\n<p>وسيتواجه الفريقان مساء اليوم في الجولة السادسة من مرحلة الدوري في دوري أبطال أوروبا.</p>\n\n\n\n<figure class=\"wp-block-image size-large\"><img loading=\"lazy\" decoding=\"async\" width=\"512\" height=\"640\" src=\"https://sc3.hihi2.com/wp-content/uploads/2025/12/hihi2-2025-12-10_22-10-08_366662-512x640.jpg?v=1765393808\" alt=\"\" class=\"wp-image-3552537\" srcset=\"https://sc1.hihi2.com/wp-content/uploads/2025/12/hihi2-2025-12-10_22-10-08_366662-512x640.jpg?v=1765393808 512w, https://hihi2.com/wp-content/uploads/2025/12/hihi2-2025-12-10_22-10-08_366662-240x300.jpg?v=1765393808 240w, https://hihi2.com/wp-content/uploads/2025/12/hihi2-2025-12-10_22-10-08_366662-160x200.jpg?v=1765393808 160w, https://hihi2.com/wp-content/uploads/2025/12/hihi2-2025-12-10_22-10-08_366662.jpg?v=1765393808 720w\" sizes=\"auto, (max-width: 512px) 100vw, 512px\" /></figure>\n",
      "image": "https://sc5.hihi2.com/wp-content/uploads/2025/12/hihi2-2025-12-10_22-10-35_976372.png?v=1765393836",
      "categories": [
        "أخبار بروسيا دورتموند",
        "أخبار دوري أبطال أوروبا",
        "بوروسيا دورتموند",
        "دوري أبطال أوروبا"
      ]
    },
    {
      "id": "3552524",
      "title": "الرسم التكتيكي لتشكيلة باريس سان جيرمان ضد بيلباو",
      "link": "https://hihi2.com/2025/12/10/p3552524.html",
      "pubDate": "2025-12-10T19:08:41.000Z",
      "summary": "هاي كورة- تنطلق مباراة باريس سان جيرمان ضد اتلتيك بيلباو بعد دقائق على ملعب سان ماميس ضمن منافسات الجولة السادسة في دوري ابطال اوروبا . الرسم التكتيكي لتشكيلة باريس سان جيرمان: الرسم التكتيكي لتشكيلة اتلتيك بيلباو :",
      "description": "<div class=\"wp-block-image\">\n<figure class=\"aligncenter size-full\"><img loading=\"lazy\" decoding=\"async\" width=\"500\" height=\"257\" src=\"https://sc5.hihi2.com/wp-content/uploads/2025/12/hihi2-2025-12-10_22-06-53_588951.jpg?v=1765393613\" alt=\"\" class=\"wp-image-3552527\" srcset=\"https://sc1.hihi2.com/wp-content/uploads/2025/12/hihi2-2025-12-10_22-06-53_588951.jpg?v=1765393613 500w, https://hihi2.com/wp-content/uploads/2025/12/hihi2-2025-12-10_22-06-53_588951-300x154.jpg?v=1765393613 300w, https://hihi2.com/wp-content/uploads/2025/12/hihi2-2025-12-10_22-06-53_588951-200x103.jpg?v=1765393613 200w\" sizes=\"auto, (max-width: 500px) 100vw, 500px\" /></figure>\n</div>\n\n\n<p>هاي كورة- تنطلق مباراة باريس سان جيرمان ضد اتلتيك بيلباو بعد دقائق على ملعب سان ماميس ضمن منافسات الجولة السادسة في دوري ابطال اوروبا .</p>\n\n\n\n<p>الرسم التكتيكي لتشكيلة باريس سان جيرمان: </p>\n\n\n<div class=\"wp-block-image\">\n<figure class=\"aligncenter size-full\"><img loading=\"lazy\" decoding=\"async\" width=\"478\" height=\"515\" src=\"https://sc1.hihi2.com/wp-content/uploads/2025/12/hihi2-2025-12-10_22-08-12_616278.png?v=1765393695\" alt=\"\" class=\"wp-image-3552531\" srcset=\"https://sc5.hihi2.com/wp-content/uploads/2025/12/hihi2-2025-12-10_22-08-12_616278.png?v=1765393695 478w, https://hihi2.com/wp-content/uploads/2025/12/hihi2-2025-12-10_22-08-12_616278-278x300.png?v=1765393695 278w, https://hihi2.com/wp-content/uploads/2025/12/hihi2-2025-12-10_22-08-12_616278-186x200.png?v=1765393695 186w\" sizes=\"auto, (max-width: 478px) 100vw, 478px\" /></figure>\n</div>\n\n\n<p>الرسم التكتيكي لتشكيلة اتلتيك بيلباو :</p>\n\n\n<div class=\"wp-block-image\">\n<figure class=\"aligncenter size-full\"><img loading=\"lazy\" decoding=\"async\" width=\"469\" height=\"522\" src=\"https://sc4.hihi2.com/wp-content/uploads/2025/12/hihi2-2025-12-10_22-07-59_423676.png?v=1765393682\" alt=\"\" class=\"wp-image-3552529\" srcset=\"https://sc1.hihi2.com/wp-content/uploads/2025/12/hihi2-2025-12-10_22-07-59_423676.png?v=1765393682 469w, https://hihi2.com/wp-content/uploads/2025/12/hihi2-2025-12-10_22-07-59_423676-270x300.png?v=1765393682 270w, https://hihi2.com/wp-content/uploads/2025/12/hihi2-2025-12-10_22-07-59_423676-180x200.png?v=1765393682 180w\" sizes=\"auto, (max-width: 469px) 100vw, 469px\" /></figure>\n</div>",
      "image": "https://sc5.hihi2.com/wp-content/uploads/2025/12/hihi2-2025-12-10_22-06-53_588951.jpg?v=1765393613",
      "categories": [
        "أخبار باريس سان جرمان",
        "باريس سان جيرمان",
        "بيلباو",
        "دوري ابطال اوروبا"
      ]
    },
    {
      "id": "3552514",
      "title": "تشكيلة يوفنتوس الرسمية ضد بافوس في دوري أبطال أوروبا",
      "link": "https://hihi2.com/2025/12/10/p3552514.html",
      "pubDate": "2025-12-10T19:08:32.000Z",
      "summary": "هاي كورة – كشف لوتشيانو سباليتي عن اختياراته الرسمية لمباراة بافوس التي ستقام الليلة في دوري أبطال أوروبا. وسيلتقي الفريقان ضمن الجولة السادسة من مرحلة الدوري في البطولة الأوروبية .",
      "description": "<div class=\"wp-block-image\">\n<figure class=\"aligncenter size-full\"><img loading=\"lazy\" decoding=\"async\" width=\"500\" height=\"250\" src=\"https://sc3.hihi2.com/wp-content/uploads/2025/12/hihi2-2025-12-10_22-05-48_569058.jpg?v=1765393548\" alt=\"\" class=\"wp-image-3552525\" srcset=\"https://sc3.hihi2.com/wp-content/uploads/2025/12/hihi2-2025-12-10_22-05-48_569058.jpg?v=1765393548 500w, https://hihi2.com/wp-content/uploads/2025/12/hihi2-2025-12-10_22-05-48_569058-300x150.jpg?v=1765393548 300w, https://hihi2.com/wp-content/uploads/2025/12/hihi2-2025-12-10_22-05-48_569058-200x100.jpg?v=1765393548 200w\" sizes=\"auto, (max-width: 500px) 100vw, 500px\" /></figure>\n</div>\n\n\n<p>هاي كورة &#8211; كشف لوتشيانو سباليتي عن اختياراته الرسمية لمباراة بافوس التي ستقام الليلة في دوري أبطال أوروبا.</p>\n\n\n\n<p>وسيلتقي الفريقان ضمن الجولة السادسة من مرحلة الدوري في البطولة الأوروبية .</p>\n\n\n<div class=\"wp-block-image\">\n<figure class=\"aligncenter size-large\"><img loading=\"lazy\" decoding=\"async\" width=\"640\" height=\"640\" src=\"https://sc1.hihi2.com/wp-content/uploads/2025/12/hihi2-2025-12-10_22-06-48_872460-640x640.jpg?v=1765393608\" alt=\"\" class=\"wp-image-3552526\" srcset=\"https://sc3.hihi2.com/wp-content/uploads/2025/12/hihi2-2025-12-10_22-06-48_872460-640x640.jpg?v=1765393608 640w, https://hihi2.com/wp-content/uploads/2025/12/hihi2-2025-12-10_22-06-48_872460-300x300.jpg?v=1765393608 300w, https://hihi2.com/wp-content/uploads/2025/12/hihi2-2025-12-10_22-06-48_872460-200x200.jpg?v=1765393608 200w, https://hihi2.com/wp-content/uploads/2025/12/hihi2-2025-12-10_22-06-48_872460.jpg?v=1765393608 680w\" sizes=\"auto, (max-width: 640px) 100vw, 640px\" /></figure>\n</div>",
      "image": "https://sc3.hihi2.com/wp-content/uploads/2025/12/hihi2-2025-12-10_22-05-48_569058.jpg?v=1765393548",
      "categories": [
        "أخبار دوري أبطال أوروبا",
        "أخبار يوفنتوس",
        "بافوس",
        "دوري أبطال أوروبا",
        "يوفنتوس"
      ]
    },
    {
      "id": "3552499",
      "title": "تشكيلة باريس سان جيرمان ضد اتلتيك بيلباو في دوري الابطال",
      "link": "https://hihi2.com/2025/12/10/p3552499.html",
      "pubDate": "2025-12-10T19:04:38.000Z",
      "summary": "هاي كورة- اعلن لويس انريكي مدرب باريس سان جيرمان عن تشكيلة فريقه الرسمية للقاء اتلتيك بيلباو ، مساء اليوم الاربعاء ، ضمن منافسات الجولة السادسة من منافسات دوري ابطال اوروبا . وجاءت التشكيلة كالتالي :",
      "description": "<div class=\"wp-block-image\">\n<figure class=\"aligncenter size-full\"><img loading=\"lazy\" decoding=\"async\" width=\"500\" height=\"252\" src=\"https://sc5.hihi2.com/wp-content/uploads/2025/12/hihi2-2025-12-10_22-03-56_167585.jpg?v=1765393436\" alt=\"\" class=\"wp-image-3552520\" srcset=\"https://sc3.hihi2.com/wp-content/uploads/2025/12/hihi2-2025-12-10_22-03-56_167585.jpg?v=1765393436 500w, https://hihi2.com/wp-content/uploads/2025/12/hihi2-2025-12-10_22-03-56_167585-300x151.jpg?v=1765393436 300w, https://hihi2.com/wp-content/uploads/2025/12/hihi2-2025-12-10_22-03-56_167585-200x101.jpg?v=1765393436 200w\" sizes=\"auto, (max-width: 500px) 100vw, 500px\" /></figure>\n</div>\n\n\n<p>هاي كورة- اعلن لويس انريكي مدرب باريس سان جيرمان عن تشكيلة فريقه الرسمية للقاء اتلتيك بيلباو ، مساء اليوم الاربعاء ، ضمن منافسات الجولة السادسة من منافسات دوري ابطال اوروبا .</p>\n\n\n\n<p>وجاءت التشكيلة كالتالي :</p>\n\n\n<div class=\"wp-block-image\">\n<figure class=\"aligncenter size-large\"><img loading=\"lazy\" decoding=\"async\" width=\"457\" height=\"640\" src=\"https://sc3.hihi2.com/wp-content/uploads/2025/12/hihi2-2025-12-10_22-02-13_398265-457x640.png?v=1765393339\" alt=\"\" class=\"wp-image-3552517\" srcset=\"https://sc1.hihi2.com/wp-content/uploads/2025/12/hihi2-2025-12-10_22-02-13_398265-457x640.png?v=1765393339 457w, https://hihi2.com/wp-content/uploads/2025/12/hihi2-2025-12-10_22-02-13_398265-214x300.png?v=1765393339 214w, https://hihi2.com/wp-content/uploads/2025/12/hihi2-2025-12-10_22-02-13_398265-143x200.png?v=1765393339 143w, https://hihi2.com/wp-content/uploads/2025/12/hihi2-2025-12-10_22-02-13_398265-768x1077.png?v=1765393339 768w, https://hihi2.com/wp-content/uploads/2025/12/hihi2-2025-12-10_22-02-13_398265-1096x1536.png?v=1765393339 1096w, https://hihi2.com/wp-content/uploads/2025/12/hihi2-2025-12-10_22-02-13_398265.png?v=1765393339 1170w\" sizes=\"auto, (max-width: 457px) 100vw, 457px\" /></figure>\n</div>",
      "image": "https://sc5.hihi2.com/wp-content/uploads/2025/12/hihi2-2025-12-10_22-03-56_167585.jpg?v=1765393436",
      "categories": [
        "أخبار باريس سان جرمان",
        "باريس سان جيرمان",
        "بيلباو",
        "دوري ابطال اوروبا"
      ]
    },
    {
      "id": "3552508",
      "title": "الرسم التكتيكي لتشكيلة مانشستر سيتي ضد الريال",
      "link": "https://hihi2.com/2025/12/10/p3552508.html",
      "pubDate": "2025-12-10T19:00:58.000Z",
      "summary": "هاي كورة- اعلن بيب غوارديولا مدرب مانشستر سيتي ، تشكيلة فريقه الرسمية لمواجهة ريال مدريد ، على ملعب سانتياغو برنابيو ، ضمن منافسات الجولة السادسة من مسابقة دوري ابطال اوروبا . اليكم تكتيك السيتي :",
      "description": "<div class=\"wp-block-image\">\n<figure class=\"aligncenter size-large\"><img decoding=\"async\" src=\"https://sc1.hihi2.com/wp-content/uploads/2025/12/hihi2-2025-12-10_21-59-22_208636-427x640.png?v=1765393175\" alt=\"\" class=\"wp-image-3552511\"/></figure>\n</div>\n\n\n<p>هاي كورة- اعلن بيب غوارديولا مدرب مانشستر سيتي ، تشكيلة فريقه الرسمية لمواجهة ريال مدريد ، على ملعب سانتياغو برنابيو ، ضمن منافسات الجولة السادسة من مسابقة دوري ابطال اوروبا .</p>\n\n\n\n<p>اليكم تكتيك السيتي :</p>\n\n\n\n<figure class=\"wp-block-image size-large\"><img loading=\"lazy\" decoding=\"async\" width=\"512\" height=\"640\" src=\"https://sc1.hihi2.com/wp-content/uploads/2025/12/hihi2-2025-12-10_21-57-53_926996-512x640.png?v=1765393079\" alt=\"\" class=\"wp-image-3552509\" srcset=\"https://sc4.hihi2.com/wp-content/uploads/2025/12/hihi2-2025-12-10_21-57-53_926996-512x640.png?v=1765393079 512w, https://hihi2.com/wp-content/uploads/2025/12/hihi2-2025-12-10_21-57-53_926996-240x300.png?v=1765393079 240w, https://hihi2.com/wp-content/uploads/2025/12/hihi2-2025-12-10_21-57-53_926996-160x200.png?v=1765393079 160w, https://hihi2.com/wp-content/uploads/2025/12/hihi2-2025-12-10_21-57-53_926996-768x960.png?v=1765393079 768w, https://hihi2.com/wp-content/uploads/2025/12/hihi2-2025-12-10_21-57-53_926996.png?v=1765393079 1080w\" sizes=\"auto, (max-width: 512px) 100vw, 512px\" /></figure>\n",
      "image": "https://sc1.hihi2.com/wp-content/uploads/2025/12/hihi2-2025-12-10_21-59-22_208636-427x640.png?v=1765393175",
      "categories": [
        "أخبار دوري أبطال أوروبا",
        "أخبار ريال مدريد",
        "أخبار مانشستر سيتي",
        "الريال",
        "السيتي",
        "دوري ابطال اوروبا",
        "ريال مدريد",
        "مانشستر سيتي"
      ]
    },
    {
      "id": "3552507",
      "title": "تشكيلة أرسنال الرسمية ضد كلوب بروج",
      "link": "https://hihi2.com/2025/12/10/p3552507.html",
      "pubDate": "2025-12-10T19:00:17.000Z",
      "summary": "هاي كورة – أعلن ميكيل أرتيتا عن تشكيلة أرسنال الرسمية لمباراة كلوب بروج في الجولة السادسة من دوري أبطال أوروبا . ويحتاج أرسنال للانتصار في المباراة من أجل البقاء على قمة الترتيب العام للبطولة .",
      "description": "<div class=\"wp-block-image\">\n<figure class=\"aligncenter size-full\"><img loading=\"lazy\" decoding=\"async\" width=\"500\" height=\"250\" src=\"https://sc4.hihi2.com/wp-content/uploads/2025/12/hihi2-2025-12-10_21-59-29_462279.png?v=1765393169\" alt=\"\" class=\"wp-image-3552512\" srcset=\"https://sc3.hihi2.com/wp-content/uploads/2025/12/hihi2-2025-12-10_21-59-29_462279.png?v=1765393169 500w, https://hihi2.com/wp-content/uploads/2025/12/hihi2-2025-12-10_21-59-29_462279-300x150.png?v=1765393169 300w, https://hihi2.com/wp-content/uploads/2025/12/hihi2-2025-12-10_21-59-29_462279-200x100.png?v=1765393169 200w\" sizes=\"auto, (max-width: 500px) 100vw, 500px\" /></figure>\n</div>\n\n\n<p>هاي كورة &#8211; أعلن ميكيل أرتيتا عن تشكيلة أرسنال الرسمية لمباراة كلوب بروج في الجولة السادسة من دوري أبطال أوروبا .</p>\n\n\n\n<p>ويحتاج أرسنال للانتصار في المباراة من أجل البقاء على قمة الترتيب العام للبطولة .</p>\n\n\n<div class=\"wp-block-image\">\n<figure class=\"aligncenter size-large\"><img loading=\"lazy\" decoding=\"async\" width=\"640\" height=\"640\" src=\"https://sc5.hihi2.com/wp-content/uploads/2025/12/hihi2-2025-12-10_21-59-20_281503-640x640.png?v=1765393161\" alt=\"\" class=\"wp-image-3552510\" srcset=\"https://sc1.hihi2.com/wp-content/uploads/2025/12/hihi2-2025-12-10_21-59-20_281503-640x640.png?v=1765393161 640w, https://hihi2.com/wp-content/uploads/2025/12/hihi2-2025-12-10_21-59-20_281503-300x300.png?v=1765393161 300w, https://hihi2.com/wp-content/uploads/2025/12/hihi2-2025-12-10_21-59-20_281503-200x200.png?v=1765393161 200w, https://hihi2.com/wp-content/uploads/2025/12/hihi2-2025-12-10_21-59-20_281503.png?v=1765393161 680w\" sizes=\"auto, (max-width: 640px) 100vw, 640px\" /></figure>\n</div>",
      "image": "https://sc4.hihi2.com/wp-content/uploads/2025/12/hihi2-2025-12-10_21-59-29_462279.png?v=1765393169",
      "categories": [
        "أخبار ارسنال",
        "أخبار دوري أبطال أوروبا",
        "أرسنال",
        "دوري أبطال أوروبا",
        "كلوب بروج"
      ]
    },
    {
      "id": "3552501",
      "title": "الرسم التكتيكي لتشكيلة ريال مدريد ضد مانشستر سيتي",
      "link": "https://hihi2.com/2025/12/10/p3552501.html",
      "pubDate": "2025-12-10T18:55:44.000Z",
      "summary": "هاي كورة- اعلن تشابي الونسو مدرب ريال مدريد ، تشكيلة فريقه الرسمية لمواجهة مانشستر سيتي ، على ملعب سانتياغو برنابيو ، ضمن منافسات الجولة السادسة من مسابقة دوري ابطال اوروبا . اليكم تكتيك الريال :",
      "description": "<div class=\"wp-block-image\">\n<figure class=\"aligncenter size-large\"><img decoding=\"async\" src=\"https://sc1.hihi2.com/wp-content/uploads/2025/12/hihi2-2025-12-10_21-54-09_339073-512x640.png?v=1765392853\" alt=\"\" class=\"wp-image-3552504\"/></figure>\n</div>\n\n\n<p>هاي كورة- اعلن تشابي الونسو مدرب ريال مدريد ، تشكيلة فريقه الرسمية لمواجهة مانشستر سيتي ، على ملعب سانتياغو برنابيو ، ضمن منافسات الجولة السادسة من مسابقة دوري ابطال اوروبا .</p>\n\n\n\n<p>اليكم تكتيك الريال :</p>\n\n\n\n<figure class=\"wp-block-image size-large\"><img loading=\"lazy\" decoding=\"async\" width=\"512\" height=\"640\" src=\"https://sc4.hihi2.com/wp-content/uploads/2025/12/hihi2-2025-12-10_21-53-14_203563-512x640.png?v=1765392797\" alt=\"\" class=\"wp-image-3552502\" srcset=\"https://sc2.hihi2.com/wp-content/uploads/2025/12/hihi2-2025-12-10_21-53-14_203563-512x640.png?v=1765392797 512w, https://hihi2.com/wp-content/uploads/2025/12/hihi2-2025-12-10_21-53-14_203563-240x300.png?v=1765392797 240w, https://hihi2.com/wp-content/uploads/2025/12/hihi2-2025-12-10_21-53-14_203563-160x200.png?v=1765392797 160w, https://hihi2.com/wp-content/uploads/2025/12/hihi2-2025-12-10_21-53-14_203563.png?v=1765392797 544w\" sizes=\"auto, (max-width: 512px) 100vw, 512px\" /></figure>\n\n\n\n<p></p>\n",
      "image": "https://sc1.hihi2.com/wp-content/uploads/2025/12/hihi2-2025-12-10_21-54-09_339073-512x640.png?v=1765392853",
      "categories": [
        "أخبار دوري أبطال أوروبا",
        "أخبار ريال مدريد",
        "أخبار مانشستر سيتي",
        "الريال",
        "السيتي",
        "دوري ابطال اوروبا",
        "ريال مدريد",
        "مانشستر سيتي"
      ]
    },
    {
      "id": "3552491",
      "title": "تشكيلة مانشستر سيتي الرسمية للقاء ريال مدريد",
      "link": "https://hihi2.com/2025/12/10/p3552491.html",
      "pubDate": "2025-12-10T18:52:06.000Z",
      "summary": "هاي كورة- اعلن بيب غوارديولا مدرب مانشستر سيتي ، تشكيلة فريقه الرسمية لمواجهة ريال مدريد ، على ملعب سانتياغو برنابيو ، ضمن منافسات الجولة السادسة من مسابقة دوري ابطال اوروبا . اليكم تشكيلة السيتي : دوناروما أورايلي — غفارديول — دياز — نونيس بيرناردو سيلفا — عونزاليس — فيل فودين جيرمي دوكو — هالاند — […]",
      "description": "<div class=\"wp-block-image\">\n<figure class=\"aligncenter size-large\"><img loading=\"lazy\" decoding=\"async\" width=\"640\" height=\"334\" src=\"https://sc1.hihi2.com/wp-content/uploads/2025/12/hihi2-2025-12-10_21-50-18_229943-640x334.jpeg?v=1765392618\" alt=\"\" class=\"wp-image-3552496\" srcset=\"https://sc3.hihi2.com/wp-content/uploads/2025/12/hihi2-2025-12-10_21-50-18_229943-640x334.jpeg?v=1765392618 640w, https://hihi2.com/wp-content/uploads/2025/12/hihi2-2025-12-10_21-50-18_229943-300x156.jpeg?v=1765392618 300w, https://hihi2.com/wp-content/uploads/2025/12/hihi2-2025-12-10_21-50-18_229943-200x104.jpeg?v=1765392618 200w, https://hihi2.com/wp-content/uploads/2025/12/hihi2-2025-12-10_21-50-18_229943-768x400.jpeg?v=1765392618 768w, https://hihi2.com/wp-content/uploads/2025/12/hihi2-2025-12-10_21-50-18_229943-1536x801.jpeg?v=1765392618 1536w, https://hihi2.com/wp-content/uploads/2025/12/hihi2-2025-12-10_21-50-18_229943.jpeg?v=1765392618 1600w\" sizes=\"auto, (max-width: 640px) 100vw, 640px\" /></figure>\n</div>\n\n\n<p>هاي كورة- اعلن بيب غوارديولا مدرب مانشستر سيتي ، تشكيلة فريقه الرسمية لمواجهة ريال مدريد ، على ملعب سانتياغو برنابيو ، ضمن منافسات الجولة السادسة من مسابقة دوري ابطال اوروبا .</p>\n\n\n\n<p>اليكم تشكيلة السيتي :</p>\n\n\n\n<p>دوناروما</p>\n\n\n\n<p>أورايلي — غفارديول — دياز — نونيس</p>\n\n\n\n<p>بيرناردو سيلفا — عونزاليس — فيل فودين</p>\n\n\n\n<p>جيرمي دوكو — هالاند — ريان شرقي</p>\n\n\n\n<figure class=\"wp-block-image size-large\"><img loading=\"lazy\" decoding=\"async\" width=\"417\" height=\"640\" src=\"https://sc1.hihi2.com/wp-content/uploads/2025/12/hihi2-2025-12-10_21-50-28_652827-417x640.png?v=1765392631\" alt=\"\" class=\"wp-image-3552497\" srcset=\"https://sc1.hihi2.com/wp-content/uploads/2025/12/hihi2-2025-12-10_21-50-28_652827-417x640.png?v=1765392631 417w, https://hihi2.com/wp-content/uploads/2025/12/hihi2-2025-12-10_21-50-28_652827-195x300.png?v=1765392631 195w, https://hihi2.com/wp-content/uploads/2025/12/hihi2-2025-12-10_21-50-28_652827-130x200.png?v=1765392631 130w, https://hihi2.com/wp-content/uploads/2025/12/hihi2-2025-12-10_21-50-28_652827.png?v=1765392631 443w\" sizes=\"auto, (max-width: 417px) 100vw, 417px\" /></figure>\n",
      "image": "https://sc1.hihi2.com/wp-content/uploads/2025/12/hihi2-2025-12-10_21-50-18_229943-640x334.jpeg?v=1765392618",
      "categories": [
        "أخبار دوري أبطال أوروبا",
        "أخبار ريال مدريد",
        "أخبار مانشستر سيتي",
        "الريال",
        "السيتي",
        "دوري ابطال اوروبا",
        "ريال مدريد",
        "غوارديولا",
        "مانشستر سيتي"
      ]
    },
    {
      "id": "3552463",
      "title": "صور .. طوابير تاريخية في مدينة غوادالاخارا لشراء تذاكر مباراة برشلونة",
      "link": "https://hihi2.com/2025/12/10/p3552463.html",
      "pubDate": "2025-12-10T18:50:33.000Z",
      "summary": "هاي كورة- اسفرت قرعة دور الـ 32 في كاس ملك اسبانيا عن مواجهة خاصة بين برشلونة وغوادالاخارا يوم الثلاثاء القادم . وفي اليوم الأول من طرح التذاكر للبيع اصطف طوابير من المشجعين لشراء تذاكر المباراة في مدينة غوادالاخارا . الصور :",
      "description": "<div class=\"wp-block-image\">\n<figure class=\"aligncenter size-full\"><img loading=\"lazy\" decoding=\"async\" width=\"433\" height=\"555\" src=\"https://sc4.hihi2.com/wp-content/uploads/2025/12/hihi2-2025-12-10_21-47-57_409035.png?v=1765392480\" alt=\"\" class=\"wp-image-3552490\" srcset=\"https://sc4.hihi2.com/wp-content/uploads/2025/12/hihi2-2025-12-10_21-47-57_409035.png?v=1765392480 433w, https://hihi2.com/wp-content/uploads/2025/12/hihi2-2025-12-10_21-47-57_409035-234x300.png?v=1765392480 234w, https://hihi2.com/wp-content/uploads/2025/12/hihi2-2025-12-10_21-47-57_409035-156x200.png?v=1765392480 156w\" sizes=\"auto, (max-width: 433px) 100vw, 433px\" /></figure>\n</div>\n\n\n<p>هاي كورة- اسفرت قرعة دور الـ 32 في كاس ملك اسبانيا عن مواجهة خاصة بين برشلونة وغوادالاخارا يوم الثلاثاء القادم .</p>\n\n\n\n<p>وفي اليوم الأول من طرح التذاكر للبيع اصطف طوابير من المشجعين لشراء تذاكر المباراة في مدينة غوادالاخارا . </p>\n\n\n\n<p>الصور :</p>\n\n\n<div class=\"wp-block-image\">\n<figure class=\"aligncenter size-full\"><img loading=\"lazy\" decoding=\"async\" width=\"433\" height=\"580\" src=\"https://sc1.hihi2.com/wp-content/uploads/2025/12/hihi2-2025-12-10_21-46-57_851370.png?v=1765392420\" alt=\"\" class=\"wp-image-3552487\" srcset=\"https://sc1.hihi2.com/wp-content/uploads/2025/12/hihi2-2025-12-10_21-46-57_851370.png?v=1765392420 433w, https://hihi2.com/wp-content/uploads/2025/12/hihi2-2025-12-10_21-46-57_851370-224x300.png?v=1765392420 224w, https://hihi2.com/wp-content/uploads/2025/12/hihi2-2025-12-10_21-46-57_851370-149x200.png?v=1765392420 149w\" sizes=\"auto, (max-width: 433px) 100vw, 433px\" /></figure>\n</div>\n\n<div class=\"wp-block-image\">\n<figure class=\"aligncenter size-full\"><img loading=\"lazy\" decoding=\"async\" width=\"429\" height=\"555\" src=\"https://sc1.hihi2.com/wp-content/uploads/2025/12/hihi2-2025-12-10_21-49-54_230425.jpg?v=1765392594\" alt=\"\" class=\"wp-image-3552494\" srcset=\"https://sc1.hihi2.com/wp-content/uploads/2025/12/hihi2-2025-12-10_21-49-54_230425.jpg?v=1765392594 429w, https://hihi2.com/wp-content/uploads/2025/12/hihi2-2025-12-10_21-49-54_230425-232x300.jpg?v=1765392594 232w, https://hihi2.com/wp-content/uploads/2025/12/hihi2-2025-12-10_21-49-54_230425-155x200.jpg?v=1765392594 155w\" sizes=\"auto, (max-width: 429px) 100vw, 429px\" /></figure>\n</div>\n\n<div class=\"wp-block-image\">\n<figure class=\"aligncenter size-full\"><img loading=\"lazy\" decoding=\"async\" width=\"426\" height=\"551\" src=\"https://sc4.hihi2.com/wp-content/uploads/2025/12/hihi2-2025-12-10_21-50-02_139283.jpg?v=1765392602\" alt=\"\" class=\"wp-image-3552495\" srcset=\"https://sc5.hihi2.com/wp-content/uploads/2025/12/hihi2-2025-12-10_21-50-02_139283.jpg?v=1765392602 426w, https://hihi2.com/wp-content/uploads/2025/12/hihi2-2025-12-10_21-50-02_139283-232x300.jpg?v=1765392602 232w, https://hihi2.com/wp-content/uploads/2025/12/hihi2-2025-12-10_21-50-02_139283-155x200.jpg?v=1765392602 155w\" sizes=\"auto, (max-width: 426px) 100vw, 426px\" /></figure>\n</div>",
      "image": "https://sc4.hihi2.com/wp-content/uploads/2025/12/hihi2-2025-12-10_21-47-57_409035.png?v=1765392480",
      "categories": [
        "أخبار برشلونة",
        "البارسا",
        "الدوري الإسباني",
        "برشلونة",
        "كاس ملك اسبانا"
      ]
    },
    {
      "id": "3552455",
      "title": "تشكيلة ريال مدريد الرسمية امام مانشستر سيتي",
      "link": "https://hihi2.com/2025/12/10/p3552455.html",
      "pubDate": "2025-12-10T18:46:13.000Z",
      "summary": "هاي كورة- اعلن تشابي الونسو مدرب ريال مدريد ، تشكيلة فريقه الرسمية لمواجهة مانشستر سيتي ، على ملعب سانتياغو برنابيو ، ضمن منافسات الجولة السادسة من مسابقة دوري ابطال اوروبا . اليكم تشكيلة الريال: تيبو كورتواكاريراس – روديجر – أسينسيو – فالفيرديبيلينجهام – تشواميني – سيبايوسفينيسيوس – غونزالو – رودريجو",
      "description": "<div class=\"wp-block-image\">\n<figure class=\"aligncenter size-large\"><img loading=\"lazy\" decoding=\"async\" width=\"640\" height=\"333\" src=\"https://sc1.hihi2.com/wp-content/uploads/2025/12/hihi2-2025-12-10_21-25-58_127127-640x333.jpeg?v=1765391158\" alt=\"\" class=\"wp-image-3552458\" srcset=\"https://sc3.hihi2.com/wp-content/uploads/2025/12/hihi2-2025-12-10_21-25-58_127127-640x333.jpeg?v=1765391158 640w, https://hihi2.com/wp-content/uploads/2025/12/hihi2-2025-12-10_21-25-58_127127-300x156.jpeg?v=1765391158 300w, https://hihi2.com/wp-content/uploads/2025/12/hihi2-2025-12-10_21-25-58_127127-200x104.jpeg?v=1765391158 200w, https://hihi2.com/wp-content/uploads/2025/12/hihi2-2025-12-10_21-25-58_127127-768x399.jpeg?v=1765391158 768w, https://hihi2.com/wp-content/uploads/2025/12/hihi2-2025-12-10_21-25-58_127127-1536x799.jpeg?v=1765391158 1536w, https://hihi2.com/wp-content/uploads/2025/12/hihi2-2025-12-10_21-25-58_127127.jpeg?v=1765391158 1600w\" sizes=\"auto, (max-width: 640px) 100vw, 640px\" /></figure>\n</div>\n\n\n<p>هاي كورة- اعلن تشابي الونسو مدرب ريال مدريد ، تشكيلة فريقه الرسمية لمواجهة مانشستر سيتي ، على ملعب سانتياغو برنابيو ، ضمن منافسات الجولة السادسة من مسابقة دوري ابطال اوروبا .</p>\n\n\n\n<p>اليكم تشكيلة الريال:</p>\n\n\n\n<p>تيبو كورتوا<br>كاريراس &#8211; روديجر &#8211; أسينسيو &#8211; فالفيردي<br>بيلينجهام &#8211; تشواميني &#8211; سيبايوس<br>فينيسيوس &#8211; غونزالو &#8211; رودريجو</p>\n\n\n\n<figure class=\"wp-block-image size-large\"><img loading=\"lazy\" decoding=\"async\" width=\"480\" height=\"640\" src=\"https://sc3.hihi2.com/wp-content/uploads/2025/12/hihi2-2025-12-10_21-45-44_108545-480x640.png?v=1765392347\" alt=\"\" class=\"wp-image-3552485\" srcset=\"https://sc5.hihi2.com/wp-content/uploads/2025/12/hihi2-2025-12-10_21-45-44_108545-480x640.png?v=1765392347 480w, https://hihi2.com/wp-content/uploads/2025/12/hihi2-2025-12-10_21-45-44_108545-225x300.png?v=1765392347 225w, https://hihi2.com/wp-content/uploads/2025/12/hihi2-2025-12-10_21-45-44_108545-150x200.png?v=1765392347 150w, https://hihi2.com/wp-content/uploads/2025/12/hihi2-2025-12-10_21-45-44_108545.png?v=1765392347 510w\" sizes=\"auto, (max-width: 480px) 100vw, 480px\" /></figure>\n",
      "image": "https://sc1.hihi2.com/wp-content/uploads/2025/12/hihi2-2025-12-10_21-25-58_127127-640x333.jpeg?v=1765391158",
      "categories": [
        "أخبار دوري أبطال أوروبا",
        "أخبار ريال مدريد",
        "أخبار مانشستر سيتي",
        "الريال",
        "السيتي",
        "الونسو",
        "دوري ابطال اوروبا",
        "ريال مدريد",
        "مانشستر سيتي"
      ]
    }
  ]
}