{
  "month": "2025-12",
  "items": [
    {
      "id": "3570113",
      "title": "ماذا يعني احتفال لامين يامال ضد فياريال ؟",
      "link": "https://hihi2.com/2025/12/22/p3570113.html",
      "pubDate": "2025-12-22T20:19:51.000Z",
      "summary": "هاي كورة- كشفت صحيفة ماركا الاسبانية عن معنى احتفال لامين يامال لاعب برشلونة بهدفه امام فياريال مساء الاحد ضمن منافسات الجولة الـ 17 في الدوري الاسباني . احتفال لامين يامال الذي قوبل بصيحات الاستهجان ليس استفزازا لمشجعي فياريال ، بل هو تكريم لسلسلة الرسوم المتحركة والمانغا الشهيرة اينازوما إليفن ، وخاصة احتفالا بالحركة المميزة لكيدو […]",
      "description": "<div class=\"wp-block-image\">\n<figure class=\"aligncenter size-large\"><img fetchpriority=\"high\" decoding=\"async\" width=\"640\" height=\"421\" src=\"https://sc3.hihi2.com/wp-content/uploads/2025/12/hihi2-2025-12-22_23-18-31_062897-640x421.png?v=1766434715\" alt=\"\" class=\"wp-image-3570119\" srcset=\"https://sc2.hihi2.com/wp-content/uploads/2025/12/hihi2-2025-12-22_23-18-31_062897-640x421.png?v=1766434715 640w, https://hihi2.com/wp-content/uploads/2025/12/hihi2-2025-12-22_23-18-31_062897-300x197.png?v=1766434715 300w, https://hihi2.com/wp-content/uploads/2025/12/hihi2-2025-12-22_23-18-31_062897-200x131.png?v=1766434715 200w, https://hihi2.com/wp-content/uploads/2025/12/hihi2-2025-12-22_23-18-31_062897.png?v=1766434715 680w\" sizes=\"(max-width: 640px) 100vw, 640px\" /></figure>\n</div>\n\n\n<p>هاي كورة- كشفت صحيفة ماركا الاسبانية عن معنى احتفال لامين يامال لاعب برشلونة بهدفه امام فياريال مساء الاحد ضمن منافسات الجولة الـ 17 في الدوري الاسباني .</p>\n\n\n\n<p>احتفال لامين يامال الذي قوبل بصيحات الاستهجان ليس استفزازا لمشجعي فياريال ، بل هو تكريم لسلسلة الرسوم المتحركة والمانغا الشهيرة اينازوما إليفن ، وخاصة احتفالا بالحركة المميزة لكيدو يوتو .</p>\n",
      "image": "https://sc3.hihi2.com/wp-content/uploads/2025/12/hihi2-2025-12-22_23-18-31_062897-640x421.png?v=1766434715",
      "categories": [
        "أخبار برشلونة",
        "البارسا",
        "الدوري الإسباني",
        "برشلونة",
        "فياريال",
        "لامين"
      ]
    },
    {
      "id": "3570111",
      "title": "غيوكيريس يتحدث عن تجربته مع أرسنال",
      "link": "https://hihi2.com/2025/12/22/p3570111.html",
      "pubDate": "2025-12-22T20:16:17.000Z",
      "summary": "هاي كورة – أكد فيكتور غيوكيريس أنه يسعى دائمًا لتقديم كل ما لديه مع أرسنال، حيث يريد الفوز مع الفريق بالبطولات المختلفة. وقال غيوكيريس في تصريحاته التي نشرها موقع تريبيونا: “أسعى دائمًا لتقديم أفضل ما لدي في كل مباراة، التأقلم مع النادي والدوري الجديد، وفهم دوري، هي أمور أساسية”. “في الوقت الحالي نلعب بشكل جيد […]",
      "description": "<div class=\"wp-block-image\">\n<figure class=\"aligncenter size-full\"><img decoding=\"async\" width=\"500\" height=\"250\" src=\"https://sc5.hihi2.com/wp-content/uploads/2025/12/hihi2-2025-12-22_23-15-45_969057.png?v=1766434546\" alt=\"\" class=\"wp-image-3570116\" srcset=\"https://sc3.hihi2.com/wp-content/uploads/2025/12/hihi2-2025-12-22_23-15-45_969057.png?v=1766434546 500w, https://hihi2.com/wp-content/uploads/2025/12/hihi2-2025-12-22_23-15-45_969057-300x150.png?v=1766434546 300w, https://hihi2.com/wp-content/uploads/2025/12/hihi2-2025-12-22_23-15-45_969057-200x100.png?v=1766434546 200w\" sizes=\"(max-width: 500px) 100vw, 500px\" /></figure>\n</div>\n\n\n<p>هاي كورة &#8211; أكد فيكتور غيوكيريس أنه يسعى دائمًا لتقديم كل ما لديه مع أرسنال، حيث يريد الفوز مع الفريق بالبطولات المختلفة.</p>\n\n\n\n<p>وقال غيوكيريس في تصريحاته التي نشرها موقع تريبيونا: &#8220;أسعى دائمًا لتقديم أفضل ما لدي في كل مباراة، التأقلم مع النادي والدوري الجديد، وفهم دوري، هي أمور أساسية&#8221;.</p>\n\n\n\n<p>&#8220;في الوقت الحالي نلعب بشكل جيد ونحقق نتائج متميزة، ومركزنا قوي في الدوري الإنجليزي الممتاز ودوري أبطال أوروبا، يجب أن نواصل العمل بنفس الأسلوب&#8221;.</p>\n",
      "image": "https://sc5.hihi2.com/wp-content/uploads/2025/12/hihi2-2025-12-22_23-15-45_969057.png?v=1766434546",
      "categories": [
        "أخبار ارسنال",
        "أرسنال",
        "الدوري الإنجليزي",
        "فيكتور غيوكيريس"
      ]
    },
    {
      "id": "3570101",
      "title": "النصر يتجاوز أزمة القيد بعد تسوية مستحقات لابورت",
      "link": "https://hihi2.com/2025/12/22/p3570101.html",
      "pubDate": "2025-12-22T20:13:51.000Z",
      "summary": "هاي كورة: نجحت إدارة نادي النصر في إنهاء أزمة إيقاف القيد التي كانت تهدد الفريق خلال الأيام الماضية، بعد التوصل لاتفاق رسمي مع المدافع إيمريك لابورت بشأن مستحقاته المتأخرة. وبهذا الإجراء، قام الاتحاد الدولي لكرة القدم “فيفا” برفع اسم النصر من قائمة الأندية المحظورة من تسجيل لاعبين جدد خلال فترة الانتقالات الشتوية القادمة، بعدما تم […]",
      "description": "\n<figure class=\"wp-block-image size-large\"><img decoding=\"async\" width=\"640\" height=\"320\" src=\"https://sc3.hihi2.com/wp-content/uploads/2025/08/hihi2-2025-08-19_17-12-40_437661-e1755612830551-640x320.png\" alt=\"\" class=\"wp-image-3346523\" srcset=\"https://sc5.hihi2.com/wp-content/uploads/2025/08/hihi2-2025-08-19_17-12-40_437661-e1755612830551-640x320.png?v=1755612763 640w, https://hihi2.com/wp-content/uploads/2025/08/hihi2-2025-08-19_17-12-40_437661-e1755612830551-300x150.png?v=1755612763 300w, https://hihi2.com/wp-content/uploads/2025/08/hihi2-2025-08-19_17-12-40_437661-e1755612830551-200x100.png?v=1755612763 200w, https://hihi2.com/wp-content/uploads/2025/08/hihi2-2025-08-19_17-12-40_437661-e1755612830551-768x384.png?v=1755612763 768w, https://hihi2.com/wp-content/uploads/2025/08/hihi2-2025-08-19_17-12-40_437661-e1755612830551.png?v=1755612763 848w\" sizes=\"(max-width: 640px) 100vw, 640px\" /></figure>\n\n\n\n<p>هاي كورة:  نجحت إدارة نادي النصر في إنهاء أزمة إيقاف القيد التي كانت تهدد الفريق خلال الأيام الماضية، بعد التوصل لاتفاق رسمي مع المدافع إيمريك لابورت بشأن مستحقاته المتأخرة.</p>\n\n\n\n<p>وبهذا الإجراء، قام الاتحاد الدولي لكرة القدم &#8220;فيفا&#8221; برفع اسم النصر من قائمة الأندية المحظورة من تسجيل لاعبين جدد خلال فترة الانتقالات الشتوية القادمة، بعدما تم تسوية جميع الالتزامات المالية الخاصة بلا بورت في الساعات الأخيرة، ما يضمن للنادي حرية تعزيز صفوفه دون أي عوائق.</p>\n",
      "image": "https://sc3.hihi2.com/wp-content/uploads/2025/08/hihi2-2025-08-19_17-12-40_437661-e1755612830551-640x320.png",
      "categories": [
        "أخبار النصر السعودي",
        "اخبار النصر",
        "النصر",
        "نادي النصر"
      ]
    },
    {
      "id": "3570106",
      "title": "فكرة برشلونة مع بيدري",
      "link": "https://hihi2.com/2025/12/22/p3570106.html",
      "pubDate": "2025-12-22T20:12:18.000Z",
      "summary": "هاي كورة- كشفت اذاعة RAC1 عن فكرة برشلونة مع لاعبه بيدري غونزاليس الذي غاب عن مباراة فياريال بسبب الاجهاد العضلي . النادي يستهدف استعادة بيدري في مباراة اسبانيول يوم 3 يناير ضمن منافسات الليغا ، والفكرة هي ان يتدرب بيدري مع المجموعة بعد عودته من اجازته ( يوم الاثنين القادم ) وبالتالي سيكون جاهزا للقاء […]",
      "description": "<div class=\"wp-block-image\">\n<figure class=\"aligncenter size-large\"><img loading=\"lazy\" decoding=\"async\" width=\"512\" height=\"640\" src=\"https://sc5.hihi2.com/wp-content/uploads/2025/12/hihi2-2025-12-22_23-11-26_110430-512x640.png?v=1766434290\" alt=\"\" class=\"wp-image-3570108\" srcset=\"https://sc3.hihi2.com/wp-content/uploads/2025/12/hihi2-2025-12-22_23-11-26_110430-512x640.png?v=1766434290 512w, https://hihi2.com/wp-content/uploads/2025/12/hihi2-2025-12-22_23-11-26_110430-240x300.png?v=1766434290 240w, https://hihi2.com/wp-content/uploads/2025/12/hihi2-2025-12-22_23-11-26_110430-160x200.png?v=1766434290 160w, https://hihi2.com/wp-content/uploads/2025/12/hihi2-2025-12-22_23-11-26_110430.png?v=1766434290 544w\" sizes=\"auto, (max-width: 512px) 100vw, 512px\" /></figure>\n</div>\n\n\n<p>هاي كورة- كشفت اذاعة RAC1 عن فكرة برشلونة مع لاعبه بيدري غونزاليس الذي غاب عن مباراة فياريال بسبب الاجهاد العضلي .</p>\n\n\n\n<p>النادي يستهدف استعادة بيدري في مباراة اسبانيول يوم 3 يناير ضمن منافسات الليغا ، والفكرة هي ان يتدرب بيدري مع المجموعة بعد عودته من اجازته ( يوم الاثنين القادم ) وبالتالي سيكون جاهزا للقاء بسبب حصوله على عدد ايام كافي من الراحة .</p>\n",
      "image": "https://sc5.hihi2.com/wp-content/uploads/2025/12/hihi2-2025-12-22_23-11-26_110430-512x640.png?v=1766434290",
      "categories": [
        "أخبار برشلونة",
        "البارسا",
        "الدوري الإسباني",
        "برشلونة",
        "بيدري"
      ]
    },
    {
      "id": "3570104",
      "title": "إصابة جديدة لنيمار",
      "link": "https://hihi2.com/2025/12/22/p3570104.html",
      "pubDate": "2025-12-22T20:11:32.000Z",
      "summary": "هاي كورة – تعرض نيمار دا سيلفا لإصابة جديدة قد تمنعه من الانضمام لمنتخب البرازيل المشارك في كأس العالم 2026. وذكرت صحيفة ليكيب أن نيمار أصيب في ركبته اليسرى، وقد تقرر أن يخضع لعملية جراحية في الغضروف الهلالي. وأكدت الصحيفة الفرنسية أن غياب نجم سانتوس قد يمتد إلى شهر فبراير القادم، وهو ما يثير الشكوك […]",
      "description": "<div class=\"wp-block-image\">\n<figure class=\"aligncenter size-full\"><img loading=\"lazy\" decoding=\"async\" width=\"500\" height=\"250\" src=\"https://sc4.hihi2.com/wp-content/uploads/2025/12/hihi2-2025-12-22_23-10-29_805303.png?v=1766434230\" alt=\"\" class=\"wp-image-3570107\" srcset=\"https://sc4.hihi2.com/wp-content/uploads/2025/12/hihi2-2025-12-22_23-10-29_805303.png?v=1766434230 500w, https://hihi2.com/wp-content/uploads/2025/12/hihi2-2025-12-22_23-10-29_805303-300x150.png?v=1766434230 300w, https://hihi2.com/wp-content/uploads/2025/12/hihi2-2025-12-22_23-10-29_805303-200x100.png?v=1766434230 200w\" sizes=\"auto, (max-width: 500px) 100vw, 500px\" /></figure>\n</div>\n\n\n<p>هاي كورة &#8211; تعرض نيمار دا سيلفا لإصابة جديدة قد تمنعه من الانضمام لمنتخب البرازيل المشارك في كأس العالم 2026.</p>\n\n\n\n<p>وذكرت صحيفة ليكيب أن نيمار أصيب في ركبته اليسرى، وقد تقرر أن يخضع لعملية جراحية في الغضروف الهلالي.</p>\n\n\n\n<p> وأكدت الصحيفة الفرنسية أن غياب نجم سانتوس قد يمتد إلى شهر فبراير القادم، وهو ما يثير الشكوك حول إمكانية ضمه لقائمة السيليساو المشاركة في المونديال.</p>\n",
      "image": "https://sc4.hihi2.com/wp-content/uploads/2025/12/hihi2-2025-12-22_23-10-29_805303.png?v=1766434230",
      "categories": [
        "أخبار الكرة البرازيلية",
        "نيمار"
      ]
    },
    {
      "id": "3570096",
      "title": "موقف تير شتيغن من مغادرة برشلونة",
      "link": "https://hihi2.com/2025/12/22/p3570096.html",
      "pubDate": "2025-12-22T20:06:05.000Z",
      "summary": "ها كورة- كشف الصحفي لويس روخو عن موقف الحارس الالماني مارك اندريه تير شتيغن من الرحيل عن برشلونة في فترة الانتقالات الشتوية القادمة . الصحفي أكد ان تير شتيغن لا ينوي الرحيل عن البارسا في يناير القادم وسيبقى على الأقل حتى يونيو المقبل . الحارس الالماني يتمسك بعقده مع البارسا الذي ينتهي في صيف 2028 […]",
      "description": "<div class=\"wp-block-image\">\n<figure class=\"aligncenter size-large\"><img loading=\"lazy\" decoding=\"async\" width=\"640\" height=\"426\" src=\"https://sc4.hihi2.com/wp-content/uploads/2025/12/hihi2-2025-12-22_23-04-58_723138-640x426.png?v=1766433902\" alt=\"\" class=\"wp-image-3570102\" srcset=\"https://sc4.hihi2.com/wp-content/uploads/2025/12/hihi2-2025-12-22_23-04-58_723138-640x426.png?v=1766433902 640w, https://hihi2.com/wp-content/uploads/2025/12/hihi2-2025-12-22_23-04-58_723138-300x200.png?v=1766433902 300w, https://hihi2.com/wp-content/uploads/2025/12/hihi2-2025-12-22_23-04-58_723138-200x133.png?v=1766433902 200w, https://hihi2.com/wp-content/uploads/2025/12/hihi2-2025-12-22_23-04-58_723138.png?v=1766433902 680w\" sizes=\"auto, (max-width: 640px) 100vw, 640px\" /></figure>\n</div>\n\n\n<p>ها كورة- كشف الصحفي لويس روخو عن موقف الحارس الالماني مارك اندريه تير شتيغن من الرحيل عن برشلونة في فترة الانتقالات الشتوية القادمة .</p>\n\n\n\n<p>الصحفي أكد ان تير شتيغن لا ينوي الرحيل عن البارسا في يناير القادم وسيبقى على الأقل حتى يونيو المقبل .</p>\n\n\n\n<p>الحارس الالماني يتمسك بعقده مع البارسا الذي ينتهي في صيف 2028 ، على الرغم من خروجه من حسابات المدرب فليك .</p>\n",
      "image": "https://sc4.hihi2.com/wp-content/uploads/2025/12/hihi2-2025-12-22_23-04-58_723138-640x426.png?v=1766433902",
      "categories": [
        "أخبار برشلونة",
        "البارسا",
        "الدوري الإسباني",
        "برشلونة",
        "تير شتيغن"
      ]
    },
    {
      "id": "3570093",
      "title": "غياب تأثير كانسيلو يضع الهلال في مأزق أمام الشارقة",
      "link": "https://hihi2.com/2025/12/22/p3570093.html",
      "pubDate": "2025-12-22T19:59:27.000Z",
      "summary": "هاي كورة: لم يتمكن جواو كانسيلو من ترك بصمة واضحة خلال مواجهة الهلال ضد الشارقة، حيث غاب عن الفاعلية في التحركات الهجومية والدفاعية على حد سواء، وافتقر اللاعب للدقة في التمريرات والمساندة التكتيكية، ما قلل من قدرة الفريق على استغلال الأطراف بشكل فعال وجعل الهجوم الهلالي أقل خطورة في معظم فترات اللقاء. إليكم الأرقام:",
      "description": "\n<figure class=\"wp-block-image size-large\"><img loading=\"lazy\" decoding=\"async\" width=\"640\" height=\"320\" src=\"https://hihi2.com/wp-content/uploads/2025/07/hihi2-2025-07-30_11-09-15_382544-e1753862977281-640x320.webp\" alt=\"\" class=\"wp-image-3320910\"/></figure>\n\n\n\n<p>هاي كورة: لم يتمكن جواو كانسيلو من ترك بصمة واضحة خلال مواجهة الهلال ضد الشارقة، حيث غاب عن الفاعلية في التحركات الهجومية والدفاعية على حد سواء، وافتقر اللاعب للدقة في التمريرات والمساندة التكتيكية، ما قلل من قدرة الفريق على استغلال الأطراف بشكل فعال وجعل الهجوم الهلالي أقل خطورة في معظم فترات اللقاء.</p>\n\n\n\n<p>إليكم الأرقام:</p>\n\n\n\n<figure class=\"wp-block-image size-full\"><img loading=\"lazy\" decoding=\"async\" width=\"316\" height=\"480\" src=\"https://sc1.hihi2.com/wp-content/uploads/2025/12/hihi2-2025-12-22_22-56-36_905056.png?v=1766433401\" alt=\"\" class=\"wp-image-3570095\" srcset=\"https://sc1.hihi2.com/wp-content/uploads/2025/12/hihi2-2025-12-22_22-56-36_905056.png?v=1766433401 316w, https://hihi2.com/wp-content/uploads/2025/12/hihi2-2025-12-22_22-56-36_905056-198x300.png?v=1766433401 198w, https://hihi2.com/wp-content/uploads/2025/12/hihi2-2025-12-22_22-56-36_905056-132x200.png?v=1766433401 132w\" sizes=\"auto, (max-width: 316px) 100vw, 316px\" /></figure>\n",
      "image": "https://hihi2.com/wp-content/uploads/2025/07/hihi2-2025-07-30_11-09-15_382544-e1753862977281-640x320.webp",
      "categories": [
        "أخبار الهلال السعودي",
        "ارقام كانسيلو",
        "كانسيلو",
        "نادي الهلال"
      ]
    },
    {
      "id": "3570087",
      "title": "لهذا السبب برشلونة لن يتعاقد أو يبيع أي لاعب في يناير !",
      "link": "https://hihi2.com/2025/12/22/p3570087.html",
      "pubDate": "2025-12-22T19:56:20.000Z",
      "summary": "هاي كورة : كشفت صحيفة ماركا الإسبانية ، عن موقف نادي برشلونة من سوق الانتقالات الشتوي القادم وخاصة بعد إصابة المدافع اندرياس كريستنسن . أكدت الصحيفة أن برشلونة لن يقوم بأي تعاقدات في يناير المقبل ، ولن يرحل عن صفوفه اي لاعب مثل روبرت ليفاندوفسكي ، مارك أندريه تير شتيغن ، كاسادو ، بيرنال . […]",
      "description": "\n<figure class=\"wp-block-image size-large\"><img loading=\"lazy\" decoding=\"async\" width=\"640\" height=\"360\" src=\"https://sc1.hihi2.com/wp-content/uploads/2025/12/hihi2-2025-12-22_22-55-27_890781-640x360.jpg?v=1766433328\" alt=\"\" class=\"wp-image-3570090\" srcset=\"https://sc2.hihi2.com/wp-content/uploads/2025/12/hihi2-2025-12-22_22-55-27_890781-640x360.jpg?v=1766433328 640w, https://hihi2.com/wp-content/uploads/2025/12/hihi2-2025-12-22_22-55-27_890781-300x169.jpg?v=1766433328 300w, https://hihi2.com/wp-content/uploads/2025/12/hihi2-2025-12-22_22-55-27_890781-200x113.jpg?v=1766433328 200w, https://hihi2.com/wp-content/uploads/2025/12/hihi2-2025-12-22_22-55-27_890781.jpg?v=1766433328 680w\" sizes=\"auto, (max-width: 640px) 100vw, 640px\" /></figure>\n\n\n\n<p>هاي كورة : كشفت صحيفة ماركا الإسبانية ، عن موقف نادي برشلونة من سوق الانتقالات الشتوي القادم وخاصة بعد إصابة المدافع اندرياس كريستنسن .</p>\n\n\n\n<p>أكدت الصحيفة أن برشلونة لن يقوم بأي تعاقدات في يناير المقبل ، ولن يرحل عن صفوفه اي لاعب مثل روبرت ليفاندوفسكي ، مارك أندريه تير شتيغن ، كاسادو ، بيرنال .</p>\n\n\n\n<p>وذلك بسبب عدم عودة الفريق إلى قاعدة اللعب المالي النظيف 1-1 .</p>\n",
      "image": "https://sc1.hihi2.com/wp-content/uploads/2025/12/hihi2-2025-12-22_22-55-27_890781-640x360.jpg?v=1766433328",
      "categories": [
        "أخبار الكرة الاسبانية",
        "أخبار برشلونة",
        "الدوري الاسباني",
        "الميركاتو الشتوي",
        "برشلونة"
      ]
    },
    {
      "id": "3570084",
      "title": "أداء باهت للاعب الهلال أمام الشارقة ويُسجل إنذارًا",
      "link": "https://hihi2.com/2025/12/22/p3570084.html",
      "pubDate": "2025-12-22T19:55:38.000Z",
      "summary": "هاي كورة: قدم عبد الإله المالكي أداءً باهتًا خلال مواجهة الهلال ضد الشارقة، حيث لم يترك أثرًا واضحًا في وسط الملعب، وافتقد للحيوية والدقة في التمريرات والتحركات، كما حصل على بطاقة إنذار بسبب تدخل قوي. إليكم الأرقام:",
      "description": "\n<figure class=\"wp-block-image size-full\"><img loading=\"lazy\" decoding=\"async\" width=\"552\" height=\"276\" src=\"https://sc1.hihi2.com/wp-content/uploads/2025/08/hihi2-2025-08-23_21-50-58_177994-e1755975111690.png\" alt=\"\" class=\"wp-image-3352361\" srcset=\"https://sc5.hihi2.com/wp-content/uploads/2025/08/hihi2-2025-08-23_21-50-58_177994-e1755975111690.png?v=1755975060 552w, https://hihi2.com/wp-content/uploads/2025/08/hihi2-2025-08-23_21-50-58_177994-e1755975111690-300x150.png?v=1755975060 300w, https://hihi2.com/wp-content/uploads/2025/08/hihi2-2025-08-23_21-50-58_177994-e1755975111690-200x100.png?v=1755975060 200w\" sizes=\"auto, (max-width: 552px) 100vw, 552px\" /></figure>\n\n\n\n<p>هاي كورة: قدم عبد الإله المالكي أداءً باهتًا خلال مواجهة الهلال ضد الشارقة، حيث لم يترك أثرًا واضحًا في وسط الملعب، وافتقد للحيوية والدقة في التمريرات والتحركات، كما حصل على بطاقة إنذار بسبب تدخل قوي.</p>\n\n\n\n<p>إليكم الأرقام:</p>\n\n\n\n<figure class=\"wp-block-image size-full\"><img loading=\"lazy\" decoding=\"async\" width=\"308\" height=\"475\" src=\"https://sc5.hihi2.com/wp-content/uploads/2025/12/hihi2-2025-12-22_22-52-24_492095.png?v=1766433147\" alt=\"\" class=\"wp-image-3570085\" srcset=\"https://sc1.hihi2.com/wp-content/uploads/2025/12/hihi2-2025-12-22_22-52-24_492095.png?v=1766433147 308w, https://hihi2.com/wp-content/uploads/2025/12/hihi2-2025-12-22_22-52-24_492095-195x300.png?v=1766433147 195w, https://hihi2.com/wp-content/uploads/2025/12/hihi2-2025-12-22_22-52-24_492095-130x200.png?v=1766433147 130w\" sizes=\"auto, (max-width: 308px) 100vw, 308px\" /></figure>\n",
      "image": "https://sc1.hihi2.com/wp-content/uploads/2025/08/hihi2-2025-08-23_21-50-58_177994-e1755975111690.png",
      "categories": [
        "أخبار الهلال السعودي",
        "اخبار الهلال",
        "الهلال",
        "نادي الهلال"
      ]
    },
    {
      "id": "3570061",
      "title": "صورة تفضح حكم برشلونة وفياريال",
      "link": "https://hihi2.com/2025/12/22/p3570061.html",
      "pubDate": "2025-12-22T19:55:10.000Z",
      "summary": "هاي كورة : تداول جمهور ريال مدريد خلال الـ ٢٤ ساعه الماضيه صورة تكشف سلوك التحكيم ضد ناديهم كما يتردد في الاعلام . الجمهور رصد صورتين الاولي تدخل على لامين يامال كان فيها القرار هو الطرد المباشر ونفس هذا الحكم في لقاء ريال مدريد واتليتكو لم يمنح لاعب الاتليتي اي بطاقه عندما دهس على قدم […]",
      "description": "<div class=\"wp-block-image\">\n<figure class=\"aligncenter size-large\"><img loading=\"lazy\" decoding=\"async\" width=\"480\" height=\"640\" src=\"https://sc5.hihi2.com/wp-content/uploads/2025/12/hihi2-2025-12-22_22-50-35_785097-480x640.png?v=1766433039\" alt=\"\" class=\"wp-image-3570082\" srcset=\"https://sc1.hihi2.com/wp-content/uploads/2025/12/hihi2-2025-12-22_22-50-35_785097-480x640.png?v=1766433039 480w, https://hihi2.com/wp-content/uploads/2025/12/hihi2-2025-12-22_22-50-35_785097-225x300.png?v=1766433039 225w, https://hihi2.com/wp-content/uploads/2025/12/hihi2-2025-12-22_22-50-35_785097-150x200.png?v=1766433039 150w, https://hihi2.com/wp-content/uploads/2025/12/hihi2-2025-12-22_22-50-35_785097.png?v=1766433039 720w\" sizes=\"auto, (max-width: 480px) 100vw, 480px\" /></figure>\n</div>\n\n\n<p>هاي كورة : تداول جمهور ريال مدريد خلال الـ ٢٤ ساعه الماضيه صورة تكشف سلوك التحكيم ضد ناديهم كما يتردد في الاعلام .</p>\n\n\n\n<p>الجمهور رصد صورتين الاولي تدخل على لامين يامال كان فيها القرار هو الطرد المباشر ونفس هذا الحكم في لقاء ريال مدريد واتليتكو لم يمنح لاعب الاتليتي اي بطاقه عندما دهس على قدم كارفخال .</p>\n\n\n<div class=\"wp-block-image\">\n<figure class=\"aligncenter size-large\"><img loading=\"lazy\" decoding=\"async\" width=\"512\" height=\"640\" src=\"https://sc1.hihi2.com/wp-content/uploads/2025/12/hihi2-2025-12-22_22-50-28_863278-512x640.png?v=1766433033\" alt=\"\" class=\"wp-image-3570081\" srcset=\"https://sc3.hihi2.com/wp-content/uploads/2025/12/hihi2-2025-12-22_22-50-28_863278-512x640.png?v=1766433033 512w, https://hihi2.com/wp-content/uploads/2025/12/hihi2-2025-12-22_22-50-28_863278-240x300.png?v=1766433033 240w, https://hihi2.com/wp-content/uploads/2025/12/hihi2-2025-12-22_22-50-28_863278-160x200.png?v=1766433033 160w, https://hihi2.com/wp-content/uploads/2025/12/hihi2-2025-12-22_22-50-28_863278-768x960.png?v=1766433033 768w, https://hihi2.com/wp-content/uploads/2025/12/hihi2-2025-12-22_22-50-28_863278.png?v=1766433033 959w\" sizes=\"auto, (max-width: 512px) 100vw, 512px\" /></figure>\n</div>",
      "image": "https://sc5.hihi2.com/wp-content/uploads/2025/12/hihi2-2025-12-22_22-50-35_785097-480x640.png?v=1766433039",
      "categories": [
        "أخبار برشلونة",
        "الأخبار",
        "البارسا",
        "الدوري الإسباني",
        "برشلونة",
        "فياريال"
      ]
    },
    {
      "id": "3570073",
      "title": "ثيو هيرنانديز يتألق مع الهلال أمام الشارقة",
      "link": "https://hihi2.com/2025/12/22/p3570073.html",
      "pubDate": "2025-12-22T19:51:23.000Z",
      "summary": "هاي كورة: برز ثيو هيرنانديز بشكل لافت خلال مواجهة الهلال والشارقة، حيث ساهم بفاعلية في الهجوم والدفاع على حد سواء، أظهر سرعة في التحركات ودقة في التمريرات، كما شارك في خلق فرص خطيرة للفريق، مما جعله أحد أبرز لاعبي الهلال في اللقاء ورفع من قوة الفريق على الأطراف خلال المباراة. إليكم التقييم:",
      "description": "\n<figure class=\"wp-block-image size-full\"><img loading=\"lazy\" decoding=\"async\" width=\"577\" height=\"289\" src=\"https://sc1.hihi2.com/wp-content/uploads/2025/08/hihi2-2025-08-02_19-30-07_489558-e1754152233569.png\" alt=\"\" class=\"wp-image-3324893\" srcset=\"https://sc5.hihi2.com/wp-content/uploads/2025/08/hihi2-2025-08-02_19-30-07_489558-e1754152233569.png?v=1754152209 577w, https://hihi2.com/wp-content/uploads/2025/08/hihi2-2025-08-02_19-30-07_489558-e1754152233569-300x150.png?v=1754152209 300w, https://hihi2.com/wp-content/uploads/2025/08/hihi2-2025-08-02_19-30-07_489558-e1754152233569-200x100.png?v=1754152209 200w\" sizes=\"auto, (max-width: 577px) 100vw, 577px\" /></figure>\n\n\n\n<p>هاي كورة: برز ثيو هيرنانديز بشكل لافت خلال مواجهة الهلال والشارقة، حيث ساهم بفاعلية في الهجوم والدفاع على حد سواء، أظهر سرعة في التحركات ودقة في التمريرات، كما شارك في خلق فرص خطيرة للفريق، مما جعله أحد أبرز لاعبي الهلال في اللقاء ورفع من قوة الفريق على الأطراف خلال المباراة.</p>\n\n\n\n<p>إليكم التقييم:</p>\n\n\n\n<figure class=\"wp-block-image size-full\"><img loading=\"lazy\" decoding=\"async\" width=\"304\" height=\"472\" src=\"https://sc3.hihi2.com/wp-content/uploads/2025/12/hihi2-2025-12-22_22-48-47_627058.png?v=1766432931\" alt=\"\" class=\"wp-image-3570080\" srcset=\"https://sc3.hihi2.com/wp-content/uploads/2025/12/hihi2-2025-12-22_22-48-47_627058.png?v=1766432931 304w, https://hihi2.com/wp-content/uploads/2025/12/hihi2-2025-12-22_22-48-47_627058-193x300.png?v=1766432931 193w, https://hihi2.com/wp-content/uploads/2025/12/hihi2-2025-12-22_22-48-47_627058-129x200.png?v=1766432931 129w\" sizes=\"auto, (max-width: 304px) 100vw, 304px\" /></figure>\n",
      "image": "https://sc1.hihi2.com/wp-content/uploads/2025/08/hihi2-2025-08-02_19-30-07_489558-e1754152233569.png",
      "categories": [
        "أخبار الهلال السعودي",
        "ارقام ثيو هيرنانديز",
        "ثيو هيرنانديز",
        "نادي الهلال"
      ]
    },
    {
      "id": "3570039",
      "title": "بعد انتهاء منتصف الموسم … كيف يمكن لريال مدريد ان ينجح ؟",
      "link": "https://hihi2.com/2025/12/22/p3570039.html",
      "pubDate": "2025-12-22T19:48:34.000Z",
      "summary": "هاي كورة : بعد مرور نصف الموسم بدأت ملامح الحقيقة تتضح في ريال مدريد ، وما يقدمه الفريق في ارض الملعب يقودنا إلى قناعة لا يمكن تجاهلها : 1- ريال مدريد لن ينجح بدون مهاجم رقم 9 حقيقي 2- الحل الاقرب للمنطق هو التحول إلى الخطة 2-4-4 ، الثنائية الواضحة في الهجوم ستعطي الفريق عمق […]",
      "description": "\n<figure class=\"wp-block-image size-large\"><img loading=\"lazy\" decoding=\"async\" width=\"640\" height=\"320\" src=\"https://sc5.hihi2.com/wp-content/uploads/2025/12/hihi2-2025-12-22_22-20-16_994780-640x320.jpeg?v=1766431217\" alt=\"\" class=\"wp-image-3570050\" srcset=\"https://sc1.hihi2.com/wp-content/uploads/2025/12/hihi2-2025-12-22_22-20-16_994780-640x320.jpeg?v=1766431217 640w, https://hihi2.com/wp-content/uploads/2025/12/hihi2-2025-12-22_22-20-16_994780-300x150.jpeg?v=1766431217 300w, https://hihi2.com/wp-content/uploads/2025/12/hihi2-2025-12-22_22-20-16_994780-200x100.jpeg?v=1766431217 200w, https://hihi2.com/wp-content/uploads/2025/12/hihi2-2025-12-22_22-20-16_994780.jpeg?v=1766431217 719w\" sizes=\"auto, (max-width: 640px) 100vw, 640px\" /></figure>\n\n\n\n<p>هاي كورة : بعد مرور نصف الموسم بدأت ملامح الحقيقة تتضح في ريال مدريد ، وما يقدمه الفريق في ارض الملعب يقودنا إلى قناعة لا يمكن تجاهلها :</p>\n\n\n\n<p>1- ريال مدريد لن ينجح بدون مهاجم رقم 9 حقيقي</p>\n\n\n\n<p>2- الحل الاقرب للمنطق هو التحول إلى الخطة 2-4-4 ، الثنائية الواضحة في الهجوم ستعطي الفريق عمق اكثر داخل منطقة الجزاء</p>\n\n\n\n<p>3- تجربة الثنائي مبابي مع فينيسيوس او رودريغو قد تنجح في المباريات المفتوحة ، ولكن يختفي تأثيرها تماما امام دفاع منطم وفريق متكتل</p>\n\n\n\n<p>4- خط الوسط يعاني ، لكنه سيعاني في أي خطة اخرى ، ولكن الفارق هنا هو ان وجود ثنائي محور بدني قوي مثل كامافينغا وتشواميني يقلل الضرر ، ويمنح الفريق التوازن الذي افتقده كثيرا هذا الموسم</p>\n\n\n\n<p>5- اما عن بيلينغهام فهو الرهان الحقيقي : زيادة هجومية ، دخول للعمق ، ضغط عالي ، مساندة دفاعية</p>\n\n\n\n<p>6ـ غونزالو قد يبدو هو الضحية حيث يتحول الى جناح ايمن دفاعي ليغلق الجبهة ، لأن الفريق يحتاج إلى التوازن قبل أي شيء</p>\n\n\n\n<p>7- تكتيكيا ، يتحول الفريق إلى 1-5-4 دفاعيا لتحقيق التوازن ، فيما هجوميا تتغير الأدوار لخلق تفوق عددي وبناء لعب افضل ، حيث يصبح ألفارو قلب دفاع ثالث ، ويضم أرنولد للوسط ويصنع التفوق العددي ويساهم في بناء اللعب ، وينطلق بيلينغهام مع ثلاثي الهجوم</p>\n\n\n\n<p>الخلاصة : بدون مهاجم رقم 9 ، وبدون خطة 2-4-4 ، وبدون قرارات شجاعة ، سيبقى ريال مدريد يدور في حلقة مفرغة حتى نهاية الموسم .</p>\n\n\n\n<p></p>\n",
      "image": "https://sc5.hihi2.com/wp-content/uploads/2025/12/hihi2-2025-12-22_22-20-16_994780-640x320.jpeg?v=1766431217",
      "categories": [
        "أخبار الكرة الاسبانية",
        "أخبار ريال مدريد",
        "الدوري الإسباني",
        "دوري أبطال أوروبا",
        "ريال مدريد"
      ]
    },
    {
      "id": "3570037",
      "title": "صور : البرنابيو يتحول الى مدينة ألعاب …! مداخيل النادي تتضاعف",
      "link": "https://hihi2.com/2025/12/22/p3570037.html",
      "pubDate": "2025-12-22T19:48:20.000Z",
      "summary": "هاي كورة- يستعد نادي ريال مدريد لفتح ابواب البرنابيو للراغبين بالاستمتاع بالملاهي التي ستوضع بالاستاد من 24 ديسمبر حتى 31 من الشهر ذاته . مجموع التذاكر المطروحة للدخول الى البرنابيو يصل الى 76 الف تذكرة دخول مقسمة على الايام ، وسيسمح لحاملي التذاكر بالدخول في مجموعات ( 4 الآف لكل مجموعة ) مقسمة حسب الوقت […]",
      "description": "<div class=\"wp-block-image\">\n<figure class=\"aligncenter size-large\"><img loading=\"lazy\" decoding=\"async\" width=\"640\" height=\"360\" src=\"https://sc2.hihi2.com/wp-content/uploads/2025/12/hihi2-2025-12-22_22-38-55_144149-640x360.png?v=1766432339\" alt=\"\" class=\"wp-image-3570064\" srcset=\"https://sc3.hihi2.com/wp-content/uploads/2025/12/hihi2-2025-12-22_22-38-55_144149-640x360.png?v=1766432339 640w, https://hihi2.com/wp-content/uploads/2025/12/hihi2-2025-12-22_22-38-55_144149-300x169.png?v=1766432339 300w, https://hihi2.com/wp-content/uploads/2025/12/hihi2-2025-12-22_22-38-55_144149-200x113.png?v=1766432339 200w, https://hihi2.com/wp-content/uploads/2025/12/hihi2-2025-12-22_22-38-55_144149-768x432.png?v=1766432339 768w, https://hihi2.com/wp-content/uploads/2025/12/hihi2-2025-12-22_22-38-55_144149.png?v=1766432339 959w\" sizes=\"auto, (max-width: 640px) 100vw, 640px\" /></figure>\n</div>\n\n\n<p>هاي كورة- يستعد نادي ريال مدريد لفتح ابواب البرنابيو للراغبين بالاستمتاع بالملاهي التي ستوضع بالاستاد من 24 ديسمبر حتى 31 من الشهر ذاته .</p>\n\n\n\n<p>مجموع التذاكر المطروحة للدخول الى البرنابيو يصل الى 76 الف تذكرة دخول مقسمة على الايام ، وسيسمح لحاملي التذاكر بالدخول في مجموعات ( 4 الآف لكل مجموعة ) مقسمة حسب الوقت المحدد .</p>\n\n\n\n<p>وتبدأ اسعار التذاكر من 20 يورو فيما فوق ، وبحال تم بيع التذاكر كلها فمعدل دخل المناسبة سيتجاوز 1.5 مليون يورو .</p>\n",
      "image": "https://sc2.hihi2.com/wp-content/uploads/2025/12/hihi2-2025-12-22_22-38-55_144149-640x360.png?v=1766432339",
      "categories": [
        "أخبار ريال مدريد",
        "البرنابيو",
        "الدوري الإسباني",
        "الريال",
        "ريال مدريد"
      ]
    },
    {
      "id": "3570068",
      "title": "أرقام روبن نيفيز تلمع في مواجهة الهلال والشارقة",
      "link": "https://hihi2.com/2025/12/22/p3570068.html",
      "pubDate": "2025-12-22T19:47:09.000Z",
      "summary": "هاي كورة: قدم روبن نيفيز أداءً مميزًا أمام الشارقة، حيث سجل نسبة تمريرات صحيحة عالية، مع قدرة واضحة على استرجاع الكرة وقطع هجمات المنافس. إليكم الأرقام:",
      "description": "\n<figure class=\"wp-block-image size-large\"><img loading=\"lazy\" decoding=\"async\" width=\"640\" height=\"320\" src=\"https://sc5.hihi2.com/wp-content/uploads/2025/04/hihi2-2025-04-24_11-54-52_492821-e1745484907280-640x320.jpeg\" alt=\"\" class=\"wp-image-3187069\"/></figure>\n\n\n\n<p>هاي كورة: قدم روبن نيفيز أداءً مميزًا أمام الشارقة، حيث سجل نسبة تمريرات صحيحة عالية، مع قدرة واضحة على استرجاع الكرة وقطع هجمات المنافس. </p>\n\n\n\n<p><br>إليكم الأرقام:</p>\n\n\n\n<figure class=\"wp-block-image size-full\"><img loading=\"lazy\" decoding=\"async\" width=\"316\" height=\"468\" src=\"https://sc2.hihi2.com/wp-content/uploads/2025/12/hihi2-2025-12-22_22-44-25_959131.png?v=1766432669\" alt=\"\" class=\"wp-image-3570071\" srcset=\"https://sc3.hihi2.com/wp-content/uploads/2025/12/hihi2-2025-12-22_22-44-25_959131.png?v=1766432669 316w, https://hihi2.com/wp-content/uploads/2025/12/hihi2-2025-12-22_22-44-25_959131-203x300.png?v=1766432669 203w, https://hihi2.com/wp-content/uploads/2025/12/hihi2-2025-12-22_22-44-25_959131-135x200.png?v=1766432669 135w\" sizes=\"auto, (max-width: 316px) 100vw, 316px\" /></figure>\n",
      "image": "https://sc5.hihi2.com/wp-content/uploads/2025/04/hihi2-2025-04-24_11-54-52_492821-e1745484907280-640x320.jpeg",
      "categories": [
        "الأخبار"
      ]
    },
    {
      "id": "3570052",
      "title": "هل يرحل صلاح في يناير؟",
      "link": "https://hihi2.com/2025/12/22/p3570052.html",
      "pubDate": "2025-12-22T19:46:46.000Z",
      "summary": "هاي كورة – أصبح مستقبل محمد صلاح مع ليفربول يثير الجدل والتكهنات في الصحافة العالمية، حيث قالت بعض المصادر أنه سيرحل في شهر يناير المقبل، بينما نفت مصادر أخرى ذلك. وذكر موقع تيم توك أنه من غير المرجح أن يرحل صلاح عن ليفربول في وسط الموسم على الرغم من وصول عروض ضخمة له. ويمتلك النجم […]",
      "description": "<div class=\"wp-block-image\">\n<figure class=\"aligncenter size-full\"><img loading=\"lazy\" decoding=\"async\" width=\"500\" height=\"250\" src=\"https://sc3.hihi2.com/wp-content/uploads/2025/12/hihi2-2025-12-22_22-45-49_527389.jpg?v=1766432749\" alt=\"\" class=\"wp-image-3570074\" srcset=\"https://sc2.hihi2.com/wp-content/uploads/2025/12/hihi2-2025-12-22_22-45-49_527389.jpg?v=1766432749 500w, https://hihi2.com/wp-content/uploads/2025/12/hihi2-2025-12-22_22-45-49_527389-300x150.jpg?v=1766432749 300w, https://hihi2.com/wp-content/uploads/2025/12/hihi2-2025-12-22_22-45-49_527389-200x100.jpg?v=1766432749 200w\" sizes=\"auto, (max-width: 500px) 100vw, 500px\" /></figure>\n</div>\n\n\n<p>هاي كورة &#8211; أصبح مستقبل محمد صلاح مع ليفربول يثير الجدل والتكهنات في الصحافة العالمية، حيث قالت بعض المصادر أنه سيرحل في شهر يناير المقبل، بينما نفت مصادر أخرى ذلك.</p>\n\n\n\n<p>وذكر موقع تيم توك أنه من غير المرجح أن يرحل صلاح عن ليفربول في وسط الموسم على الرغم من وصول عروض ضخمة له.</p>\n\n\n\n<p>ويمتلك النجم المصري عقدًا مع بطل الدوري الإنجليزي الممتاز ممتد حتى عام 2027.</p>\n",
      "image": "https://sc3.hihi2.com/wp-content/uploads/2025/12/hihi2-2025-12-22_22-45-49_527389.jpg?v=1766432749",
      "categories": [
        "أخبار ليفربول",
        "الدوري الانجليزي",
        "ليفربول",
        "محمد صلاح"
      ]
    },
    {
      "id": "3570062",
      "title": "من يتصدر تقييمات لاعبي الهلال أمام الشارقة؟",
      "link": "https://hihi2.com/2025/12/22/p3570062.html",
      "pubDate": "2025-12-22T19:44:59.000Z",
      "summary": "هاي كورة: حصل روبن نيفيز على أعلى تقييم بين لاعبي الهلال خلال مواجهة الشارقة في دوري أبطال آسيا، بفضل أدائه المتوازن في وسط الملعب وقدرته على تنظيم الهجمات وقطع الكرات، وبرز دوره بشكل واضح في تعزيز السيطرة الهجومية والدفاعية للفريق، ما جعله اللاعب الأكثر تأثيرًا في مجريات اللقاء وحصل على إشادة واسعة من المحللين والمتابعين. […]",
      "description": "\n<figure class=\"wp-block-image size-large\"><img loading=\"lazy\" decoding=\"async\" width=\"640\" height=\"326\" src=\"https://sc4.hihi2.com/wp-content/uploads/2025/04/hihi2-2025-04-24_12-03-31_139047-640x326.jpeg\" alt=\"\" class=\"wp-image-3187083\" srcset=\"https://sc1.hihi2.com/wp-content/uploads/2025/04/hihi2-2025-04-24_12-03-31_139047-640x326.jpeg?v=1745485411 640w, https://hihi2.com/wp-content/uploads/2025/04/hihi2-2025-04-24_12-03-31_139047-300x153.jpeg?v=1745485411 300w, https://hihi2.com/wp-content/uploads/2025/04/hihi2-2025-04-24_12-03-31_139047-200x102.jpeg?v=1745485411 200w, https://hihi2.com/wp-content/uploads/2025/04/hihi2-2025-04-24_12-03-31_139047-768x391.jpeg?v=1745485411 768w, https://hihi2.com/wp-content/uploads/2025/04/hihi2-2025-04-24_12-03-31_139047.jpeg?v=1745485411 1070w\" sizes=\"auto, (max-width: 640px) 100vw, 640px\" /></figure>\n\n\n\n<p>هاي كورة: حصل روبن نيفيز على أعلى تقييم بين لاعبي الهلال خلال مواجهة الشارقة في دوري أبطال آسيا، بفضل أدائه المتوازن في وسط الملعب وقدرته على تنظيم الهجمات وقطع الكرات، وبرز دوره بشكل واضح في تعزيز السيطرة الهجومية والدفاعية للفريق، ما جعله اللاعب الأكثر تأثيرًا في مجريات اللقاء وحصل على إشادة واسعة من المحللين والمتابعين.</p>\n\n\n\n<p>إليكم التقييم:</p>\n\n\n\n<figure class=\"wp-block-image size-full\"><img loading=\"lazy\" decoding=\"async\" width=\"318\" height=\"249\" src=\"https://sc3.hihi2.com/wp-content/uploads/2025/12/hihi2-2025-12-22_22-43-00_617752.png?v=1766432584\" alt=\"\" class=\"wp-image-3570066\" srcset=\"https://sc1.hihi2.com/wp-content/uploads/2025/12/hihi2-2025-12-22_22-43-00_617752.png?v=1766432584 318w, https://hihi2.com/wp-content/uploads/2025/12/hihi2-2025-12-22_22-43-00_617752-300x235.png?v=1766432584 300w, https://hihi2.com/wp-content/uploads/2025/12/hihi2-2025-12-22_22-43-00_617752-200x157.png?v=1766432584 200w\" sizes=\"auto, (max-width: 318px) 100vw, 318px\" /></figure>\n",
      "image": "https://sc4.hihi2.com/wp-content/uploads/2025/04/hihi2-2025-04-24_12-03-31_139047-640x326.jpeg",
      "categories": [
        "أخبار الهلال السعودي",
        "الهلال",
        "مباراة الهلال",
        "نادي الهلال"
      ]
    },
    {
      "id": "3570056",
      "title": "آخر تطورات صفقة انتقال حمزة عبد الكريم الى برشلونة",
      "link": "https://hihi2.com/2025/12/22/p3570056.html",
      "pubDate": "2025-12-22T19:37:17.000Z",
      "summary": "هاي كورة- كشف الصحفي فابريزيو رومانو عن آخر تطورات تعاقد برشلونة مع حمزة عبد الكريم لاعب نادي الأهلي المصري . بحسب الصحفي ، المهاجم المصري البالغ من العمر 17 عاما يتوق للانضمام الى برشلونة ، بل ويذهب الى ابعد من ذلك ، واصفا انضمامه بـ ” الحلم ” . العقبة الرئيسية أمام انضمامه الى البلوغرانا […]",
      "description": "<div class=\"wp-block-image\">\n<figure class=\"aligncenter size-large\"><img loading=\"lazy\" decoding=\"async\" width=\"512\" height=\"640\" src=\"https://sc5.hihi2.com/wp-content/uploads/2025/12/hihi2-2025-12-22_22-36-00_072432-512x640.png?v=1766432164\" alt=\"\" class=\"wp-image-3570058\" srcset=\"https://sc5.hihi2.com/wp-content/uploads/2025/12/hihi2-2025-12-22_22-36-00_072432-512x640.png?v=1766432164 512w, https://hihi2.com/wp-content/uploads/2025/12/hihi2-2025-12-22_22-36-00_072432-240x300.png?v=1766432164 240w, https://hihi2.com/wp-content/uploads/2025/12/hihi2-2025-12-22_22-36-00_072432-160x200.png?v=1766432164 160w, https://hihi2.com/wp-content/uploads/2025/12/hihi2-2025-12-22_22-36-00_072432.png?v=1766432164 544w\" sizes=\"auto, (max-width: 512px) 100vw, 512px\" /></figure>\n</div>\n\n\n<p>هاي كورة- كشف الصحفي فابريزيو رومانو عن آخر تطورات تعاقد برشلونة مع حمزة عبد الكريم لاعب نادي الأهلي المصري .</p>\n\n\n\n<p>بحسب الصحفي ، المهاجم المصري البالغ من العمر 17 عاما يتوق للانضمام الى برشلونة ، بل ويذهب الى ابعد من ذلك ، واصفا انضمامه بـ &#8221; الحلم &#8221; .</p>\n\n\n\n<p>العقبة الرئيسية أمام انضمامه الى البلوغرانا هي نادي الأهلي الذي لا يرغب في خسارته ، فالنادي المصري يعرقل الصفقة حاليا على مستوى التفاوض بين الاندية بسبب مطالبه المالية المرتفعة لقيمة الانتقال .</p>\n",
      "image": "https://sc5.hihi2.com/wp-content/uploads/2025/12/hihi2-2025-12-22_22-36-00_072432-512x640.png?v=1766432164",
      "categories": [
        "أخبار برشلونة",
        "البارسا",
        "الدوري الإسباني",
        "برشلونة",
        "حمزة عبد الكريم"
      ]
    },
    {
      "id": "3570046",
      "title": "اكثر الفرق التي سجل عليها برشلونة في 2025",
      "link": "https://hihi2.com/2025/12/22/p3570046.html",
      "pubDate": "2025-12-22T19:26:15.000Z",
      "summary": "هاي كورة- اختتم نادي برشلونة عام 2025 بالفوز على فياريال على ملعب لا سيراميكا بهدفين نظيفين ، مساء امس الاحد ، ضمن منافسات الجولة الـ 17 في الدوري الاسباني . اكثر الفرق التي سجل عليها برشلونة اهدافا في 2025 : فالنسيا (18 هدف ) ريال مدريد (13 هدف ) اتلتيكو مدريد (12 هدف ) ريال […]",
      "description": "<div class=\"wp-block-image\">\n<figure class=\"aligncenter size-large\"><img loading=\"lazy\" decoding=\"async\" width=\"640\" height=\"426\" src=\"https://sc5.hihi2.com/wp-content/uploads/2025/12/hihi2-2025-12-22_22-25-29_188579-640x426.png?v=1766431533\" alt=\"\" class=\"wp-image-3570053\" srcset=\"https://sc4.hihi2.com/wp-content/uploads/2025/12/hihi2-2025-12-22_22-25-29_188579-640x426.png?v=1766431533 640w, https://hihi2.com/wp-content/uploads/2025/12/hihi2-2025-12-22_22-25-29_188579-300x200.png?v=1766431533 300w, https://hihi2.com/wp-content/uploads/2025/12/hihi2-2025-12-22_22-25-29_188579-200x133.png?v=1766431533 200w, https://hihi2.com/wp-content/uploads/2025/12/hihi2-2025-12-22_22-25-29_188579.png?v=1766431533 680w\" sizes=\"auto, (max-width: 640px) 100vw, 640px\" /></figure>\n</div>\n\n\n<p>هاي كورة- اختتم نادي برشلونة عام 2025 بالفوز على فياريال على ملعب لا سيراميكا بهدفين نظيفين ، مساء امس الاحد ، ضمن منافسات الجولة الـ 17 في الدوري الاسباني .</p>\n\n\n\n<p>اكثر الفرق التي سجل عليها برشلونة اهدافا في 2025 :</p>\n\n\n\n<p>فالنسيا (18 هدف )</p>\n\n\n\n<p>ريال مدريد (13 هدف )</p>\n\n\n\n<p>اتلتيكو مدريد (12 هدف ) </p>\n\n\n\n<p>ريال بيتيس (11 هدف ) .</p>\n",
      "image": "https://sc5.hihi2.com/wp-content/uploads/2025/12/hihi2-2025-12-22_22-25-29_188579-640x426.png?v=1766431533",
      "categories": [
        "أخبار برشلونة",
        "البارسا",
        "الدوري الإسباني",
        "الليغا",
        "برشلونة"
      ]
    },
    {
      "id": "3570044",
      "title": "تشكيلة منتخب مصر ضد زيمبابوي في كأس الأمم الإفريقية 2025",
      "link": "https://hihi2.com/2025/12/22/p3570044.html",
      "pubDate": "2025-12-22T19:19:35.000Z",
      "summary": "هاي كورة – أعلن حسام حسن مدرب المنتخب المصري عن التشكيلة الرسمية التي ستخوض مباراة زيمبابوي في كأس الأمم الإفريقية 2025. وسيقود النجم محمد صلاح المنتخب الوطني في لقاء الليلة، بالإضافة إلى تواجد عمر مرموش نجم مانشستر سيتي.",
      "description": "<div class=\"wp-block-image\">\n<figure class=\"aligncenter size-full\"><img loading=\"lazy\" decoding=\"async\" width=\"500\" height=\"250\" src=\"https://sc2.hihi2.com/wp-content/uploads/2025/12/hihi2-2025-12-22_22-18-30_488616.png?v=1766431110\" alt=\"\" class=\"wp-image-3570048\" srcset=\"https://sc4.hihi2.com/wp-content/uploads/2025/12/hihi2-2025-12-22_22-18-30_488616.png?v=1766431110 500w, https://hihi2.com/wp-content/uploads/2025/12/hihi2-2025-12-22_22-18-30_488616-300x150.png?v=1766431110 300w, https://hihi2.com/wp-content/uploads/2025/12/hihi2-2025-12-22_22-18-30_488616-200x100.png?v=1766431110 200w\" sizes=\"auto, (max-width: 500px) 100vw, 500px\" /></figure>\n</div>\n\n\n<p>هاي كورة &#8211; أعلن حسام حسن مدرب المنتخب المصري عن التشكيلة الرسمية التي ستخوض مباراة زيمبابوي في كأس الأمم الإفريقية 2025.</p>\n\n\n\n<p>وسيقود النجم محمد صلاح المنتخب الوطني في لقاء الليلة، بالإضافة إلى تواجد عمر مرموش نجم مانشستر سيتي.</p>\n\n\n<div class=\"wp-block-image\">\n<figure class=\"aligncenter size-large\"><img loading=\"lazy\" decoding=\"async\" width=\"512\" height=\"640\" src=\"https://sc3.hihi2.com/wp-content/uploads/2025/12/hihi2-2025-12-22_22-16-47_066292-512x640.jpeg?v=1766431007\" alt=\"\" class=\"wp-image-3570047\" srcset=\"https://sc4.hihi2.com/wp-content/uploads/2025/12/hihi2-2025-12-22_22-16-47_066292-512x640.jpeg?v=1766431007 512w, https://hihi2.com/wp-content/uploads/2025/12/hihi2-2025-12-22_22-16-47_066292-240x300.jpeg?v=1766431007 240w, https://hihi2.com/wp-content/uploads/2025/12/hihi2-2025-12-22_22-16-47_066292-160x200.jpeg?v=1766431007 160w, https://hihi2.com/wp-content/uploads/2025/12/hihi2-2025-12-22_22-16-47_066292.jpeg?v=1766431007 720w\" sizes=\"auto, (max-width: 512px) 100vw, 512px\" /></figure>\n</div>",
      "image": "https://sc2.hihi2.com/wp-content/uploads/2025/12/hihi2-2025-12-22_22-18-30_488616.png?v=1766431110",
      "categories": [
        "أخبار المنتخب المصري",
        "أخبار كأس الأمم الافريقية",
        "كأس الأمم الإفريقية",
        "منتخب زيمبابوي",
        "منتخب مصر"
      ]
    },
    {
      "id": "3570038",
      "title": "ريال مدريد يحتاج الى كارفخال",
      "link": "https://hihi2.com/2025/12/22/p3570038.html",
      "pubDate": "2025-12-22T19:15:33.000Z",
      "summary": "هاي كورة- يقترب داني كارفخال من العودة الى ريال مدريد بعد التعافي من اصابته التي تعرض لها في اكتوبر الماضي (خلع في مفصل الركبة ) . وفقا لصحيفة ماركا الاسبانية ، عودة داني كارفخال ستعد الأبرز في ريال مدريد ، ليس فقط لمهاراته كظهير أيمن بل لدوره القيادي في الفريق . غيابه اثر داخل الملعب […]",
      "description": "<div class=\"wp-block-image\">\n<figure class=\"aligncenter size-full\"><img loading=\"lazy\" decoding=\"async\" width=\"500\" height=\"252\" src=\"https://sc1.hihi2.com/wp-content/uploads/2025/12/hihi2-2025-12-22_22-14-59_364342.jpg?v=1766430899\" alt=\"\" class=\"wp-image-3570043\" srcset=\"https://sc3.hihi2.com/wp-content/uploads/2025/12/hihi2-2025-12-22_22-14-59_364342.jpg?v=1766430899 500w, https://hihi2.com/wp-content/uploads/2025/12/hihi2-2025-12-22_22-14-59_364342-300x151.jpg?v=1766430899 300w, https://hihi2.com/wp-content/uploads/2025/12/hihi2-2025-12-22_22-14-59_364342-200x101.jpg?v=1766430899 200w\" sizes=\"auto, (max-width: 500px) 100vw, 500px\" /></figure>\n</div>\n\n\n<p>هاي كورة- يقترب داني كارفخال من العودة الى ريال مدريد بعد التعافي من اصابته التي تعرض لها في اكتوبر الماضي (خلع في مفصل الركبة ) .</p>\n\n\n\n<p>وفقا لصحيفة ماركا الاسبانية ، عودة داني كارفخال ستعد الأبرز في ريال مدريد ، ليس فقط لمهاراته كظهير أيمن بل لدوره القيادي في الفريق .</p>\n\n\n\n<p>غيابه اثر داخل الملعب وخارجه وعودته تعتبر دفعة معنوية لغرفة الملابس .</p>\n\n\n\n<p>ورغم التفاؤل ، يسود الحذر لتجنب اي انتكاسة ، والقرار النهائي بشأن مشاركته في السوبر الاسباني سيحدد وفق تطور حالته البدنية دون استعجال نظرا لأهميته في مشروع النادي الجديد .</p>\n",
      "image": "https://sc1.hihi2.com/wp-content/uploads/2025/12/hihi2-2025-12-22_22-14-59_364342.jpg?v=1766430899",
      "categories": [
        "أخبار ريال مدريد",
        "الدوري الإسباني",
        "الريال",
        "ريال مدريد",
        "كارفخال"
      ]
    },
    {
      "id": "3570033",
      "title": "ما هو رأي جمهور ريال مدريد الاسباني في المهزلة التي يمر بها الفريق …! شاهد النتائج",
      "link": "https://hihi2.com/2025/12/22/p3570033.html",
      "pubDate": "2025-12-22T19:08:09.000Z",
      "summary": "هاي كورة : صحيفة ماركا اختصرت الاحداث التي يمر بها ريال مدريد بشكل مبسط وسهل جدا …! حيث وضعت تصويت للجمهور من اجل ان يحدد اساس المشاكل للفريق والمتطلبات اذ اتت النتائج على النحو التالي : مشاكل الفريق الكبرى ؟ 61% : اللاعبون 23%: الادارة 16% : تشابي الونسو . ماذا تفعل مع تشابي ؟ […]",
      "description": "<div class=\"wp-block-image\">\n<figure class=\"aligncenter size-large\"><img loading=\"lazy\" decoding=\"async\" width=\"640\" height=\"361\" src=\"https://sc5.hihi2.com/wp-content/uploads/2025/12/hihi2-2025-12-22_22-06-59_341665-640x361.jpg?v=1766430419\" alt=\"\" class=\"wp-image-3570034\" srcset=\"https://sc2.hihi2.com/wp-content/uploads/2025/12/hihi2-2025-12-22_22-06-59_341665-640x361.jpg?v=1766430419 640w, https://hihi2.com/wp-content/uploads/2025/12/hihi2-2025-12-22_22-06-59_341665-300x169.jpg?v=1766430419 300w, https://hihi2.com/wp-content/uploads/2025/12/hihi2-2025-12-22_22-06-59_341665-200x113.jpg?v=1766430419 200w, https://hihi2.com/wp-content/uploads/2025/12/hihi2-2025-12-22_22-06-59_341665-768x433.jpg?v=1766430419 768w, https://hihi2.com/wp-content/uploads/2025/12/hihi2-2025-12-22_22-06-59_341665.jpg?v=1766430419 1255w\" sizes=\"auto, (max-width: 640px) 100vw, 640px\" /></figure>\n</div>\n\n\n<p>هاي كورة : صحيفة ماركا اختصرت الاحداث التي يمر بها ريال مدريد بشكل مبسط وسهل جدا …! حيث وضعت تصويت للجمهور من اجل ان يحدد اساس المشاكل للفريق والمتطلبات اذ اتت النتائج على النحو التالي :</p>\n\n\n\n<p><strong>مشاكل الفريق الكبرى ؟</strong></p>\n\n\n\n<p>61% : اللاعبون</p>\n\n\n\n<p>23%: الادارة</p>\n\n\n\n<p>16% : تشابي الونسو .</p>\n\n\n\n<p><strong>ماذا تفعل مع تشابي ؟</strong></p>\n\n\n\n<p>76%: الاستمرار ودعمه</p>\n\n\n\n<p>14%: الاقالة فورا</p>\n\n\n\n<p>10% : انتظار السوبر .</p>\n\n\n\n<p><strong>قضية فينيسيوس ؟</strong></p>\n\n\n\n<p>86% : بيعه ، ميؤوس من وضعه .</p>\n\n\n\n<p>7% : دعمه وتجديده</p>\n\n\n\n<p>7% : المشكلة مؤقتة .</p>\n\n\n\n<p><strong>الميركاتو الشتوي ؟</strong></p>\n\n\n\n<p>79% : نعم ، الفريق يحتاج تدعيم</p>\n\n\n\n<p> 21% : لا ، الفريق بخير .</p>\n",
      "image": "https://sc5.hihi2.com/wp-content/uploads/2025/12/hihi2-2025-12-22_22-06-59_341665-640x361.jpg?v=1766430419",
      "categories": [
        "أخبار ريال مدريد",
        "الدوري الإسباني",
        "الونسو",
        "ريال مدريد",
        "فنيسيوس"
      ]
    },
    {
      "id": "3570029",
      "title": "ما هو اجمل “ سيناريو “ يحدث لجمهور ريال مدريد هذا الموسم …؟!",
      "link": "https://hihi2.com/2025/12/22/p3570029.html",
      "pubDate": "2025-12-22T18:59:49.000Z",
      "summary": "هاي كورة : على الرغم من تمرد اللاعبين والتخاذل العلني ضد المدرب الا ان المدرب نفسه خيب آمال الكثير سواء في افكاره او حتى نهجه الفني …! اي نعم تشابي اتى في البدايه بفكر واسلوب واضح بل كان صارم في كل شيء الا ان المدرب انهار مع اول تصادم امام الابقار المقدسه . السيناريو والأمل […]",
      "description": "<div class=\"wp-block-image\">\n<figure class=\"aligncenter size-full\"><img loading=\"lazy\" decoding=\"async\" width=\"500\" height=\"254\" src=\"https://sc4.hihi2.com/wp-content/uploads/2025/12/hihi2-2025-12-22_21-59-19_447793.jpg?v=1766429959\" alt=\"\" class=\"wp-image-3570030\" srcset=\"https://sc4.hihi2.com/wp-content/uploads/2025/12/hihi2-2025-12-22_21-59-19_447793.jpg?v=1766429959 500w, https://hihi2.com/wp-content/uploads/2025/12/hihi2-2025-12-22_21-59-19_447793-300x152.jpg?v=1766429959 300w, https://hihi2.com/wp-content/uploads/2025/12/hihi2-2025-12-22_21-59-19_447793-200x102.jpg?v=1766429959 200w\" sizes=\"auto, (max-width: 500px) 100vw, 500px\" /></figure>\n</div>\n\n\n<p>هاي كورة : على الرغم من تمرد اللاعبين والتخاذل العلني ضد المدرب الا ان المدرب نفسه خيب آمال الكثير سواء في افكاره او حتى نهجه الفني …! اي نعم تشابي اتى في البدايه بفكر واسلوب واضح بل كان صارم في كل شيء الا ان المدرب انهار مع اول تصادم امام الابقار المقدسه .</p>\n\n\n\n<p>السيناريو والأمل الوحيد لجمهور الريال هو التسلسل التالي :<br>١- خسارة الونسو من اتليتكو مدريد في السوبر ومغادرة البطولة<br>٢- طرد تشابي مباشره بعد الخسارة<br>٣- تعيين زين الدين زيدان مدرب مؤقت حتى الصيف<br>٤- تنظيف غرف الملابس من المخلفات والمتمردين والحديث هنا عن فيني و فالفيردي .<br>٥- تعيين مدرب جديد صارم جدا الصيف القادم.</p>\n\n\n\n<p>غالبا وبكل اسف موسم للنسيان والسبب تخبطات الادارة المترهلة ، ولو استمر فيني الموسم القادم من سابع المستحيلات يستمر الريال في تحقيق اي بطولة هذا اللاعب انتهى رسميا .</p>\n",
      "image": "https://sc4.hihi2.com/wp-content/uploads/2025/12/hihi2-2025-12-22_21-59-19_447793.jpg?v=1766429959",
      "categories": [
        "أخبار ريال مدريد",
        "الدوري الإسباني",
        "الريال",
        "الونسو",
        "ريال مدريد",
        "زيدان"
      ]
    },
    {
      "id": "3570025",
      "title": "استراحة قصيرة لـ ألونسو .. كأس السوبر نقطة الحسم",
      "link": "https://hihi2.com/2025/12/22/p3570025.html",
      "pubDate": "2025-12-22T18:56:32.000Z",
      "summary": "هاي كورة- يأخذ تشابي الونسو مدرب ريال مدريد راحة قصيرة من القلق حول مستقبله مع ريال مدريد لحين انتهاء عطلة اعياد الميلاد . وفقا للصحفي غييلرمو راي ، بقاء تشابي الونسو مع الريال ليس مضمونا تماما على الرغم من تحقيق 3 انتصارات متتالية بعد سلسلة من التعثرات . هذه النتائج منحت الونسو بعض الوقت ولكن […]",
      "description": "<div class=\"wp-block-image\">\n<figure class=\"aligncenter size-full\"><img loading=\"lazy\" decoding=\"async\" width=\"500\" height=\"249\" src=\"https://sc1.hihi2.com/wp-content/uploads/2025/12/hihi2-2025-12-22_21-55-30_791101.jpg?v=1766429730\" alt=\"\" class=\"wp-image-3570026\" srcset=\"https://sc4.hihi2.com/wp-content/uploads/2025/12/hihi2-2025-12-22_21-55-30_791101.jpg?v=1766429730 500w, https://hihi2.com/wp-content/uploads/2025/12/hihi2-2025-12-22_21-55-30_791101-300x149.jpg?v=1766429730 300w, https://hihi2.com/wp-content/uploads/2025/12/hihi2-2025-12-22_21-55-30_791101-200x100.jpg?v=1766429730 200w\" sizes=\"auto, (max-width: 500px) 100vw, 500px\" /></figure>\n</div>\n\n\n<p>هاي كورة- يأخذ تشابي الونسو مدرب ريال مدريد راحة قصيرة من القلق حول مستقبله مع ريال مدريد لحين انتهاء عطلة اعياد الميلاد .</p>\n\n\n\n<p>وفقا للصحفي غييلرمو راي ، بقاء تشابي الونسو مع الريال ليس مضمونا تماما على الرغم من تحقيق 3 انتصارات متتالية بعد سلسلة من التعثرات .</p>\n\n\n\n<p>هذه النتائج منحت الونسو بعض الوقت ولكن تركت قلق كبير داخل النادي بشان الاداء .</p>\n\n\n\n<p>ويعتبر كأس السوبر الاسباني هو نقطة الحسم في مستقبل المدرب الاسباني فإما البقاء لنهاية الموسم اوالاقالة في حال الهزيمة امام اتلتيكو مدرب ف نصف النهائي .</p>\n",
      "image": "https://sc1.hihi2.com/wp-content/uploads/2025/12/hihi2-2025-12-22_21-55-30_791101.jpg?v=1766429730",
      "categories": [
        "أخبار ريال مدريد",
        "الدوري الإسباني",
        "الريال",
        "الونسو",
        "ريال مدريد",
        "كاس السوبر الاسباني"
      ]
    },
    {
      "id": "3570001",
      "title": "هذا “ التافه “ اصبح وضعه صعب للغايه",
      "link": "https://hihi2.com/2025/12/22/p3570001.html",
      "pubDate": "2025-12-22T18:48:23.000Z",
      "summary": "هاي كورة : تقول صحيفة “ ذا اتليتك “ وهي الصحيفه المقربه جدا من البرازيلي ان فينيسيوس تحت الضغط منذ انفجاره غضبا بسبب استبداله في الكلاسيكو . وفي مباراة السبت ضد اشبيلية تعرض لصافرات استهجان متكررة من جماهير ريال مدريد التي بلغت ذروتها عند خروجه للتبديل . وردا على الصافرات ، قام فينيسيوس بتغيير صورة […]",
      "description": "<div class=\"wp-block-image\">\n<figure class=\"aligncenter size-large\"><img loading=\"lazy\" decoding=\"async\" width=\"520\" height=\"640\" src=\"https://sc2.hihi2.com/wp-content/uploads/2025/12/hihi2-2025-12-22_21-47-09_793258-520x640.png?v=1766429233\" alt=\"\" class=\"wp-image-3570021\" srcset=\"https://sc3.hihi2.com/wp-content/uploads/2025/12/hihi2-2025-12-22_21-47-09_793258-520x640.png?v=1766429233 520w, https://hihi2.com/wp-content/uploads/2025/12/hihi2-2025-12-22_21-47-09_793258-244x300.png?v=1766429233 244w, https://hihi2.com/wp-content/uploads/2025/12/hihi2-2025-12-22_21-47-09_793258-162x200.png?v=1766429233 162w, https://hihi2.com/wp-content/uploads/2025/12/hihi2-2025-12-22_21-47-09_793258.png?v=1766429233 731w\" sizes=\"auto, (max-width: 520px) 100vw, 520px\" /></figure>\n</div>\n\n\n<p>هاي كورة : تقول صحيفة “ ذا اتليتك “ وهي الصحيفه المقربه جدا من البرازيلي ان فينيسيوس تحت الضغط منذ انفجاره غضبا بسبب استبداله في الكلاسيكو .</p>\n\n\n\n<p>وفي مباراة السبت ضد اشبيلية تعرض لصافرات استهجان متكررة من جماهير ريال مدريد التي بلغت ذروتها عند خروجه للتبديل .</p>\n\n\n\n<p>وردا على الصافرات ، قام فينيسيوس بتغيير صورة ملفه الشخصي الى صورته بقميص البرازيل بدلا من مدريد ، فالبرازيلي يعلم ان وضعه معقد للغاية الآن مع الفريق .</p>\n\n\n\n<p>العبرة من هذا الخبر هو ان البرازيلي كان يستعين بتلك الصحيفه من اجل ابتزاز ريال مدريد والضغط على الادارة …! فينيسيوس كان المسرب الاول لاخبار غرف الملابس والان بعد ان ثارت عليه الجماهير اول من تخلى عنه تلك الصحيفه واصدقائه من المرتزقه قامو برميه في سلة المهملات وهربوا .</p>\n",
      "image": "https://sc2.hihi2.com/wp-content/uploads/2025/12/hihi2-2025-12-22_21-47-09_793258-520x640.png?v=1766429233",
      "categories": [
        "أخبار ريال مدريد",
        "الأخبار",
        "الدوري الإسباني",
        "الريال",
        "ريال مدريد",
        "فينيسيوس"
      ]
    },
    {
      "id": "3570016",
      "title": "إصابة كريستنسن تفتح باب الميركاتو الشتوي لبرشلونة",
      "link": "https://hihi2.com/2025/12/22/p3570016.html",
      "pubDate": "2025-12-22T18:47:31.000Z",
      "summary": "هاي كورة : وفقًا لصحيفة ذا أثلتيك ، فقد تدفع إصابة اللاعب اندرياس كريستنسن المتوقعة وغيابه لمدة أربعة أشهر برشلونة للتحرك في سوق الانتقالات الشتوي القادم . لوائح الليغا تسمح للأندية بتعويض تسجيل لاعب مصاب بلاعب جديد ، بشرط ألا يتجاوز راتبه 80٪ من راتب اللاعب المصاب . وللاستفادة من هذا الاستثناء ، يجب تصنيف […]",
      "description": "\n<figure class=\"wp-block-image size-large\"><img loading=\"lazy\" decoding=\"async\" width=\"640\" height=\"422\" src=\"https://sc5.hihi2.com/wp-content/uploads/2025/12/hihi2-2025-12-22_21-44-43_660905-640x422.jpg?v=1766429084\" alt=\"\" class=\"wp-image-3570017\" srcset=\"https://sc3.hihi2.com/wp-content/uploads/2025/12/hihi2-2025-12-22_21-44-43_660905-640x422.jpg?v=1766429084 640w, https://hihi2.com/wp-content/uploads/2025/12/hihi2-2025-12-22_21-44-43_660905-300x198.jpg?v=1766429084 300w, https://hihi2.com/wp-content/uploads/2025/12/hihi2-2025-12-22_21-44-43_660905-200x132.jpg?v=1766429084 200w, https://hihi2.com/wp-content/uploads/2025/12/hihi2-2025-12-22_21-44-43_660905-768x507.jpg?v=1766429084 768w, https://hihi2.com/wp-content/uploads/2025/12/hihi2-2025-12-22_21-44-43_660905-1536x1014.jpg?v=1766429084 1536w, https://hihi2.com/wp-content/uploads/2025/12/hihi2-2025-12-22_21-44-43_660905-2048x1352.jpg?v=1766429084 2048w\" sizes=\"auto, (max-width: 640px) 100vw, 640px\" /></figure>\n\n\n\n<p>هاي كورة : وفقًا لصحيفة ذا أثلتيك ، فقد تدفع إصابة اللاعب اندرياس كريستنسن المتوقعة وغيابه لمدة أربعة أشهر برشلونة للتحرك في سوق الانتقالات الشتوي القادم .</p>\n\n\n\n<p>لوائح الليغا تسمح للأندية بتعويض تسجيل لاعب مصاب بلاعب جديد ، بشرط ألا يتجاوز راتبه 80٪ من راتب اللاعب المصاب .</p>\n\n\n\n<p>وللاستفادة من هذا الاستثناء ، يجب تصنيف الإصابة على أنها طويلة الأمد من قبل اللجنة الطبية المستقلة التابعة لليغا .</p>\n\n\n\n<p>داخل النادي ، هناك قناعة بأن تسجيل كريستنسن سيتم تحريره، ما يفتح الباب أمام خطوة محتملة في الميركاتو .</p>\n",
      "image": "https://sc5.hihi2.com/wp-content/uploads/2025/12/hihi2-2025-12-22_21-44-43_660905-640x422.jpg?v=1766429084",
      "categories": [
        "أخبار الكرة الاسبانية",
        "أخبار برشلونة",
        "الدوري الاسباني",
        "اندرياس كريستنسن",
        "برشلونة"
      ]
    }
  ]
}